Workbook

Sheet Trim Take Off
B2: Job | C2: GREENE
B3: Customer | C3: BAR 17
B5: TAKE OFF
B6: ITEM | C6: LF | P6: Start by filling out the Job and Customer names, then fill in the information in the Take Off Table
B7: EXT WALL | C7: 150 | P7: Total lf of exterior wall (to receive base trim)
B8: INT WALL | C8: 100 | P8: Total lf of interior walls (to receive base trim)
B9: EXT DOORS | C9: 3 | P9: Total EXT Doors, double doors count as 2
B10: SLIDERS | C10: 3 | P10: Total Sliders, extra large count as 2
B11: WINDOWS | C11: 15 | P11: Total windows
B12: INT DOORS | C12: 15 | P12: Total interior swing doors
B13: POCKET DOOR | C13: 2 | P13: Total pocket, bi fold, or bi pass doors
B14: BARN DOOR/WRAPPED OPENING | C14: 1 | P14: Total barn doors or wrapped openings
B15: DOOR HEIGHT | C15: 80 | P15: Door height, if door height changes either do 2 take offs, or adjust counts proportionally
B16: STYLE | C16: CRAFTSMAN | P16: (an 80" is 84% of a 96" door, 84" door is 88% of a 96" door)
B17: PROFILE | C17: CUSTOM | P17: Style will change the LF outputs based on assumtions
B18: DRYWALL INT JAMBS | C18: NO | P18: Profile is trim profile, changes knife cost and set up fees
B19: FULL DRYWALL WRAP WINDOWS SLIDERS | C19: NO | P19: Drywall int jambs refers to places like barn doors, pocket doors, and wrapped openings
B20: SPECIES 1 | C20: Poplar | P20: Drwall wraped windows refers to the jambs on windows and sliding doors
B21: SPECIES 2 | P21: Up to 3 species can be selected to show on the final estimate
B22: SPECIES 3
B23: FINISH SIZE | C23: STANDARD | P23: Finish size will change the default sized of each piece of trim but can be overriden
P24: (See the chart on price data tab to see list of sizes)
A26: STYLE | B26: PART | C26: LF | D26: DESCRIPTION | E26: CUSTOM WIDTH | F26: CUSTOM THICKNESS | G26: STANDARD WIDTH | H26: STANDARD THICKNESS | I26: ECONOMY WIDTH | J26: ECONOMY THICKNESS | K26: UPGRADE WIDTH | L26: UPGRADED THICKNESS | M26: ACTUAL WIDTH | N26: ACTUAL THICKNESS
A27: CRAFTSMAN | B27: BASE | C27: =$C$7+$C$8*2 -> 350 | D27: =Table5[[#This Row],[STYLE]]&" "&Table5[[#This Row],[PART]] -> CRAFTSMAN BASE | G27: 5.25 | H27: 0.5 | I27: 2.25 | J27: 0.5 | K27: 7 | L27: 0.75 | M27: =IF(Table5[[#This Row],[CUSTOM WIDTH]]<>"",Table5[[#This Row],[CUSTOM WIDTH]],(IF($C$23="standard",Table5[[#This Row],[STANDARD WIDTH]],IF($C$23="economy",Table5[[#This Row],[ECONOMY WIDTH]],IF($C$23="upgraded",Table5[[#This Row],[UPGRADE WIDTH]],Table5[[#This Row],[CUSTOM WIDTH]]))))) -> 5.25 | N27: =IF(Table5[[#This Row],[CUSTOM THICKNESS]]<>"",Table5[[#This Row],[CUSTOM THICKNESS]],(IF($C$23="standard",Table5[[#This Row],[STANDARD THICKNESS]],IF($C$23="economy",Table5[[#This Row],[ECONOMY THICKNESS]],IF($C$23="upgraded",Table5[[#This Row],[UPGRADED THICKNESS]],Table5[[#This Row],[CUSTOM THICKNESS]]))))) -> 0.5 | P27: To override a default width select from the drop down on width
A28: CRAFTSMAN | B28: CASE | C28: =(2*$C$9*(ROUNDUP($C$15/12,0)))+(4*$C$12*(ROUNDUP($C$15/12,0)))+(IF($C$19="yes",0,(ROUNDUP($C$15/12,0))*2*($C$13+$C$14+$C$11))) -> 714 | D28: =Table5[[#This Row],[STYLE]]&" "&Table5[[#This Row],[PART]] -> CRAFTSMAN CASE | G28: 3.25 | H28: 0.625 | I28: 3.25 | J28: 0.625 | K28: 4.25 | L28: 1 | M28: =IF(Table5[[#This Row],[CUSTOM WIDTH]]<>"",Table5[[#This Row],[CUSTOM WIDTH]],(IF($C$23="standard",Table5[[#This Row],[STANDARD WIDTH]],IF($C$23="economy",Table5[[#This Row],[ECONOMY WIDTH]],IF($C$23="upgraded",Table5[[#This Row],[UPGRADE WIDTH]],Table5[[#This Row],[CUSTOM WIDTH]]))))) -> 3.25 | N28: =IF(Table5[[#This Row],[CUSTOM THICKNESS]]<>"",Table5[[#This Row],[CUSTOM THICKNESS]],(IF($C$23="standard",Table5[[#This Row],[STANDARD THICKNESS]],IF($C$23="economy",Table5[[#This Row],[ECONOMY THICKNESS]],IF($C$23="upgraded",Table5[[#This Row],[UPGRADED THICKNESS]],Table5[[#This Row],[CUSTOM THICKNESS]]))))) -> 0.625 | P28: To override a default on thickness enter any number between .5 and 2
A29: CRAFTSMAN | B29: HEADER | C29: =(ROUNDUP($C$15/12,0)/2)*($C$9+($C$12*2))+(IF(C19="yes",0,($C$10+$C$11+2*($C$13+$C$14)))) -> 139.5 | D29: =Table5[[#This Row],[STYLE]]&" "&Table5[[#This Row],[PART]] -> CRAFTSMAN HEADER | G29: 5.25 | H29: 0.875 | I29: 4.25 | J29: 0.75 | K29: 7 | L29: 1.125 | M29: =IF(Table5[[#This Row],[CUSTOM WIDTH]]<>"",Table5[[#This Row],[CUSTOM WIDTH]],(IF($C$23="standard",Table5[[#This Row],[STANDARD WIDTH]],IF($C$23="economy",Table5[[#This Row],[ECONOMY WIDTH]],IF($C$23="upgraded",Table5[[#This Row],[UPGRADE WIDTH]],Table5[[#This Row],[CUSTOM WIDTH]]))))) -> 5.25 | N29: =IF(Table5[[#This Row],[CUSTOM THICKNESS]]<>"",Table5[[#This Row],[CUSTOM THICKNESS]],(IF($C$23="standard",Table5[[#This Row],[STANDARD THICKNESS]],IF($C$23="economy",Table5[[#This Row],[ECONOMY THICKNESS]],IF($C$23="upgraded",Table5[[#This Row],[UPGRADED THICKNESS]],Table5[[#This Row],[CUSTOM THICKNESS]]))))) -> 0.875 | P29: Everything else in the lower table works from info provided in the take off table
A30: CRAFTSMAN | B30: INT JAMB | C30: =IF($C$18="yes",0,(ROUNDUP($C$15/12,0))*($C$13+$C$14)) -> 21 | D30: =Table5[[#This Row],[STYLE]]&" "&Table5[[#This Row],[PART]] -> CRAFTSMAN INT JAMB | G30: 4.75 | H30: 0.75 | I30: 4.75 | J30: 0.75 | K30: 4.75 | L30: 0.75 | M30: =IF(Table5[[#This Row],[CUSTOM WIDTH]]<>"",Table5[[#This Row],[CUSTOM WIDTH]],(IF($C$23="standard",Table5[[#This Row],[STANDARD WIDTH]],IF($C$23="economy",Table5[[#This Row],[ECONOMY WIDTH]],IF($C$23="upgraded",Table5[[#This Row],[UPGRADE WIDTH]],Table5[[#This Row],[CUSTOM WIDTH]]))))) -> 4.75 | N30: =IF(Table5[[#This Row],[CUSTOM THICKNESS]]<>"",Table5[[#This Row],[CUSTOM THICKNESS]],(IF($C$23="standard",Table5[[#This Row],[STANDARD THICKNESS]],IF($C$23="economy",Table5[[#This Row],[ECONOMY THICKNESS]],IF($C$23="upgraded",Table5[[#This Row],[UPGRADED THICKNESS]],Table5[[#This Row],[CUSTOM THICKNESS]]))))) -> 0.75
A31: CRAFTSMAN | B31: WINDOW JAMB | C31: =IF(C18="yes",0,((ROUNDUP(($C$15/12),0)*2)*$C$11+(ROUNDUP($C$15/12,0)*3)*$C$10)) -> 273 | D31: =Table5[[#This Row],[STYLE]]&" "&Table5[[#This Row],[PART]] -> CRAFTSMAN WINDOW JAMB | G31: 6 | H31: 0.75 | I31: 6 | J31: 0.75 | K31: 6 | L31: 0.75 | M31: =IF(Table5[[#This Row],[CUSTOM WIDTH]]<>"",Table5[[#This Row],[CUSTOM WIDTH]],(IF($C$23="standard",Table5[[#This Row],[STANDARD WIDTH]],IF($C$23="economy",Table5[[#This Row],[ECONOMY WIDTH]],IF($C$23="upgraded",Table5[[#This Row],[UPGRADE WIDTH]],Table5[[#This Row],[CUSTOM WIDTH]]))))) -> 6 | N31: =IF(Table5[[#This Row],[CUSTOM THICKNESS]]<>"",Table5[[#This Row],[CUSTOM THICKNESS]],(IF($C$23="standard",Table5[[#This Row],[STANDARD THICKNESS]],IF($C$23="economy",Table5[[#This Row],[ECONOMY THICKNESS]],IF($C$23="upgraded",Table5[[#This Row],[UPGRADED THICKNESS]],Table5[[#This Row],[CUSTOM THICKNESS]]))))) -> 0.75
A32: CRAFTSMAN | B32: SILL | C32: =C29 -> 139.5 | D32: =Table5[[#This Row],[STYLE]]&" "&Table5[[#This Row],[PART]] -> CRAFTSMAN SILL | G32: 7.25 | H32: 0.75 | I32: 7.25 | J32: 0.75 | K32: 7.25 | L32: 0.75 | M32: =IF(Table5[[#This Row],[CUSTOM WIDTH]]<>"",Table5[[#This Row],[CUSTOM WIDTH]],(IF($C$23="standard",Table5[[#This Row],[STANDARD WIDTH]],IF($C$23="economy",Table5[[#This Row],[ECONOMY WIDTH]],IF($C$23="upgraded",Table5[[#This Row],[UPGRADE WIDTH]],Table5[[#This Row],[CUSTOM WIDTH]]))))) -> 7.25 | N32: =IF(Table5[[#This Row],[CUSTOM THICKNESS]]<>"",Table5[[#This Row],[CUSTOM THICKNESS]],(IF($C$23="standard",Table5[[#This Row],[STANDARD THICKNESS]],IF($C$23="economy",Table5[[#This Row],[ECONOMY THICKNESS]],IF($C$23="upgraded",Table5[[#This Row],[UPGRADED THICKNESS]],Table5[[#This Row],[CUSTOM THICKNESS]]))))) -> 0.75
A33: CRAFTSMAN | B33: APRON | C33: =C32 -> 139.5 | D33: =Table5[[#This Row],[STYLE]]&" "&Table5[[#This Row],[PART]] -> CRAFTSMAN APRON | G33: =G27 -> 5.25 | H33: =H27 -> 0.5 | I33: =I27 -> 2.25 | J33: =J27 -> 0.5 | K33: =K27 -> 7 | L33: =L27 -> 0.75 | M33: =IF(Table5[[#This Row],[CUSTOM WIDTH]]<>"",Table5[[#This Row],[CUSTOM WIDTH]],(IF($C$23="standard",Table5[[#This Row],[STANDARD WIDTH]],IF($C$23="economy",Table5[[#This Row],[ECONOMY WIDTH]],IF($C$23="upgraded",Table5[[#This Row],[UPGRADE WIDTH]],Table5[[#This Row],[CUSTOM WIDTH]]))))) -> 5.25 | N33: =IF(Table5[[#This Row],[CUSTOM THICKNESS]]<>"",Table5[[#This Row],[CUSTOM THICKNESS]],(IF($C$23="standard",Table5[[#This Row],[STANDARD THICKNESS]],IF($C$23="economy",Table5[[#This Row],[ECONOMY THICKNESS]],IF($C$23="upgraded",Table5[[#This Row],[UPGRADED THICKNESS]],Table5[[#This Row],[CUSTOM THICKNESS]]))))) -> 0.5
A34: CRAFTSMAN PLUS | B34: DENTIL | C34: =C37*2 -> 279 | D34: =Table5[[#This Row],[STYLE]]&" "&Table5[[#This Row],[PART]] -> CRAFTSMAN PLUS DENTIL | G34: 1.5 | H34: 0.5 | I34: 0 | J34: 0 | K34: 2 | L34: 0.75 | M34: =IF(Table5[[#This Row],[CUSTOM WIDTH]]<>"",Table5[[#This Row],[CUSTOM WIDTH]],(IF($C$23="standard",Table5[[#This Row],[STANDARD WIDTH]],IF($C$23="economy",Table5[[#This Row],[ECONOMY WIDTH]],IF($C$23="upgraded",Table5[[#This Row],[UPGRADE WIDTH]],Table5[[#This Row],[CUSTOM WIDTH]]))))) -> 1.5 | N34: =IF(Table5[[#This Row],[CUSTOM THICKNESS]]<>"",Table5[[#This Row],[CUSTOM THICKNESS]],(IF($C$23="standard",Table5[[#This Row],[STANDARD THICKNESS]],IF($C$23="economy",Table5[[#This Row],[ECONOMY THICKNESS]],IF($C$23="upgraded",Table5[[#This Row],[UPGRADED THICKNESS]],Table5[[#This Row],[CUSTOM THICKNESS]]))))) -> 0.5
A35: CRAFTSMAN PLUS | B35: BASE | C35: =$C$7+$C$8*2 -> 350 | D35: =Table5[[#This Row],[STYLE]]&" "&Table5[[#This Row],[PART]] -> CRAFTSMAN PLUS BASE | G35: 5.25 | H35: 0.5 | I35: 2.25 | J35: 0.5 | K35: 7 | L35: 0.75 | M35: =IF(Table5[[#This Row],[CUSTOM WIDTH]]<>"",Table5[[#This Row],[CUSTOM WIDTH]],(IF($C$23="standard",Table5[[#This Row],[STANDARD WIDTH]],IF($C$23="economy",Table5[[#This Row],[ECONOMY WIDTH]],IF($C$23="upgraded",Table5[[#This Row],[UPGRADE WIDTH]],Table5[[#This Row],[CUSTOM WIDTH]]))))) -> 5.25 | N35: =IF(Table5[[#This Row],[CUSTOM THICKNESS]]<>"",Table5[[#This Row],[CUSTOM THICKNESS]],(IF($C$23="standard",Table5[[#This Row],[STANDARD THICKNESS]],IF($C$23="economy",Table5[[#This Row],[ECONOMY THICKNESS]],IF($C$23="upgraded",Table5[[#This Row],[UPGRADED THICKNESS]],Table5[[#This Row],[CUSTOM THICKNESS]]))))) -> 0.5
A36: CRAFTSMAN PLUS | B36: CASE | C36: =(2*$C$9*(ROUNDUP($C$15/12,0)))+(4*$C$12*(ROUNDUP($C$15/12,0)))+(IF($C$19="yes",0,(ROUNDUP($C$15/12,0))*(2*($C$13+$C$14+$C$11)))) -> 714 | D36: =Table5[[#This Row],[STYLE]]&" "&Table5[[#This Row],[PART]] -> CRAFTSMAN PLUS CASE | G36: 3.25 | H36: 0.625 | I36: 2.25 | J36: 0.625 | K36: 4.25 | L36: 1 | M36: =IF(Table5[[#This Row],[CUSTOM WIDTH]]<>"",Table5[[#This Row],[CUSTOM WIDTH]],(IF($C$23="standard",Table5[[#This Row],[STANDARD WIDTH]],IF($C$23="economy",Table5[[#This Row],[ECONOMY WIDTH]],IF($C$23="upgraded",Table5[[#This Row],[UPGRADE WIDTH]],Table5[[#This Row],[CUSTOM WIDTH]]))))) -> 3.25 | N36: =IF(Table5[[#This Row],[CUSTOM THICKNESS]]<>"",Table5[[#This Row],[CUSTOM THICKNESS]],(IF($C$23="standard",Table5[[#This Row],[STANDARD THICKNESS]],IF($C$23="economy",Table5[[#This Row],[ECONOMY THICKNESS]],IF($C$23="upgraded",Table5[[#This Row],[UPGRADED THICKNESS]],Table5[[#This Row],[CUSTOM THICKNESS]]))))) -> 0.625
A37: CRAFTSMAN PLUS | B37: HEADER | C37: =(ROUNDUP($C$15/12,0)/2)*($C$9+($C$12*2))+(IF(C32="yes",0,($C$10+$C$11+2*($C$13+$C$14)))) -> 139.5 | D37: =Table5[[#This Row],[STYLE]]&" "&Table5[[#This Row],[PART]] -> CRAFTSMAN PLUS HEADER | G37: 5.25 | H37: 0.875 | I37: 4.25 | J37: 0.75 | K37: 7 | L37: 1.125 | M37: =IF(Table5[[#This Row],[CUSTOM WIDTH]]<>"",Table5[[#This Row],[CUSTOM WIDTH]],(IF($C$23="standard",Table5[[#This Row],[STANDARD WIDTH]],IF($C$23="economy",Table5[[#This Row],[ECONOMY WIDTH]],IF($C$23="upgraded",Table5[[#This Row],[UPGRADE WIDTH]],Table5[[#This Row],[CUSTOM WIDTH]]))))) -> 5.25 | N37: =IF(Table5[[#This Row],[CUSTOM THICKNESS]]<>"",Table5[[#This Row],[CUSTOM THICKNESS]],(IF($C$23="standard",Table5[[#This Row],[STANDARD THICKNESS]],IF($C$23="economy",Table5[[#This Row],[ECONOMY THICKNESS]],IF($C$23="upgraded",Table5[[#This Row],[UPGRADED THICKNESS]],Table5[[#This Row],[CUSTOM THICKNESS]]))))) -> 0.875
A38: CRAFTSMAN PLUS | B38: INT JAMB | C38: =IF($C$18="yes",0,(ROUNDUP($C$15/12,0))*($C$13+$C$14)) -> 21 | D38: =Table5[[#This Row],[STYLE]]&" "&Table5[[#This Row],[PART]] -> CRAFTSMAN PLUS INT JAMB | G38: 4.75 | H38: 0.75 | I38: 4.75 | J38: 0.75 | K38: 4.75 | L38: 0.75 | M38: =IF(Table5[[#This Row],[CUSTOM WIDTH]]<>"",Table5[[#This Row],[CUSTOM WIDTH]],(IF($C$23="standard",Table5[[#This Row],[STANDARD WIDTH]],IF($C$23="economy",Table5[[#This Row],[ECONOMY WIDTH]],IF($C$23="upgraded",Table5[[#This Row],[UPGRADE WIDTH]],Table5[[#This Row],[CUSTOM WIDTH]]))))) -> 4.75 | N38: =IF(Table5[[#This Row],[CUSTOM THICKNESS]]<>"",Table5[[#This Row],[CUSTOM THICKNESS]],(IF($C$23="standard",Table5[[#This Row],[STANDARD THICKNESS]],IF($C$23="economy",Table5[[#This Row],[ECONOMY THICKNESS]],IF($C$23="upgraded",Table5[[#This Row],[UPGRADED THICKNESS]],Table5[[#This Row],[CUSTOM THICKNESS]]))))) -> 0.75
A39: CRAFTSMAN PLUS | B39: WINDOW JAMB | C39: =IF(C31="yes",0,((ROUNDUP(($C$15/12),0)*2)*$C$11+(ROUNDUP($C$15/12,0)*3)*$C$10)) -> 273 | D39: =Table5[[#This Row],[STYLE]]&" "&Table5[[#This Row],[PART]] -> CRAFTSMAN PLUS WINDOW JAMB | G39: 6 | H39: 0.75 | I39: 6 | J39: 0.75 | K39: 6 | L39: 0.75 | M39: =IF(Table5[[#This Row],[CUSTOM WIDTH]]<>"",Table5[[#This Row],[CUSTOM WIDTH]],(IF($C$23="standard",Table5[[#This Row],[STANDARD WIDTH]],IF($C$23="economy",Table5[[#This Row],[ECONOMY WIDTH]],IF($C$23="upgraded",Table5[[#This Row],[UPGRADE WIDTH]],Table5[[#This Row],[CUSTOM WIDTH]]))))) -> 6 | N39: =IF(Table5[[#This Row],[CUSTOM THICKNESS]]<>"",Table5[[#This Row],[CUSTOM THICKNESS]],(IF($C$23="standard",Table5[[#This Row],[STANDARD THICKNESS]],IF($C$23="economy",Table5[[#This Row],[ECONOMY THICKNESS]],IF($C$23="upgraded",Table5[[#This Row],[UPGRADED THICKNESS]],Table5[[#This Row],[CUSTOM THICKNESS]]))))) -> 0.75
A40: CRAFTSMAN PLUS | B40: SILL | C40: =C37 -> 139.5 | D40: =Table5[[#This Row],[STYLE]]&" "&Table5[[#This Row],[PART]] -> CRAFTSMAN PLUS SILL | G40: 7.25 | H40: 0.75 | I40: 7.25 | J40: 0.75 | K40: 7.25 | L40: 0.75 | M40: =IF(Table5[[#This Row],[CUSTOM WIDTH]]<>"",Table5[[#This Row],[CUSTOM WIDTH]],(IF($C$23="standard",Table5[[#This Row],[STANDARD WIDTH]],IF($C$23="economy",Table5[[#This Row],[ECONOMY WIDTH]],IF($C$23="upgraded",Table5[[#This Row],[UPGRADE WIDTH]],Table5[[#This Row],[CUSTOM WIDTH]]))))) -> 7.25 | N40: =IF(Table5[[#This Row],[CUSTOM THICKNESS]]<>"",Table5[[#This Row],[CUSTOM THICKNESS]],(IF($C$23="standard",Table5[[#This Row],[STANDARD THICKNESS]],IF($C$23="economy",Table5[[#This Row],[ECONOMY THICKNESS]],IF($C$23="upgraded",Table5[[#This Row],[UPGRADED THICKNESS]],Table5[[#This Row],[CUSTOM THICKNESS]]))))) -> 0.75
A41: CRAFTSMAN PLUS | B41: APRON | C41: =C37 -> 139.5 | D41: =Table5[[#This Row],[STYLE]]&" "&Table5[[#This Row],[PART]] -> CRAFTSMAN PLUS APRON | G41: =G35 -> 5.25 | H41: =H35 -> 0.5 | I41: =I35 -> 2.25 | J41: =J35 -> 0.5 | K41: =K35 -> 7 | L41: =L35 -> 0.75 | M41: =IF(Table5[[#This Row],[CUSTOM WIDTH]]<>"",Table5[[#This Row],[CUSTOM WIDTH]],(IF($C$23="standard",Table5[[#This Row],[STANDARD WIDTH]],IF($C$23="economy",Table5[[#This Row],[ECONOMY WIDTH]],IF($C$23="upgraded",Table5[[#This Row],[UPGRADE WIDTH]],Table5[[#This Row],[CUSTOM WIDTH]]))))) -> 5.25 | N41: =IF(Table5[[#This Row],[CUSTOM THICKNESS]]<>"",Table5[[#This Row],[CUSTOM THICKNESS]],(IF($C$23="standard",Table5[[#This Row],[STANDARD THICKNESS]],IF($C$23="economy",Table5[[#This Row],[ECONOMY THICKNESS]],IF($C$23="upgraded",Table5[[#This Row],[UPGRADED THICKNESS]],Table5[[#This Row],[CUSTOM THICKNESS]]))))) -> 0.5
A42: MITERED | B42: BASE | C42: =$C$7+$C$8*2 -> 350 | D42: =Table5[[#This Row],[STYLE]]&" "&Table5[[#This Row],[PART]] -> MITERED BASE | G42: 5.25 | H42: 0.5 | I42: 2.25 | J42: 0.5 | K42: 7 | L42: 0.75 | M42: =IF(Table5[[#This Row],[CUSTOM WIDTH]]<>"",Table5[[#This Row],[CUSTOM WIDTH]],(IF($C$23="standard",Table5[[#This Row],[STANDARD WIDTH]],IF($C$23="economy",Table5[[#This Row],[ECONOMY WIDTH]],IF($C$23="upgraded",Table5[[#This Row],[UPGRADE WIDTH]],Table5[[#This Row],[CUSTOM WIDTH]]))))) -> 5.25 | N42: =IF(Table5[[#This Row],[CUSTOM THICKNESS]]<>"",Table5[[#This Row],[CUSTOM THICKNESS]],(IF($C$23="standard",Table5[[#This Row],[STANDARD THICKNESS]],IF($C$23="economy",Table5[[#This Row],[ECONOMY THICKNESS]],IF($C$23="upgraded",Table5[[#This Row],[UPGRADED THICKNESS]],Table5[[#This Row],[CUSTOM THICKNESS]]))))) -> 0.5
A43: MITERED | B43: CASE | C43: =(2*$C$9*(ROUNDUP($C$15/12,0)))+(4*$C$12*(ROUNDUP($C$15/12,0)))+(IF($C$19="yes",0,(ROUNDUP($C$15/12,0)*2)*(2*($C$13+$C$14+$C$11)))) -> 966 | D43: =Table5[[#This Row],[STYLE]]&" "&Table5[[#This Row],[PART]] -> MITERED CASE | G43: 3.25 | H43: 0.625 | I43: 2.25 | J43: 0.625 | K43: 4.25 | L43: 1 | M43: =IF(Table5[[#This Row],[CUSTOM WIDTH]]<>"",Table5[[#This Row],[CUSTOM WIDTH]],(IF($C$23="standard",Table5[[#This Row],[STANDARD WIDTH]],IF($C$23="economy",Table5[[#This Row],[ECONOMY WIDTH]],IF($C$23="upgraded",Table5[[#This Row],[UPGRADE WIDTH]],Table5[[#This Row],[CUSTOM WIDTH]]))))) -> 3.25 | N43: =IF(Table5[[#This Row],[CUSTOM THICKNESS]]<>"",Table5[[#This Row],[CUSTOM THICKNESS]],(IF($C$23="standard",Table5[[#This Row],[STANDARD THICKNESS]],IF($C$23="economy",Table5[[#This Row],[ECONOMY THICKNESS]],IF($C$23="upgraded",Table5[[#This Row],[UPGRADED THICKNESS]],Table5[[#This Row],[CUSTOM THICKNESS]]))))) -> 0.625
A44: MITERED | B44: INT JAMB | C44: =IF($C$18="yes",0,(ROUNDUP($C$15/12,0))*($C$13+$C$14)) -> 21 | D44: =Table5[[#This Row],[STYLE]]&" "&Table5[[#This Row],[PART]] -> MITERED INT JAMB | G44: 4.75 | H44: 0.75 | I44: 4.75 | J44: 0.75 | K44: 4.75 | L44: 0.75 | M44: =IF(Table5[[#This Row],[CUSTOM WIDTH]]<>"",Table5[[#This Row],[CUSTOM WIDTH]],(IF($C$23="standard",Table5[[#This Row],[STANDARD WIDTH]],IF($C$23="economy",Table5[[#This Row],[ECONOMY WIDTH]],IF($C$23="upgraded",Table5[[#This Row],[UPGRADE WIDTH]],Table5[[#This Row],[CUSTOM WIDTH]]))))) -> 4.75 | N44: =IF(Table5[[#This Row],[CUSTOM THICKNESS]]<>"",Table5[[#This Row],[CUSTOM THICKNESS]],(IF($C$23="standard",Table5[[#This Row],[STANDARD THICKNESS]],IF($C$23="economy",Table5[[#This Row],[ECONOMY THICKNESS]],IF($C$23="upgraded",Table5[[#This Row],[UPGRADED THICKNESS]],Table5[[#This Row],[CUSTOM THICKNESS]]))))) -> 0.75
A45: MITERED | B45: WINDOW JAMB | C45: =IF(C37="yes",0,((ROUNDUP(($C$15/12),0)*2)*$C$11+(ROUNDUP($C$15/12,0)*3)*$C$10)) -> 273 | D45: =Table5[[#This Row],[STYLE]]&" "&Table5[[#This Row],[PART]] -> MITERED WINDOW JAMB | G45: 6 | H45: 0.75 | I45: 6 | J45: 0.75 | K45: 6 | L45: 0.75 | M45: =IF(Table5[[#This Row],[CUSTOM WIDTH]]<>"",Table5[[#This Row],[CUSTOM WIDTH]],(IF($C$23="standard",Table5[[#This Row],[STANDARD WIDTH]],IF($C$23="economy",Table5[[#This Row],[ECONOMY WIDTH]],IF($C$23="upgraded",Table5[[#This Row],[UPGRADE WIDTH]],Table5[[#This Row],[CUSTOM WIDTH]]))))) -> 6 | N45: =IF(Table5[[#This Row],[CUSTOM THICKNESS]]<>"",Table5[[#This Row],[CUSTOM THICKNESS]],(IF($C$23="standard",Table5[[#This Row],[STANDARD THICKNESS]],IF($C$23="economy",Table5[[#This Row],[ECONOMY THICKNESS]],IF($C$23="upgraded",Table5[[#This Row],[UPGRADED THICKNESS]],Table5[[#This Row],[CUSTOM THICKNESS]]))))) -> 0.75

Sheet Door Schedule
A2: Line Number | B2: Type | C2: Width | D2: Height | E2: LH | F2: RH | G2: Total | H2: Width Name | I2: Height Name | J2: Door Name | K2: Door Price | L2: Finish Price | N2: We probably need to get a quote for each schedule/option that isn't on the standard price sheets, then plug them in by hand
A3: 1 | B3: =IFERROR(INDEX(Table18[Type],MATCH(Table17[[#This Row],[Line Number]],Table18[Line Number],0)),"") -> Swing | C3: =IFERROR(INDEX(Table18[Width],MATCH(Table17[[#This Row],[Line Number]],Table18[Line Number],0)),"") -> 26 | D3: =IFERROR(INDEX(Table18[Height],MATCH(Table17[[#This Row],[Line Number]],Table18[Line Number],0)),"") -> 80 | E3: =IFERROR(INDEX(Table18[LH],MATCH(Table17[[#This Row],[Line Number]],Table18[Line Number],0)),"") -> 1 | F3: =IFERROR(INDEX(Table18[RH],MATCH(Table17[[#This Row],[Line Number]],Table18[Line Number],0)),"") -> 0 | G3: =IFERROR(Table17[[#This Row],[RH]]+Table17[[#This Row],[LH]],"") -> 1 | H3: =IFERROR(INDEX(Table16[Name],MATCH(Table17[[#This Row],[Width]],Table16[Size],0)),"") -> 2' 2" | I3: =IFERROR(INDEX(Table16[Name],MATCH(Table17[[#This Row],[Height]],Table16[Size],0)),"") -> 6' 8" | J3: =IF(Table17[[#This Row],[Type]]="","",Table17[[#This Row],[Width Name]]&"/"&Table17[[#This Row],[Height Name]]&" "&Table17[[#This Row],[Type]]) -> 2' 2"/6' 8" Swing | N3: You can request a quote by coping and pasting the results in the door estimate tab then emailing Paul at Rugby
A4: 2 | B4: =IFERROR(INDEX(Table18[Type],MATCH(Table17[[#This Row],[Line Number]],Table18[Line Number],0)),"") -> Swing | C4: =IFERROR(INDEX(Table18[Width],MATCH(Table17[[#This Row],[Line Number]],Table18[Line Number],0)),"") -> 28 | D4: =IFERROR(INDEX(Table18[Height],MATCH(Table17[[#This Row],[Line Number]],Table18[Line Number],0)),"") -> 80 | E4: =IFERROR(INDEX(Table18[LH],MATCH(Table17[[#This Row],[Line Number]],Table18[Line Number],0)),"") -> 0 | F4: =IFERROR(INDEX(Table18[RH],MATCH(Table17[[#This Row],[Line Number]],Table18[Line Number],0)),"") -> 2 | G4: =IFERROR(Table17[[#This Row],[RH]]+Table17[[#This Row],[LH]],"") -> 2 | H4: =IFERROR(INDEX(Table16[Name],MATCH(Table17[[#This Row],[Width]],Table16[Size],0)),"") -> 2' 4" | I4: =IFERROR(INDEX(Table16[Name],MATCH(Table17[[#This Row],[Height]],Table16[Size],0)),"") -> 6' 8" | J4: =IF(Table17[[#This Row],[Type]]="","",Table17[[#This Row],[Width Name]]&"/"&Table17[[#This Row],[Height Name]]&" "&Table17[[#This Row],[Type]]) -> 2' 4"/6' 8" Swing
A5: 3 | B5: =IFERROR(INDEX(Table18[Type],MATCH(Table17[[#This Row],[Line Number]],Table18[Line Number],0)),"") -> Swing | C5: =IFERROR(INDEX(Table18[Width],MATCH(Table17[[#This Row],[Line Number]],Table18[Line Number],0)),"") -> 30 | D5: =IFERROR(INDEX(Table18[Height],MATCH(Table17[[#This Row],[Line Number]],Table18[Line Number],0)),"") -> 84 | E5: =IFERROR(INDEX(Table18[LH],MATCH(Table17[[#This Row],[Line Number]],Table18[Line Number],0)),"") -> 3 | F5: =IFERROR(INDEX(Table18[RH],MATCH(Table17[[#This Row],[Line Number]],Table18[Line Number],0)),"") -> 0 | G5: =IFERROR(Table17[[#This Row],[RH]]+Table17[[#This Row],[LH]],"") -> 3 | H5: =IFERROR(INDEX(Table16[Name],MATCH(Table17[[#This Row],[Width]],Table16[Size],0)),"") -> 2' 6" | I5: =IFERROR(INDEX(Table16[Name],MATCH(Table17[[#This Row],[Height]],Table16[Size],0)),"") -> 7' 0" | J5: =IF(Table17[[#This Row],[Type]]="","",Table17[[#This Row],[Width Name]]&"/"&Table17[[#This Row],[Height Name]]&" "&Table17[[#This Row],[Type]]) -> 2' 6"/7' 0" Swing
A6: 4 | B6: =IFERROR(INDEX(Table18[Type],MATCH(Table17[[#This Row],[Line Number]],Table18[Line Number],0)),"") -> Swing | C6: =IFERROR(INDEX(Table18[Width],MATCH(Table17[[#This Row],[Line Number]],Table18[Line Number],0)),"") -> 32 | D6: =IFERROR(INDEX(Table18[Height],MATCH(Table17[[#This Row],[Line Number]],Table18[Line Number],0)),"") -> 84 | E6: =IFERROR(INDEX(Table18[LH],MATCH(Table17[[#This Row],[Line Number]],Table18[Line Number],0)),"") -> 2 | F6: =IFERROR(INDEX(Table18[RH],MATCH(Table17[[#This Row],[Line Number]],Table18[Line Number],0)),"") -> 0 | G6: =IFERROR(Table17[[#This Row],[RH]]+Table17[[#This Row],[LH]],"") -> 2 | H6: =IFERROR(INDEX(Table16[Name],MATCH(Table17[[#This Row],[Width]],Table16[Size],0)),"") -> 2' 8" | I6: =IFERROR(INDEX(Table16[Name],MATCH(Table17[[#This Row],[Height]],Table16[Size],0)),"") -> 7' 0" | J6: =IF(Table17[[#This Row],[Type]]="","",Table17[[#This Row],[Width Name]]&"/"&Table17[[#This Row],[Height Name]]&" "&Table17[[#This Row],[Type]]) -> 2' 8"/7' 0" Swing
A7: 5 | B7: =IFERROR(INDEX(Table18[Type],MATCH(Table17[[#This Row],[Line Number]],Table18[Line Number],0)),"") -> Swing | C7: =IFERROR(INDEX(Table18[Width],MATCH(Table17[[#This Row],[Line Number]],Table18[Line Number],0)),"") -> 36 | D7: =IFERROR(INDEX(Table18[Height],MATCH(Table17[[#This Row],[Line Number]],Table18[Line Number],0)),"") -> 96 | E7: =IFERROR(INDEX(Table18[LH],MATCH(Table17[[#This Row],[Line Number]],Table18[Line Number],0)),"") -> 0 | F7: =IFERROR(INDEX(Table18[RH],MATCH(Table17[[#This Row],[Line Number]],Table18[Line Number],0)),"") -> 1 | G7: =IFERROR(Table17[[#This Row],[RH]]+Table17[[#This Row],[LH]],"") -> 1 | H7: =IFERROR(INDEX(Table16[Name],MATCH(Table17[[#This Row],[Width]],Table16[Size],0)),"") -> 3' 0" | I7: =IFERROR(INDEX(Table16[Name],MATCH(Table17[[#This Row],[Height]],Table16[Size],0)),"") -> 8' 0" | J7: =IF(Table17[[#This Row],[Type]]="","",Table17[[#This Row],[Width Name]]&"/"&Table17[[#This Row],[Height Name]]&" "&Table17[[#This Row],[Type]]) -> 3' 0"/8' 0" Swing
A8: 6 | B8: =IFERROR(INDEX(Table18[Type],MATCH(Table17[[#This Row],[Line Number]],Table18[Line Number],0)),"") | C8: =IFERROR(INDEX(Table18[Width],MATCH(Table17[[#This Row],[Line Number]],Table18[Line Number],0)),"") | D8: =IFERROR(INDEX(Table18[Height],MATCH(Table17[[#This Row],[Line Number]],Table18[Line Number],0)),"") | E8: =IFERROR(INDEX(Table18[LH],MATCH(Table17[[#This Row],[Line Number]],Table18[Line Number],0)),"") | F8: =IFERROR(INDEX(Table18[RH],MATCH(Table17[[#This Row],[Line Number]],Table18[Line Number],0)),"") | G8: =IFERROR(Table17[[#This Row],[RH]]+Table17[[#This Row],[LH]],"") | H8: =IFERROR(INDEX(Table16[Name],MATCH(Table17[[#This Row],[Width]],Table16[Size],0)),"") | I8: =IFERROR(INDEX(Table16[Name],MATCH(Table17[[#This Row],[Height]],Table16[Size],0)),"") | J8: =IF(Table17[[#This Row],[Type]]="","",Table17[[#This Row],[Width Name]]&"/"&Table17[[#This Row],[Height Name]]&" "&Table17[[#This Row],[Type]])
A9: 7 | B9: =IFERROR(INDEX(Table18[Type],MATCH(Table17[[#This Row],[Line Number]],Table18[Line Number],0)),"") | C9: =IFERROR(INDEX(Table18[Width],MATCH(Table17[[#This Row],[Line Number]],Table18[Line Number],0)),"") | D9: =IFERROR(INDEX(Table18[Height],MATCH(Table17[[#This Row],[Line Number]],Table18[Line Number],0)),"") | E9: =IFERROR(INDEX(Table18[LH],MATCH(Table17[[#This Row],[Line Number]],Table18[Line Number],0)),"") | F9: =IFERROR(INDEX(Table18[RH],MATCH(Table17[[#This Row],[Line Number]],Table18[Line Number],0)),"") | G9: =IFERROR(Table17[[#This Row],[RH]]+Table17[[#This Row],[LH]],"") | H9: =IFERROR(INDEX(Table16[Name],MATCH(Table17[[#This Row],[Width]],Table16[Size],0)),"") | I9: =IFERROR(INDEX(Table16[Name],MATCH(Table17[[#This Row],[Height]],Table16[Size],0)),"") | J9: =IF(Table17[[#This Row],[Type]]="","",Table17[[#This Row],[Width Name]]&"/"&Table17[[#This Row],[Height Name]]&" "&Table17[[#This Row],[Type]])
A10: 8 | B10: =IFERROR(INDEX(Table18[Type],MATCH(Table17[[#This Row],[Line Number]],Table18[Line Number],0)),"") | C10: =IFERROR(INDEX(Table18[Width],MATCH(Table17[[#This Row],[Line Number]],Table18[Line Number],0)),"") | D10: =IFERROR(INDEX(Table18[Height],MATCH(Table17[[#This Row],[Line Number]],Table18[Line Number],0)),"") | E10: =IFERROR(INDEX(Table18[LH],MATCH(Table17[[#This Row],[Line Number]],Table18[Line Number],0)),"") | F10: =IFERROR(INDEX(Table18[RH],MATCH(Table17[[#This Row],[Line Number]],Table18[Line Number],0)),"") | G10: =IFERROR(Table17[[#This Row],[RH]]+Table17[[#This Row],[LH]],"") | H10: =IFERROR(INDEX(Table16[Name],MATCH(Table17[[#This Row],[Width]],Table16[Size],0)),"") | I10: =IFERROR(INDEX(Table16[Name],MATCH(Table17[[#This Row],[Height]],Table16[Size],0)),"") | J10: =IF(Table17[[#This Row],[Type]]="","",Table17[[#This Row],[Width Name]]&"/"&Table17[[#This Row],[Height Name]]&" "&Table17[[#This Row],[Type]])
A11: 9 | B11: =IFERROR(INDEX(Table18[Type],MATCH(Table17[[#This Row],[Line Number]],Table18[Line Number],0)),"") | C11: =IFERROR(INDEX(Table18[Width],MATCH(Table17[[#This Row],[Line Number]],Table18[Line Number],0)),"") | D11: =IFERROR(INDEX(Table18[Height],MATCH(Table17[[#This Row],[Line Number]],Table18[Line Number],0)),"") | E11: =IFERROR(INDEX(Table18[LH],MATCH(Table17[[#This Row],[Line Number]],Table18[Line Number],0)),"") | F11: =IFERROR(INDEX(Table18[RH],MATCH(Table17[[#This Row],[Line Number]],Table18[Line Number],0)),"") | G11: =IFERROR(Table17[[#This Row],[RH]]+Table17[[#This Row],[LH]],"") | H11: =IFERROR(INDEX(Table16[Name],MATCH(Table17[[#This Row],[Width]],Table16[Size],0)),"") | I11: =IFERROR(INDEX(Table16[Name],MATCH(Table17[[#This Row],[Height]],Table16[Size],0)),"") | J11: =IF(Table17[[#This Row],[Type]]="","",Table17[[#This Row],[Width Name]]&"/"&Table17[[#This Row],[Height Name]]&" "&Table17[[#This Row],[Type]])
A12: 10 | B12: =IFERROR(INDEX(Table18[Type],MATCH(Table17[[#This Row],[Line Number]],Table18[Line Number],0)),"") | C12: =IFERROR(INDEX(Table18[Width],MATCH(Table17[[#This Row],[Line Number]],Table18[Line Number],0)),"") | D12: =IFERROR(INDEX(Table18[Height],MATCH(Table17[[#This Row],[Line Number]],Table18[Line Number],0)),"") | E12: =IFERROR(INDEX(Table18[LH],MATCH(Table17[[#This Row],[Line Number]],Table18[Line Number],0)),"") | F12: =IFERROR(INDEX(Table18[RH],MATCH(Table17[[#This Row],[Line Number]],Table18[Line Number],0)),"") | G12: =IFERROR(Table17[[#This Row],[RH]]+Table17[[#This Row],[LH]],"") | H12: =IFERROR(INDEX(Table16[Name],MATCH(Table17[[#This Row],[Width]],Table16[Size],0)),"") | I12: =IFERROR(INDEX(Table16[Name],MATCH(Table17[[#This Row],[Height]],Table16[Size],0)),"") | J12: =IF(Table17[[#This Row],[Type]]="","",Table17[[#This Row],[Width Name]]&"/"&Table17[[#This Row],[Height Name]]&" "&Table17[[#This Row],[Type]])
A13: 11 | B13: =IFERROR(INDEX(Table18[Type],MATCH(Table17[[#This Row],[Line Number]],Table18[Line Number],0)),"") | C13: =IFERROR(INDEX(Table18[Width],MATCH(Table17[[#This Row],[Line Number]],Table18[Line Number],0)),"") | D13: =IFERROR(INDEX(Table18[Height],MATCH(Table17[[#This Row],[Line Number]],Table18[Line Number],0)),"") | E13: =IFERROR(INDEX(Table18[LH],MATCH(Table17[[#This Row],[Line Number]],Table18[Line Number],0)),"") | F13: =IFERROR(INDEX(Table18[RH],MATCH(Table17[[#This Row],[Line Number]],Table18[Line Number],0)),"") | G13: =IFERROR(Table17[[#This Row],[RH]]+Table17[[#This Row],[LH]],"") | H13: =IFERROR(INDEX(Table16[Name],MATCH(Table17[[#This Row],[Width]],Table16[Size],0)),"") | I13: =IFERROR(INDEX(Table16[Name],MATCH(Table17[[#This Row],[Height]],Table16[Size],0)),"") | J13: =IF(Table17[[#This Row],[Type]]="","",Table17[[#This Row],[Width Name]]&"/"&Table17[[#This Row],[Height Name]]&" "&Table17[[#This Row],[Type]])
A14: 12 | B14: =IFERROR(INDEX(Table18[Type],MATCH(Table17[[#This Row],[Line Number]],Table18[Line Number],0)),"") | C14: =IFERROR(INDEX(Table18[Width],MATCH(Table17[[#This Row],[Line Number]],Table18[Line Number],0)),"") | D14: =IFERROR(INDEX(Table18[Height],MATCH(Table17[[#This Row],[Line Number]],Table18[Line Number],0)),"") | E14: =IFERROR(INDEX(Table18[LH],MATCH(Table17[[#This Row],[Line Number]],Table18[Line Number],0)),"") | F14: =IFERROR(INDEX(Table18[RH],MATCH(Table17[[#This Row],[Line Number]],Table18[Line Number],0)),"") | G14: =IFERROR(Table17[[#This Row],[RH]]+Table17[[#This Row],[LH]],"") | H14: =IFERROR(INDEX(Table16[Name],MATCH(Table17[[#This Row],[Width]],Table16[Size],0)),"") | I14: =IFERROR(INDEX(Table16[Name],MATCH(Table17[[#This Row],[Height]],Table16[Size],0)),"") | J14: =IF(Table17[[#This Row],[Type]]="","",Table17[[#This Row],[Width Name]]&"/"&Table17[[#This Row],[Height Name]]&" "&Table17[[#This Row],[Type]])
A15: 13 | B15: =IFERROR(INDEX(Table18[Type],MATCH(Table17[[#This Row],[Line Number]],Table18[Line Number],0)),"") | C15: =IFERROR(INDEX(Table18[Width],MATCH(Table17[[#This Row],[Line Number]],Table18[Line Number],0)),"") | D15: =IFERROR(INDEX(Table18[Height],MATCH(Table17[[#This Row],[Line Number]],Table18[Line Number],0)),"") | E15: =IFERROR(INDEX(Table18[LH],MATCH(Table17[[#This Row],[Line Number]],Table18[Line Number],0)),"") | F15: =IFERROR(INDEX(Table18[RH],MATCH(Table17[[#This Row],[Line Number]],Table18[Line Number],0)),"") | G15: =IFERROR(Table17[[#This Row],[RH]]+Table17[[#This Row],[LH]],"") | H15: =IFERROR(INDEX(Table16[Name],MATCH(Table17[[#This Row],[Width]],Table16[Size],0)),"") | I15: =IFERROR(INDEX(Table16[Name],MATCH(Table17[[#This Row],[Height]],Table16[Size],0)),"") | J15: =IF(Table17[[#This Row],[Type]]="","",Table17[[#This Row],[Width Name]]&"/"&Table17[[#This Row],[Height Name]]&" "&Table17[[#This Row],[Type]])
... A52: 50 | B52: =IFERROR(INDEX(Table18[Type],MATCH(Table17[[#This Row],[Line Number]],Table18[Line Number],0)),"") | C52: =IFERROR(INDEX(Table18[Width],MATCH(Table17[[#This Row],[Line Number]],Table18[Line Number],0)),"") | D52: =IFERROR(INDEX(Table18[Height],MATCH(Table17[[#This Row],[Line Number]],Table18[Line Number],0)),"") | E52: =IFERROR(INDEX(Table18[LH],MATCH(Table17[[#This Row],[Line Number]],Table18[Line Number],0)),"") | F52: =IFERROR(INDEX(Table18[RH],MATCH(Table17[[#This Row],[Line Number]],Table18[Line Number],0)),"") | G52: =IFERROR(Table17[[#This Row],[RH]]+Table17[[#This Row],[LH]],"") | H52: =IFERROR(INDEX(Table16[Name],MATCH(Table17[[#This Row],[Width]],Table16[Size],0)),"") | I52: =IFERROR(INDEX(Table16[Name],MATCH(Table17[[#This Row],[Height]],Table16[Size],0)),"") | J52: =IF(Table17[[#This Row],[Type]]="","",Table17[[#This Row],[Width Name]]&"/"&Table17[[#This Row],[Height Name]]&" "&Table17[[#This Row],[Type]])

Sheet Door Price Data
B2: Size | C2: Moulded 4-9/16 fjp | D2: Melrose Berkley 4-9/16 FJP | E2: Logan * Lincoln 4-9/16 FJP | F2: Winslow 4-9/16 FJP | G2: Birch 4-9/16 FJP | H2: Oak 4-9/16 FJP | I2: PCHB 4-9/16 FJP | K2: SLAB ONLY DEDUCT 60 ON 6/8 AND 85 ON 8/0
B3: 1-6 6-8 1-3/8 HC | C3: 108.3 | D3: 123.1 | E3: 122 | F3: 118.65 | G3: 124.1 | H3: 127.9 | I3: 90.6
B4: 1-8 6-8 1-3/8 HC | C4: 108.3 | D4: 123.1 | E4: 122 | F4: 118.65 | G4: 124.1 | H4: 127.9 | I4: 90.6
B5: 1-10 6-8 1-3/8 HC | C5: 108.3 | D5: 123.1 | E5: 122 | F5: 118.65 | G5: 124.1 | H5: 127.9 | I5: 90.6
B6: 2-0 6-8 1-3/8 HC | C6: 108.3 | D6: 123.1 | E6: 122 | F6: 118.65 | G6: 125 | H6: 127.9 | I6: 90.6
B7: 2-2 6-8 1-3/8 HC | C7: 111.9 | D7: 126.3 | E7: 122.75 | F7: 122.2 | G7: 131.25 | H7: 130.5 | I7: 93.1
B8: 2-4 6-8 1-3/8 HC | C8: 111.9 | D8: 126.3 | E8: 122.75 | F8: 122.2 | G8: 131.25 | H8: 136.3 | I8: 93.1
B9: 2-6 6-8 1-3/8 HC | C9: 111.9 | D9: 129.75 | E9: 125.25 | F9: 124.6 | G9: 131.25 | H9: 136.3 | I9: 94.35
B10: 2-8 6-8 1-3/8 HC | C10: 117.35 | D10: 133.3 | E10: 127.9 | F10: 127.26 | G10: 134.75 | H10: 139.05 | I10: 96.3
B11: 2-10 6-8 1-3/8 HC | C11: 122.25 | D11: 139.45 | E11: 132.5 | F11: 132.4 | G11: 139 | H11: 139 | I11: 98.45
B12: 3-0 6-8 1-3/8 HC | C12: 122.25 | D12: 139.45 | E12: 132.5 | F12: 132.4 | G12: 139 | H12: 144.6 | I12: 98.45
B13: 1-6 6-8 1-3/8 SC | C13: 143.46 | E13: 154.72
B14: 2-0 6-8 1-3/8 SC | C14: 143.46 | D14: 164.9 | E14: 154.72 | F14: 153.95 | G14: 134.1 | H14: 142.2 | I14: 120.8
B15: 2-4 6-8 1-3/8 SC | C15: 148.6 | D15: 171.4 | E15: 158.85 | F15: 157.2 | G15: 142.8 | H15: 151.2 | I15: 122.5
B16: 2-6 6-8 1-3/8 SC | C16: 148.9 | D16: 171.65 | E16: 158.85 | F16: 157.46 | G16: 149.4 | H16: 158 | I16: 124.1
B17: 2-8 6-8 1-3/8 SC | C17: 154.35 | D17: 178.3 | E17: 164.1 | F17: 163.24 | G17: 151.95 | H17: 160.55 | I17: 129.95
B18: 3-0 6-8 1-3/8 SC | C18: 158.15 | D18: 183.45 | E18: 168.1 | F18: 167.17 | G18: 159.1 | H18: 168.7 | I18: 131.1
B19: 2-6 6-8 1-3/4 20 Stmp | G19: 249.8 | H19: 252.4 | I19: 215.2
B20: 2-8 6-8 1-3/4 20 Stmp | C20: 251.5 | D20: 262.5 | E20: 268.6 | F20: 263.8 | G20: 254.8 | H20: 285.1 | I20: 221.6
B21: 3-0 6-8 1-3/4 20 Stmp | C21: 255.4 | D21: 266.7 | E21: 272.5 | F21: 267.7 | G21: 262.65 | H21: 266.85 | I21: 226.2
B22: 2-0 8-0 1-3/8 HC | C22: 179.3 | E22: 200.75
B23: 2-4 8-0 1-3/8 HC | C23: 185.5 | E23: 208.1
B24: 2-6 8-0 1-3/8 HC | C24: 189.5 | E24: 208.1
B25: 2-8 8-0 1-3/8 HC | C25: 192.65 | E25: 215.76
B26: 3-0 8-0 1-3/8 HC | C26: 199.75 | E26: 225.1
B27: 2-0 8-0 1-3/8 SC | C27: 224.25 | E27: 260.6 | G27: 239 | I27: 182.8
B28: 2-4 8-0 1-3/8 SC | C28: 231.1 | E28: 268.75 | G28: 250.8 | I28: 186.4
B29: 2-6 8-0 1-3/8 SC | C29: 238.8 | E29: 268.75 | G29: 250.8 | I29: 190.6
B30: 2-8 8-0 1-3/8 SC | C30: 238.8 | E30: 276.4 | G30: 255.25 | I30: 191.3
B31: 3-0 8-0 1-3/8 SC | C31: 246.6 | E31: 281.8 | G31: 264.45 | I31: 196.75
B32: 2-8 8-0 1-3/4 20 Stmp | C32: 335 | E32: 430.4
B33: 3-0 8-0 1-3/4 20 Stmp | C33: 389 | E33: 436.3 | G33: 401.25 | I33: 341.4

Sheet Door Take Off
B2: =COUNT(Table11[Line Number]) -> 2 | C2: 80" | I2: =COUNT(Table11[Line Number]) -> 2 | J2: 84" | P2: =COUNT(Table11[Line Number]) -> 2 | Q2: 96"
B3: Line Number | C3: Type | D3: Width | E3: LH | F3: RH | G3: Total | I3: Line Number | J3: Type | K3: Width | L3: LH | M3: RH | N3: Total | P3: Line Number | Q3: Type | R3: Width | S3: LH | T3: RH | U3: Total | W3: Filter out door types and sizes not in use to make filling out the table easier | Y3: Size | Z3: Name | AB3: Line Number | AC3: Type | AD3: Width | AE3: Height | AF3: LH | AG3: RH | AH3: total
B4: =IF(Table11[[#This Row],[Total]]=0,"",(MAX(B$3:B3)+1)) | C4: Swing | D4: 24 | G4: =Table11[[#This Row],[RH]]+Table11[[#This Row],[LH]] -> 0 | I4: =IF(Table1115[[#This Row],[Total]]=0,"",(MAX(I$3:I3)+1)+(MAX(Table11[Line Number]))) | J4: Swing | K4: 24 | N4: =Table1115[[#This Row],[RH]]+Table1115[[#This Row],[LH]] -> 0 | P4: =IF(Table1116[[#This Row],[Total]]=0,"",(MAX(P$3:P3)+1)+MAX(Table1115[Line Number])) | Q4: Swing | R4: 24 | U4: =Table1116[[#This Row],[RH]]+Table1116[[#This Row],[LH]] -> 0 | W4: Note each door height has its own table | Y4: 24 | Z4: =INT(Y4/12)&"' "&MOD(Y4,12)&"""" -> 2' 0" | AB4: =IF(Table18[[#This Row],[total]]=0,"",(MAX($AB$3:$AB3)+1)) | AC4: Swing | AD4: 24 | AE4: 80 | AF4: =Table11[[#This Row],[LH]] -> 0 | AG4: =Table11[[#This Row],[RH]] -> 0 | AH4: =Table18[[#This Row],[RH]]+Table18[[#This Row],[LH]] -> 0
B5: =IF(Table11[[#This Row],[Total]]=0,"",(MAX(B$3:B4)+1)) -> 1 | C5: Swing | D5: 26 | E5: 1 | G5: =Table11[[#This Row],[RH]]+Table11[[#This Row],[LH]] -> 1 | I5: =IF(Table1115[[#This Row],[Total]]=0,"",(MAX(I$3:I4)+1)+(MAX(Table11[Line Number]))) | J5: Swing | K5: 26 | N5: =Table1115[[#This Row],[RH]]+Table1115[[#This Row],[LH]] -> 0 | P5: =IF(Table1116[[#This Row],[Total]]=0,"",(MAX(P$3:P4)+1)+MAX(Table1115[Line Number])) | Q5: Swing | R5: 26 | U5: =Table1116[[#This Row],[RH]]+Table1116[[#This Row],[LH]] -> 0 | W5: Enter the number of LH in swing or RH in swing according to plans | Y5: 26 | Z5: =INT(Y5/12)&"' "&MOD(Y5,12)&"""" -> 2' 2" | AB5: =IF(Table18[[#This Row],[total]]=0,"",(MAX($AB$3:$AB4)+1)) -> 1 | AC5: Swing | AD5: 26 | AE5: 80 | AF5: =Table11[[#This Row],[LH]] -> 1 | AG5: =Table11[[#This Row],[RH]] -> 0 | AH5: =Table18[[#This Row],[RH]]+Table18[[#This Row],[LH]] -> 1
B6: =IF(Table11[[#This Row],[Total]]=0,"",(MAX(B$3:B5)+1)) -> 2 | C6: Swing | D6: 28 | F6: 2 | G6: =Table11[[#This Row],[RH]]+Table11[[#This Row],[LH]] -> 2 | I6: =IF(Table1115[[#This Row],[Total]]=0,"",(MAX(I$3:I5)+1)+(MAX(Table11[Line Number]))) | J6: Swing | K6: 28 | N6: =Table1115[[#This Row],[RH]]+Table1115[[#This Row],[LH]] -> 0 | P6: =IF(Table1116[[#This Row],[Total]]=0,"",(MAX(P$3:P5)+1)+MAX(Table1115[Line Number])) | Q6: Swing | R6: 28 | U6: =Table1116[[#This Row],[RH]]+Table1116[[#This Row],[LH]] -> 0 | Y6: 28 | Z6: =INT(Y6/12)&"' "&MOD(Y6,12)&"""" -> 2' 4" | AB6: =IF(Table18[[#This Row],[total]]=0,"",(MAX($AB$3:$AB5)+1)) -> 2 | AC6: Swing | AD6: 28 | AE6: 80 | AF6: =Table11[[#This Row],[LH]] -> 0 | AG6: =Table11[[#This Row],[RH]] -> 2 | AH6: =Table18[[#This Row],[RH]]+Table18[[#This Row],[LH]] -> 2
B7: =IF(Table11[[#This Row],[Total]]=0,"",(MAX(B$3:B6)+1)) | C7: Swing | D7: 30 | G7: =Table11[[#This Row],[RH]]+Table11[[#This Row],[LH]] -> 0 | I7: =IF(Table1115[[#This Row],[Total]]=0,"",(MAX(I$3:I6)+1)+(MAX(Table11[Line Number]))) -> 3 | J7: Swing | K7: 30 | L7: 3 | N7: =Table1115[[#This Row],[RH]]+Table1115[[#This Row],[LH]] -> 3 | P7: =IF(Table1116[[#This Row],[Total]]=0,"",(MAX(P$3:P6)+1)+MAX(Table1115[Line Number])) | Q7: Swing | R7: 30 | U7: =Table1116[[#This Row],[RH]]+Table1116[[#This Row],[LH]] -> 0 | Y7: 30 | Z7: =INT(Y7/12)&"' "&MOD(Y7,12)&"""" -> 2' 6" | AB7: =IF(Table18[[#This Row],[total]]=0,"",(MAX($AB$3:$AB6)+1)) | AC7: Swing | AD7: 30 | AE7: 80 | AF7: =Table11[[#This Row],[LH]] -> 0 | AG7: =Table11[[#This Row],[RH]] -> 0 | AH7: =Table18[[#This Row],[RH]]+Table18[[#This Row],[LH]] -> 0
B8: =IF(Table11[[#This Row],[Total]]=0,"",(MAX(B$3:B7)+1)) | C8: Swing | D8: 32 | G8: =Table11[[#This Row],[RH]]+Table11[[#This Row],[LH]] -> 0 | I8: =IF(Table1115[[#This Row],[Total]]=0,"",(MAX(I$3:I7)+1)+(MAX(Table11[Line Number]))) -> 6 | J8: Swing | K8: 32 | L8: 2 | N8: =Table1115[[#This Row],[RH]]+Table1115[[#This Row],[LH]] -> 2 | P8: =IF(Table1116[[#This Row],[Total]]=0,"",(MAX(P$3:P7)+1)+MAX(Table1115[Line Number])) | Q8: Swing | R8: 32 | U8: =Table1116[[#This Row],[RH]]+Table1116[[#This Row],[LH]] -> 0 | Y8: 32 | Z8: =INT(Y8/12)&"' "&MOD(Y8,12)&"""" -> 2' 8" | AB8: =IF(Table18[[#This Row],[total]]=0,"",(MAX($AB$3:$AB7)+1)) | AC8: Swing | AD8: 32 | AE8: 80 | AF8: =Table11[[#This Row],[LH]] -> 0 | AG8: =Table11[[#This Row],[RH]] -> 0 | AH8: =Table18[[#This Row],[RH]]+Table18[[#This Row],[LH]] -> 0
B9: =IF(Table11[[#This Row],[Total]]=0,"",(MAX(B$3:B8)+1)) | C9: Swing | D9: 34 | G9: =Table11[[#This Row],[RH]]+Table11[[#This Row],[LH]] -> 0 | I9: =IF(Table1115[[#This Row],[Total]]=0,"",(MAX(I$3:I8)+1)+(MAX(Table11[Line Number]))) | J9: Swing | K9: 34 | N9: =Table1115[[#This Row],[RH]]+Table1115[[#This Row],[LH]] -> 0 | P9: =IF(Table1116[[#This Row],[Total]]=0,"",(MAX(P$3:P8)+1)+MAX(Table1115[Line Number])) | Q9: Swing | R9: 34 | U9: =Table1116[[#This Row],[RH]]+Table1116[[#This Row],[LH]] -> 0 | Y9: 34 | Z9: =INT(Y9/12)&"' "&MOD(Y9,12)&"""" -> 2' 10" | AB9: =IF(Table18[[#This Row],[total]]=0,"",(MAX($AB$3:$AB8)+1)) | AC9: Swing | AD9: 34 | AE9: 80 | AF9: =Table11[[#This Row],[LH]] -> 0 | AG9: =Table11[[#This Row],[RH]] -> 0 | AH9: =Table18[[#This Row],[RH]]+Table18[[#This Row],[LH]] -> 0
B10: =IF(Table11[[#This Row],[Total]]=0,"",(MAX(B$3:B9)+1)) | C10: Swing | D10: 36 | G10: =Table11[[#This Row],[RH]]+Table11[[#This Row],[LH]] -> 0 | I10: =IF(Table1115[[#This Row],[Total]]=0,"",(MAX(I$3:I9)+1)+(MAX(Table11[Line Number]))) | J10: Swing | K10: 36 | N10: =Table1115[[#This Row],[RH]]+Table1115[[#This Row],[LH]] -> 0 | P10: =IF(Table1116[[#This Row],[Total]]=0,"",(MAX(P$3:P9)+1)+MAX(Table1115[Line Number])) -> 7 | Q10: Swing | R10: 36 | T10: 1 | U10: =Table1116[[#This Row],[RH]]+Table1116[[#This Row],[LH]] -> 1 | Y10: 36 | Z10: =INT(Y10/12)&"' "&MOD(Y10,12)&"""" -> 3' 0" | AB10: =IF(Table18[[#This Row],[total]]=0,"",(MAX($AB$3:$AB9)+1)) | AC10: Swing | AD10: 36 | AE10: 80 | AF10: =Table11[[#This Row],[LH]] -> 0 | AG10: =Table11[[#This Row],[RH]] -> 0 | AH10: =Table18[[#This Row],[RH]]+Table18[[#This Row],[LH]] -> 0
B11: =IF(Table11[[#This Row],[Total]]=0,"",(MAX(B$3:B10)+1)) | C11: Bi-Fold | D11: 24 | G11: =Table11[[#This Row],[RH]]+Table11[[#This Row],[LH]] -> 0 | I11: =IF(Table1115[[#This Row],[Total]]=0,"",(MAX(I$3:I10)+1)+(MAX(Table11[Line Number]))) | J11: Bi-Fold | K11: 24 | N11: =Table1115[[#This Row],[RH]]+Table1115[[#This Row],[LH]] -> 0 | P11: =IF(Table1116[[#This Row],[Total]]=0,"",(MAX(P$3:P10)+1)+MAX(Table1115[Line Number])) | Q11: Bi-Fold | R11: 24 | U11: =Table1116[[#This Row],[RH]]+Table1116[[#This Row],[LH]] -> 0 | Y11: 48 | Z11: =INT(Y11/12)&"' "&MOD(Y11,12)&"""" -> 4' 0" | AB11: =IF(Table18[[#This Row],[total]]=0,"",(MAX($AB$3:$AB10)+1)) | AC11: Bi-Fold | AD11: 24 | AE11: 80 | AF11: =Table11[[#This Row],[LH]] -> 0 | AG11: =Table11[[#This Row],[RH]] -> 0 | AH11: =Table18[[#This Row],[RH]]+Table18[[#This Row],[LH]] -> 0
B12: =IF(Table11[[#This Row],[Total]]=0,"",(MAX(B$3:B11)+1)) | C12: Bi-Fold | D12: 26 | G12: =Table11[[#This Row],[RH]]+Table11[[#This Row],[LH]] -> 0 | I12: =IF(Table1115[[#This Row],[Total]]=0,"",(MAX(I$3:I11)+1)+(MAX(Table11[Line Number]))) | J12: Bi-Fold | K12: 26 | N12: =Table1115[[#This Row],[RH]]+Table1115[[#This Row],[LH]] -> 0 | P12: =IF(Table1116[[#This Row],[Total]]=0,"",(MAX(P$3:P11)+1)+MAX(Table1115[Line Number])) | Q12: Bi-Fold | R12: 26 | U12: =Table1116[[#This Row],[RH]]+Table1116[[#This Row],[LH]] -> 0 | Y12: 60 | Z12: =INT(Y12/12)&"' "&MOD(Y12,12)&"""" -> 5' 0" | AB12: =IF(Table18[[#This Row],[total]]=0,"",(MAX($AB$3:$AB11)+1)) | AC12: Bi-Fold | AD12: 26 | AE12: 80 | AF12: =Table11[[#This Row],[LH]] -> 0 | AG12: =Table11[[#This Row],[RH]] -> 0 | AH12: =Table18[[#This Row],[RH]]+Table18[[#This Row],[LH]] -> 0
B13: =IF(Table11[[#This Row],[Total]]=0,"",(MAX(B$3:B12)+1)) | C13: Bi-Fold | D13: 28 | G13: =Table11[[#This Row],[RH]]+Table11[[#This Row],[LH]] -> 0 | I13: =IF(Table1115[[#This Row],[Total]]=0,"",(MAX(I$3:I12)+1)+(MAX(Table11[Line Number]))) | J13: Bi-Fold | K13: 28 | N13: =Table1115[[#This Row],[RH]]+Table1115[[#This Row],[LH]] -> 0 | P13: =IF(Table1116[[#This Row],[Total]]=0,"",(MAX(P$3:P12)+1)+MAX(Table1115[Line Number])) | Q13: Bi-Fold | R13: 28 | U13: =Table1116[[#This Row],[RH]]+Table1116[[#This Row],[LH]] -> 0 | Y13: 72 | Z13: =INT(Y13/12)&"' "&MOD(Y13,12)&"""" -> 6' 0" | AB13: =IF(Table18[[#This Row],[total]]=0,"",(MAX($AB$3:$AB12)+1)) | AC13: Bi-Fold | AD13: 28 | AE13: 80 | AF13: =Table11[[#This Row],[LH]] -> 0 | AG13: =Table11[[#This Row],[RH]] -> 0 | AH13: =Table18[[#This Row],[RH]]+Table18[[#This Row],[LH]] -> 0
B14: =IF(Table11[[#This Row],[Total]]=0,"",(MAX(B$3:B13)+1)) | C14: Bi-Fold | D14: 30 | G14: =Table11[[#This Row],[RH]]+Table11[[#This Row],[LH]] -> 0 | I14: =IF(Table1115[[#This Row],[Total]]=0,"",(MAX(I$3:I13)+1)+(MAX(Table11[Line Number]))) | J14: Bi-Fold | K14: 30 | N14: =Table1115[[#This Row],[RH]]+Table1115[[#This Row],[LH]] -> 0 | P14: =IF(Table1116[[#This Row],[Total]]=0,"",(MAX(P$3:P13)+1)+MAX(Table1115[Line Number])) | Q14: Bi-Fold | R14: 30 | U14: =Table1116[[#This Row],[RH]]+Table1116[[#This Row],[LH]] -> 0 | Y14: 39 | Z14: =INT(Y14/12)&"' "&MOD(Y14,12)&"""" -> 3' 3" | AB14: =IF(Table18[[#This Row],[total]]=0,"",(MAX($AB$3:$AB13)+1)) | AC14: Bi-Fold | AD14: 30 | AE14: 80 | AF14: =Table11[[#This Row],[LH]] -> 0 | AG14: =Table11[[#This Row],[RH]] -> 0 | AH14: =Table18[[#This Row],[RH]]+Table18[[#This Row],[LH]] -> 0
B15: =IF(Table11[[#This Row],[Total]]=0,"",(MAX(B$3:B14)+1)) | C15: Bi-Fold | D15: 32 | G15: =Table11[[#This Row],[RH]]+Table11[[#This Row],[LH]] -> 0 | I15: =IF(Table1115[[#This Row],[Total]]=0,"",(MAX(I$3:I14)+1)+(MAX(Table11[Line Number]))) | J15: Bi-Fold | K15: 32 | N15: =Table1115[[#This Row],[RH]]+Table1115[[#This Row],[LH]] -> 0 | P15: =IF(Table1116[[#This Row],[Total]]=0,"",(MAX(P$3:P14)+1)+MAX(Table1115[Line Number])) | Q15: Bi-Fold | R15: 32 | U15: =Table1116[[#This Row],[RH]]+Table1116[[#This Row],[LH]] -> 0 | Y15: 42 | Z15: =INT(Y15/12)&"' "&MOD(Y15,12)&"""" -> 3' 6" | AB15: =IF(Table18[[#This Row],[total]]=0,"",(MAX($AB$3:$AB14)+1)) | AC15: Bi-Fold | AD15: 32 | AE15: 80 | AF15: =Table11[[#This Row],[LH]] -> 0 | AG15: =Table11[[#This Row],[RH]] -> 0 | AH15: =Table18[[#This Row],[RH]]+Table18[[#This Row],[LH]] -> 0
B16: =IF(Table11[[#This Row],[Total]]=0,"",(MAX(B$3:B15)+1)) | C16: Bi-Fold | D16: 34 | G16: =Table11[[#This Row],[RH]]+Table11[[#This Row],[LH]] -> 0 | I16: =IF(Table1115[[#This Row],[Total]]=0,"",(MAX(I$3:I15)+1)+(MAX(Table11[Line Number]))) | J16: Bi-Fold | K16: 34 | N16: =Table1115[[#This Row],[RH]]+Table1115[[#This Row],[LH]] -> 0 | P16: =IF(Table1116[[#This Row],[Total]]=0,"",(MAX(P$3:P15)+1)+MAX(Table1115[Line Number])) | Q16: Bi-Fold | R16: 34 | U16: =Table1116[[#This Row],[RH]]+Table1116[[#This Row],[LH]] -> 0 | Y16: 45 | Z16: =INT(Y16/12)&"' "&MOD(Y16,12)&"""" -> 3' 9" | AB16: =IF(Table18[[#This Row],[total]]=0,"",(MAX($AB$3:$AB15)+1)) | AC16: Bi-Fold | AD16: 34 | AE16: 80 | AF16: =Table11[[#This Row],[LH]] -> 0 | AG16: =Table11[[#This Row],[RH]] -> 0 | AH16: =Table18[[#This Row],[RH]]+Table18[[#This Row],[LH]] -> 0
B17: =IF(Table11[[#This Row],[Total]]=0,"",(MAX(B$3:B16)+1)) | C17: Bi-Fold | D17: 36 | G17: =Table11[[#This Row],[RH]]+Table11[[#This Row],[LH]] -> 0 | I17: =IF(Table1115[[#This Row],[Total]]=0,"",(MAX(I$3:I16)+1)+(MAX(Table11[Line Number]))) | J17: Bi-Fold | K17: 36 | N17: =Table1115[[#This Row],[RH]]+Table1115[[#This Row],[LH]] -> 0 | P17: =IF(Table1116[[#This Row],[Total]]=0,"",(MAX(P$3:P16)+1)+MAX(Table1115[Line Number])) | Q17: Bi-Fold | R17: 36 | U17: =Table1116[[#This Row],[RH]]+Table1116[[#This Row],[LH]] -> 0 | Y17: 80 | Z17: =INT(Y17/12)&"' "&MOD(Y17,12)&"""" -> 6' 8" | AB17: =IF(Table18[[#This Row],[total]]=0,"",(MAX($AB$3:$AB16)+1)) | AC17: Bi-Fold | AD17: 36 | AE17: 80 | AF17: =Table11[[#This Row],[LH]] -> 0 | AG17: =Table11[[#This Row],[RH]] -> 0 | AH17: =Table18[[#This Row],[RH]]+Table18[[#This Row],[LH]] -> 0
B18: =IF(Table11[[#This Row],[Total]]=0,"",(MAX(B$3:B17)+1)) | C18: Bi-Pass | D18: 48 | G18: =Table11[[#This Row],[RH]]+Table11[[#This Row],[LH]] -> 0 | I18: =IF(Table1115[[#This Row],[Total]]=0,"",(MAX(I$3:I17)+1)+(MAX(Table11[Line Number]))) | J18: Bi-Pass | K18: 48 | N18: =Table1115[[#This Row],[RH]]+Table1115[[#This Row],[LH]] -> 0 | P18: =IF(Table1116[[#This Row],[Total]]=0,"",(MAX(P$3:P17)+1)+MAX(Table1115[Line Number])) | Q18: Bi-Pass | R18: 48 | U18: =Table1116[[#This Row],[RH]]+Table1116[[#This Row],[LH]] -> 0 | Y18: 84 | Z18: =INT(Y18/12)&"' "&MOD(Y18,12)&"""" -> 7' 0" | AB18: =IF(Table18[[#This Row],[total]]=0,"",(MAX($AB$3:$AB17)+1)) | AC18: Bi-Pass | AD18: 48 | AE18: 80 | AF18: =Table11[[#This Row],[LH]] -> 0 | AG18: =Table11[[#This Row],[RH]] -> 0 | AH18: =Table18[[#This Row],[RH]]+Table18[[#This Row],[LH]] -> 0
B19: =IF(Table11[[#This Row],[Total]]=0,"",(MAX(B$3:B18)+1)) | C19: Bi-Pass | D19: 60 | G19: =Table11[[#This Row],[RH]]+Table11[[#This Row],[LH]] -> 0 | I19: =IF(Table1115[[#This Row],[Total]]=0,"",(MAX(I$3:I18)+1)+(MAX(Table11[Line Number]))) | J19: Bi-Pass | K19: 60 | N19: =Table1115[[#This Row],[RH]]+Table1115[[#This Row],[LH]] -> 0 | P19: =IF(Table1116[[#This Row],[Total]]=0,"",(MAX(P$3:P18)+1)+MAX(Table1115[Line Number])) | Q19: Bi-Pass | R19: 60 | U19: =Table1116[[#This Row],[RH]]+Table1116[[#This Row],[LH]] -> 0 | Y19: 96 | Z19: =INT(Y19/12)&"' "&MOD(Y19,12)&"""" -> 8' 0" | AB19: =IF(Table18[[#This Row],[total]]=0,"",(MAX($AB$3:$AB18)+1)) | AC19: Bi-Pass | AD19: 60 | AE19: 80 | AF19: =Table11[[#This Row],[LH]] -> 0 | AG19: =Table11[[#This Row],[RH]] -> 0 | AH19: =Table18[[#This Row],[RH]]+Table18[[#This Row],[LH]] -> 0
B20: =IF(Table11[[#This Row],[Total]]=0,"",(MAX(B$3:B19)+1)) | C20: Bi-Pass | D20: 72 | G20: =Table11[[#This Row],[RH]]+Table11[[#This Row],[LH]] -> 0 | I20: =IF(Table1115[[#This Row],[Total]]=0,"",(MAX(I$3:I19)+1)+(MAX(Table11[Line Number]))) | J20: Bi-Pass | K20: 72 | N20: =Table1115[[#This Row],[RH]]+Table1115[[#This Row],[LH]] -> 0 | P20: =IF(Table1116[[#This Row],[Total]]=0,"",(MAX(P$3:P19)+1)+MAX(Table1115[Line Number])) | Q20: Bi-Pass | R20: 72 | U20: =Table1116[[#This Row],[RH]]+Table1116[[#This Row],[LH]] -> 0 | AB20: =IF(Table18[[#This Row],[total]]=0,"",(MAX($AB$3:$AB19)+1)) | AC20: Bi-Pass | AD20: 72 | AE20: 80 | AF20: =Table11[[#This Row],[LH]] -> 0 | AG20: =Table11[[#This Row],[RH]] -> 0 | AH20: =Table18[[#This Row],[RH]]+Table18[[#This Row],[LH]] -> 0
B21: =IF(Table11[[#This Row],[Total]]=0,"",(MAX(B$3:B20)+1)) | C21: Pocket | D21: 24 | G21: =Table11[[#This Row],[RH]]+Table11[[#This Row],[LH]] -> 0 | I21: =IF(Table1115[[#This Row],[Total]]=0,"",(MAX(I$3:I20)+1)+(MAX(Table11[Line Number]))) | J21: Pocket | K21: 24 | N21: =Table1115[[#This Row],[RH]]+Table1115[[#This Row],[LH]] -> 0 | P21: =IF(Table1116[[#This Row],[Total]]=0,"",(MAX(P$3:P20)+1)+MAX(Table1115[Line Number])) | Q21: Pocket | R21: 24 | U21: =Table1116[[#This Row],[RH]]+Table1116[[#This Row],[LH]] -> 0 | AB21: =IF(Table18[[#This Row],[total]]=0,"",(MAX($AB$3:$AB20)+1)) | AC21: Pocket | AD21: 24 | AE21: 80 | AF21: =Table11[[#This Row],[LH]] -> 0 | AG21: =Table11[[#This Row],[RH]] -> 0 | AH21: =Table18[[#This Row],[RH]]+Table18[[#This Row],[LH]] -> 0
B22: =IF(Table11[[#This Row],[Total]]=0,"",(MAX(B$3:B21)+1)) | C22: Pocket | D22: 26 | G22: =Table11[[#This Row],[RH]]+Table11[[#This Row],[LH]] -> 0 | I22: =IF(Table1115[[#This Row],[Total]]=0,"",(MAX(I$3:I21)+1)+(MAX(Table11[Line Number]))) | J22: Pocket | K22: 26 | N22: =Table1115[[#This Row],[RH]]+Table1115[[#This Row],[LH]] -> 0 | P22: =IF(Table1116[[#This Row],[Total]]=0,"",(MAX(P$3:P21)+1)+MAX(Table1115[Line Number])) | Q22: Pocket | R22: 26 | U22: =Table1116[[#This Row],[RH]]+Table1116[[#This Row],[LH]] -> 0 | AB22: =IF(Table18[[#This Row],[total]]=0,"",(MAX($AB$3:$AB21)+1)) | AC22: Pocket | AD22: 26 | AE22: 80 | AF22: =Table11[[#This Row],[LH]] -> 0 | AG22: =Table11[[#This Row],[RH]] -> 0 | AH22: =Table18[[#This Row],[RH]]+Table18[[#This Row],[LH]] -> 0
B23: =IF(Table11[[#This Row],[Total]]=0,"",(MAX(B$3:B22)+1)) | C23: Pocket | D23: 28 | G23: =Table11[[#This Row],[RH]]+Table11[[#This Row],[LH]] -> 0 | I23: =IF(Table1115[[#This Row],[Total]]=0,"",(MAX(I$3:I22)+1)+(MAX(Table11[Line Number]))) | J23: Pocket | K23: 28 | N23: =Table1115[[#This Row],[RH]]+Table1115[[#This Row],[LH]] -> 0 | P23: =IF(Table1116[[#This Row],[Total]]=0,"",(MAX(P$3:P22)+1)+MAX(Table1115[Line Number])) | Q23: Pocket | R23: 28 | U23: =Table1116[[#This Row],[RH]]+Table1116[[#This Row],[LH]] -> 0 | AB23: =IF(Table18[[#This Row],[total]]=0,"",(MAX($AB$3:$AB22)+1)) | AC23: Pocket | AD23: 28 | AE23: 80 | AF23: =Table11[[#This Row],[LH]] -> 0 | AG23: =Table11[[#This Row],[RH]] -> 0 | AH23: =Table18[[#This Row],[RH]]+Table18[[#This Row],[LH]] -> 0
B24: =IF(Table11[[#This Row],[Total]]=0,"",(MAX(B$3:B23)+1)) | C24: Pocket | D24: 30 | G24: =Table11[[#This Row],[RH]]+Table11[[#This Row],[LH]] -> 0 | I24: =IF(Table1115[[#This Row],[Total]]=0,"",(MAX(I$3:I23)+1)+(MAX(Table11[Line Number]))) | J24: Pocket | K24: 30 | N24: =Table1115[[#This Row],[RH]]+Table1115[[#This Row],[LH]] -> 0 | P24: =IF(Table1116[[#This Row],[Total]]=0,"",(MAX(P$3:P23)+1)+MAX(Table1115[Line Number])) | Q24: Pocket | R24: 30 | U24: =Table1116[[#This Row],[RH]]+Table1116[[#This Row],[LH]] -> 0 | AB24: =IF(Table18[[#This Row],[total]]=0,"",(MAX($AB$3:$AB23)+1)) | AC24: Pocket | AD24: 30 | AE24: 80 | AF24: =Table11[[#This Row],[LH]] -> 0 | AG24: =Table11[[#This Row],[RH]] -> 0 | AH24: =Table18[[#This Row],[RH]]+Table18[[#This Row],[LH]] -> 0
B25: =IF(Table11[[#This Row],[Total]]=0,"",(MAX(B$3:B24)+1)) | C25: Pocket | D25: 32 | G25: =Table11[[#This Row],[RH]]+Table11[[#This Row],[LH]] -> 0 | I25: =IF(Table1115[[#This Row],[Total]]=0,"",(MAX(I$3:I24)+1)+(MAX(Table11[Line Number]))) | J25: Pocket | K25: 32 | N25: =Table1115[[#This Row],[RH]]+Table1115[[#This Row],[LH]] -> 0 | P25: =IF(Table1116[[#This Row],[Total]]=0,"",(MAX(P$3:P24)+1)+MAX(Table1115[Line Number])) | Q25: Pocket | R25: 32 | U25: =Table1116[[#This Row],[RH]]+Table1116[[#This Row],[LH]] -> 0 | AB25: =IF(Table18[[#This Row],[total]]=0,"",(MAX($AB$3:$AB24)+1)) | AC25: Pocket | AD25: 32 | AE25: 80 | AF25: =Table11[[#This Row],[LH]] -> 0 | AG25: =Table11[[#This Row],[RH]] -> 0 | AH25: =Table18[[#This Row],[RH]]+Table18[[#This Row],[LH]] -> 0
B26: =IF(Table11[[#This Row],[Total]]=0,"",(MAX(B$3:B25)+1)) | C26: Pocket | D26: 34 | G26: =Table11[[#This Row],[RH]]+Table11[[#This Row],[LH]] -> 0 | I26: =IF(Table1115[[#This Row],[Total]]=0,"",(MAX(I$3:I25)+1)+(MAX(Table11[Line Number]))) | J26: Pocket | K26: 34 | N26: =Table1115[[#This Row],[RH]]+Table1115[[#This Row],[LH]] -> 0 | P26: =IF(Table1116[[#This Row],[Total]]=0,"",(MAX(P$3:P25)+1)+MAX(Table1115[Line Number])) | Q26: Pocket | R26: 34 | U26: =Table1116[[#This Row],[RH]]+Table1116[[#This Row],[LH]] -> 0 | AB26: =IF(Table18[[#This Row],[total]]=0,"",(MAX($AB$3:$AB25)+1)) | AC26: Pocket | AD26: 34 | AE26: 80 | AF26: =Table11[[#This Row],[LH]] -> 0 | AG26: =Table11[[#This Row],[RH]] -> 0 | AH26: =Table18[[#This Row],[RH]]+Table18[[#This Row],[LH]] -> 0
B27: =IF(Table11[[#This Row],[Total]]=0,"",(MAX(B$3:B26)+1)) | C27: Pocket | D27: 36 | G27: =Table11[[#This Row],[RH]]+Table11[[#This Row],[LH]] -> 0 | I27: =IF(Table1115[[#This Row],[Total]]=0,"",(MAX(I$3:I26)+1)+(MAX(Table11[Line Number]))) | J27: Pocket | K27: 36 | N27: =Table1115[[#This Row],[RH]]+Table1115[[#This Row],[LH]] -> 0 | P27: =IF(Table1116[[#This Row],[Total]]=0,"",(MAX(P$3:P26)+1)+MAX(Table1115[Line Number])) | Q27: Pocket | R27: 36 | U27: =Table1116[[#This Row],[RH]]+Table1116[[#This Row],[LH]] -> 0 | AB27: =IF(Table18[[#This Row],[total]]=0,"",(MAX($AB$3:$AB26)+1)) | AC27: Pocket | AD27: 36 | AE27: 80 | AF27: =Table11[[#This Row],[LH]] -> 0 | AG27: =Table11[[#This Row],[RH]] -> 0 | AH27: =Table18[[#This Row],[RH]]+Table18[[#This Row],[LH]] -> 0
B28: =IF(Table11[[#This Row],[Total]]=0,"",(MAX(B$3:B27)+1)) | C28: Barn | D28: 30 | G28: =Table11[[#This Row],[RH]]+Table11[[#This Row],[LH]] -> 0 | I28: =IF(Table1115[[#This Row],[Total]]=0,"",(MAX(I$3:I27)+1)+(MAX(Table11[Line Number]))) | J28: Barn | K28: 30 | N28: =Table1115[[#This Row],[RH]]+Table1115[[#This Row],[LH]] -> 0 | P28: =IF(Table1116[[#This Row],[Total]]=0,"",(MAX(P$3:P27)+1)+MAX(Table1115[Line Number])) | Q28: Barn | R28: 30 | U28: =Table1116[[#This Row],[RH]]+Table1116[[#This Row],[LH]] -> 0 | AB28: =IF(Table18[[#This Row],[total]]=0,"",(MAX($AB$3:$AB27)+1)) | AC28: Barn | AD28: 30 | AE28: 80 | AF28: =Table11[[#This Row],[LH]] -> 0 | AG28: =Table11[[#This Row],[RH]] -> 0 | AH28: =Table18[[#This Row],[RH]]+Table18[[#This Row],[LH]] -> 0
B29: =IF(Table11[[#This Row],[Total]]=0,"",(MAX(B$3:B28)+1)) | C29: Barn | D29: 32 | G29: =Table11[[#This Row],[RH]]+Table11[[#This Row],[LH]] -> 0 | I29: =IF(Table1115[[#This Row],[Total]]=0,"",(MAX(I$3:I28)+1)+(MAX(Table11[Line Number]))) | J29: Barn | K29: 32 | N29: =Table1115[[#This Row],[RH]]+Table1115[[#This Row],[LH]] -> 0 | P29: =IF(Table1116[[#This Row],[Total]]=0,"",(MAX(P$3:P28)+1)+MAX(Table1115[Line Number])) | Q29: Barn | R29: 32 | U29: =Table1116[[#This Row],[RH]]+Table1116[[#This Row],[LH]] -> 0 | AB29: =IF(Table18[[#This Row],[total]]=0,"",(MAX($AB$3:$AB28)+1)) | AC29: Barn | AD29: 32 | AE29: 80 | AF29: =Table11[[#This Row],[LH]] -> 0 | AG29: =Table11[[#This Row],[RH]] -> 0 | AH29: =Table18[[#This Row],[RH]]+Table18[[#This Row],[LH]] -> 0
B30: =IF(Table11[[#This Row],[Total]]=0,"",(MAX(B$3:B29)+1)) | C30: Barn | D30: 34 | G30: =Table11[[#This Row],[RH]]+Table11[[#This Row],[LH]] -> 0 | I30: =IF(Table1115[[#This Row],[Total]]=0,"",(MAX(I$3:I29)+1)+(MAX(Table11[Line Number]))) | J30: Barn | K30: 34 | N30: =Table1115[[#This Row],[RH]]+Table1115[[#This Row],[LH]] -> 0 | P30: =IF(Table1116[[#This Row],[Total]]=0,"",(MAX(P$3:P29)+1)+MAX(Table1115[Line Number])) | Q30: Barn | R30: 34 | U30: =Table1116[[#This Row],[RH]]+Table1116[[#This Row],[LH]] -> 0 | AB30: =IF(Table18[[#This Row],[total]]=0,"",(MAX($AB$3:$AB29)+1)) | AC30: Barn | AD30: 34 | AE30: 80 | AF30: =Table11[[#This Row],[LH]] -> 0 | AG30: =Table11[[#This Row],[RH]] -> 0 | AH30: =Table18[[#This Row],[RH]]+Table18[[#This Row],[LH]] -> 0
B31: =IF(Table11[[#This Row],[Total]]=0,"",(MAX(B$3:B30)+1)) | C31: Barn | D31: 36 | G31: =Table11[[#This Row],[RH]]+Table11[[#This Row],[LH]] -> 0 | I31: =IF(Table1115[[#This Row],[Total]]=0,"",(MAX(I$3:I30)+1)+(MAX(Table11[Line Number]))) | J31: Barn | K31: 36 | N31: =Table1115[[#This Row],[RH]]+Table1115[[#This Row],[LH]] -> 0 | P31: =IF(Table1116[[#This Row],[Total]]=0,"",(MAX(P$3:P30)+1)+MAX(Table1115[Line Number])) | Q31: Barn | R31: 36 | U31: =Table1116[[#This Row],[RH]]+Table1116[[#This Row],[LH]] -> 0 | AB31: =IF(Table18[[#This Row],[total]]=0,"",(MAX($AB$3:$AB30)+1)) | AC31: Barn | AD31: 36 | AE31: 80 | AF31: =Table11[[#This Row],[LH]] -> 0 | AG31: =Table11[[#This Row],[RH]] -> 0 | AH31: =Table18[[#This Row],[RH]]+Table18[[#This Row],[LH]] -> 0
... B35: =IF(Table11[[#This Row],[Total]]=0,"",(MAX(B$3:B34)+1)) | C35: Barn | D35: 48 | G35: =Table11[[#This Row],[RH]]+Table11[[#This Row],[LH]] -> 0 | I35: =IF(Table1115[[#This Row],[Total]]=0,"",(MAX(I$3:I34)+1)+(MAX(Table11[Line Number]))) | J35: Barn | K35: 48 | N35: =Table1115[[#This Row],[RH]]+Table1115[[#This Row],[LH]] -> 0 | P35: =IF(Table1116[[#This Row],[Total]]=0,"",(MAX(P$3:P34)+1)+MAX(Table1115[Line Number])) | Q35: Barn | R35: 48 | U35: =Table1116[[#This Row],[RH]]+Table1116[[#This Row],[LH]] -> 0 | AB35: =IF(Table18[[#This Row],[total]]=0,"",(MAX($AB$3:$AB34)+1)) | AC35: Barn | AD35: 48 | AE35: 80 | AF35: =Table11[[#This Row],[LH]] -> 0 | AG35: =Table11[[#This Row],[RH]] -> 0 | AH35: =Table18[[#This Row],[RH]]+Table18[[#This Row],[LH]] -> 0
AB36: =IF(Table18[[#This Row],[total]]=0,"",(MAX($AB$3:$AB35)+1)) | AC36: Swing | AD36: 24 | AE36: 84 | AF36: =L4 -> 0 | AG36: =M4 -> 0 | AH36: =Table18[[#This Row],[RH]]+Table18[[#This Row],[LH]] -> 0
AB37: =IF(Table18[[#This Row],[total]]=0,"",(MAX($AB$3:$AB36)+1)) | AC37: Swing | AD37: 26 | AE37: 84 | AF37: =L5 -> 0 | AG37: =M5 -> 0 | AH37: =Table18[[#This Row],[RH]]+Table18[[#This Row],[LH]] -> 0
AB38: =IF(Table18[[#This Row],[total]]=0,"",(MAX($AB$3:$AB37)+1)) | AC38: Swing | AD38: 28 | AE38: 84 | AF38: =L6 -> 0 | AG38: =M6 -> 0 | AH38: =Table18[[#This Row],[RH]]+Table18[[#This Row],[LH]] -> 0
AB39: =IF(Table18[[#This Row],[total]]=0,"",(MAX($AB$3:$AB38)+1)) -> 3 | AC39: Swing | AD39: 30 | AE39: 84 | AF39: =L7 -> 3 | AG39: =M7 -> 0 | AH39: =Table18[[#This Row],[RH]]+Table18[[#This Row],[LH]] -> 3
AB40: =IF(Table18[[#This Row],[total]]=0,"",(MAX($AB$3:$AB39)+1)) -> 4 | AC40: Swing | AD40: 32 | AE40: 84 | AF40: =L8 -> 2 | AG40: =M8 -> 0 | AH40: =Table18[[#This Row],[RH]]+Table18[[#This Row],[LH]] -> 2
AB41: =IF(Table18[[#This Row],[total]]=0,"",(MAX($AB$3:$AB40)+1)) | AC41: Swing | AD41: 34 | AE41: 84 | AF41: =L9 -> 0 | AG41: =M9 -> 0 | AH41: =Table18[[#This Row],[RH]]+Table18[[#This Row],[LH]] -> 0
AB42: =IF(Table18[[#This Row],[total]]=0,"",(MAX($AB$3:$AB41)+1)) | AC42: Swing | AD42: 36 | AE42: 84 | AF42: =L10 -> 0 | AG42: =M10 -> 0 | AH42: =Table18[[#This Row],[RH]]+Table18[[#This Row],[LH]] -> 0
AB43: =IF(Table18[[#This Row],[total]]=0,"",(MAX($AB$3:$AB42)+1)) | AC43: Bi-Fold | AD43: 24 | AE43: 84 | AF43: =L11 -> 0 | AG43: =M11 -> 0 | AH43: =Table18[[#This Row],[RH]]+Table18[[#This Row],[LH]] -> 0
AB44: =IF(Table18[[#This Row],[total]]=0,"",(MAX($AB$3:$AB43)+1)) | AC44: Bi-Fold | AD44: 26 | AE44: 84 | AF44: =L12 -> 0 | AG44: =M12 -> 0 | AH44: =Table18[[#This Row],[RH]]+Table18[[#This Row],[LH]] -> 0
AB45: =IF(Table18[[#This Row],[total]]=0,"",(MAX($AB$3:$AB44)+1)) | AC45: Bi-Fold | AD45: 28 | AE45: 84 | AF45: =L13 -> 0 | AG45: =M13 -> 0 | AH45: =Table18[[#This Row],[RH]]+Table18[[#This Row],[LH]] -> 0
AB46: =IF(Table18[[#This Row],[total]]=0,"",(MAX($AB$3:$AB45)+1)) | AC46: Bi-Fold | AD46: 30 | AE46: 84 | AF46: =L14 -> 0 | AG46: =M14 -> 0 | AH46: =Table18[[#This Row],[RH]]+Table18[[#This Row],[LH]] -> 0
AB47: =IF(Table18[[#This Row],[total]]=0,"",(MAX($AB$3:$AB46)+1)) | AC47: Bi-Fold | AD47: 32 | AE47: 84 | AF47: =L15 -> 0 | AG47: =M15 -> 0 | AH47: =Table18[[#This Row],[RH]]+Table18[[#This Row],[LH]] -> 0
... AB67: =IF(Table18[[#This Row],[total]]=0,"",(MAX($AB$3:$AB66)+1)) | AC67: Barn | AD67: 48 | AE67: 84 | AF67: =L35 -> 0 | AG67: =M35 -> 0 | AH67: =Table18[[#This Row],[RH]]+Table18[[#This Row],[LH]] -> 0
AB68: =IF(Table18[[#This Row],[total]]=0,"",(MAX($AB$3:$AB67)+1)) | AC68: Swing | AD68: 24 | AE68: 96 | AF68: =S4 -> 0 | AG68: =T4 -> 0 | AH68: =Table18[[#This Row],[RH]]+Table18[[#This Row],[LH]] -> 0
AB69: =IF(Table18[[#This Row],[total]]=0,"",(MAX($AB$3:$AB68)+1)) | AC69: Swing | AD69: 26 | AE69: 96 | AF69: =S5 -> 0 | AG69: =T5 -> 0 | AH69: =Table18[[#This Row],[RH]]+Table18[[#This Row],[LH]] -> 0
AB70: =IF(Table18[[#This Row],[total]]=0,"",(MAX($AB$3:$AB69)+1)) | AC70: Swing | AD70: 28 | AE70: 96 | AF70: =S6 -> 0 | AG70: =T6 -> 0 | AH70: =Table18[[#This Row],[RH]]+Table18[[#This Row],[LH]] -> 0
AB71: =IF(Table18[[#This Row],[total]]=0,"",(MAX($AB$3:$AB70)+1)) | AC71: Swing | AD71: 30 | AE71: 96 | AF71: =S7 -> 0 | AG71: =T7 -> 0 | AH71: =Table18[[#This Row],[RH]]+Table18[[#This Row],[LH]] -> 0
AB72: =IF(Table18[[#This Row],[total]]=0,"",(MAX($AB$3:$AB71)+1)) | AC72: Swing | AD72: 32 | AE72: 96 | AF72: =S8 -> 0 | AG72: =T8 -> 0 | AH72: =Table18[[#This Row],[RH]]+Table18[[#This Row],[LH]] -> 0
AB73: =IF(Table18[[#This Row],[total]]=0,"",(MAX($AB$3:$AB72)+1)) | AC73: Swing | AD73: 34 | AE73: 96 | AF73: =S9 -> 0 | AG73: =T9 -> 0 | AH73: =Table18[[#This Row],[RH]]+Table18[[#This Row],[LH]] -> 0
AB74: =IF(Table18[[#This Row],[total]]=0,"",(MAX($AB$3:$AB73)+1)) -> 5 | AC74: Swing | AD74: 36 | AE74: 96 | AF74: =S10 -> 0 | AG74: =T10 -> 1 | AH74: =Table18[[#This Row],[RH]]+Table18[[#This Row],[LH]] -> 1
AB75: =IF(Table18[[#This Row],[total]]=0,"",(MAX($AB$3:$AB74)+1)) | AC75: Bi-Fold | AD75: 24 | AE75: 96 | AF75: =S11 -> 0 | AG75: =T11 -> 0 | AH75: =Table18[[#This Row],[RH]]+Table18[[#This Row],[LH]] -> 0
AB76: =IF(Table18[[#This Row],[total]]=0,"",(MAX($AB$3:$AB75)+1)) | AC76: Bi-Fold | AD76: 26 | AE76: 96 | AF76: =S12 -> 0 | AG76: =T12 -> 0 | AH76: =Table18[[#This Row],[RH]]+Table18[[#This Row],[LH]] -> 0
AB77: =IF(Table18[[#This Row],[total]]=0,"",(MAX($AB$3:$AB76)+1)) | AC77: Bi-Fold | AD77: 28 | AE77: 96 | AF77: =S13 -> 0 | AG77: =T13 -> 0 | AH77: =Table18[[#This Row],[RH]]+Table18[[#This Row],[LH]] -> 0
AB78: =IF(Table18[[#This Row],[total]]=0,"",(MAX($AB$3:$AB77)+1)) | AC78: Bi-Fold | AD78: 30 | AE78: 96 | AF78: =S14 -> 0 | AG78: =T14 -> 0 | AH78: =Table18[[#This Row],[RH]]+Table18[[#This Row],[LH]] -> 0
AB79: =IF(Table18[[#This Row],[total]]=0,"",(MAX($AB$3:$AB78)+1)) | AC79: Bi-Fold | AD79: 32 | AE79: 96 | AF79: =S15 -> 0 | AG79: =T15 -> 0 | AH79: =Table18[[#This Row],[RH]]+Table18[[#This Row],[LH]] -> 0
... AB99: =IF(Table18[[#This Row],[total]]=0,"",(MAX($AB$3:$AB98)+1)) | AC99: Barn | AD99: 48 | AE99: 96 | AF99: =S35 -> 0 | AG99: =T35 -> 0 | AH99: =Table18[[#This Row],[RH]]+Table18[[#This Row],[LH]] -> 0

Sheet Trim Calc
H2: Rip Factor Increase | I2: 0.15 | J2: This increases the BF required to get the LF of trim requested
H3: Material Mark Up | I3: 0.25 | J3: Our mark up on the BF ordered
H4: Set Up Fee | I4: =IF('Trim Take Off'!$C$17="CUSTOM",175,75) -> 175 | J4: Set up fee determined by profile in take off table, can be manually overriden here
H5: Lin Ft Add | I5: 0.85 | J5: Standard LF add for running, we can add a table that takes into account total feet or complexity to adjust this automatically
H6: Knife Cost/ IN | I6: 100 | J6: Cost included to cut a knife if custom profile
H7: Sell/LF Margin | I7: 0.1 | J7: Additional margin that can be added to the entire project
H8: Total | I8: =SUBTOTAL(9,TRIM[Total Raw]) -> 4904.1568 | J8: You shouldn't need to do anything in the table below, but if you NEED to you can hard key any value in to replace the formulas
A14: line number | B14: Species | C14: Finish Size | D14: Finish | E14: FINISH HELP | F14: Type | G14: NAME TYPE | H14: Description | I14: Width | J14: Thickness | K14: Rough Thick | L14: Lin.Ft. | M14: Factor | N14: Cost/BF | O14: BF | P14: Total Cost | Q14: Material Mark Up | R14: Set-up | S14: LF Add | T14: Knife Grind | U14: Total Raw | V14: cost/L.F. | W14: LF Finish Add | X14: Sell/LF Margin | Y14: Set Up Total
A15: =IF(TRIM[[#This Row],[Species]]=0,"",IF(TRIM[[#This Row],[Lin.Ft.]]>1,(MAX($A$14:$A14)+1),"")) -> 1 | B15: ='Trim Take Off'!$C$20 -> Poplar | C15: =IF(TRIM[[#This Row],[Width]]>5.25,"LARGE",IF(TRIM[[#This Row],[Width]]>3,"AVG",IF(TRIM[[#This Row],[Width]]="","","SMALL"))) -> AVG | D15: =IF(TRIM[[#This Row],[Species]]="","",IF(TRIM[[#This Row],[Species]]="POPLAR","PRIMED",IF(TRIM[[#This Row],[Species]]="MDF","PRIMED","STAINED"))) -> PRIMED | E15: =TRIM[[#This Row],[Finish]]&" "&TRIM[[#This Row],[Finish Size]] -> PRIMED AVG | F15: BASE | G15: ='Trim Take Off'!$C$16&" "&TRIM[[#This Row],[Type]] -> CRAFTSMAN BASE | H15: =IFERROR(TRIM[[#This Row],[Species]]&" "&TRIM[[#This Row],[Finish]]&" "&TRIM[[#This Row],[Type]]&" "&TRIM[[#This Row],[Width]]&" x "&TRIM[[#This Row],[Thickness]],"") -> Poplar PRIMED BASE 5.25 x 0.5 | I15: =IFERROR(INDEX(Table5[ACTUAL WIDTH],MATCH(TRIM[[#This Row],[NAME TYPE]],Table5[DESCRIPTION],0)),) -> 5.25 | J15: =IFERROR(INDEX(Table5[ACTUAL THICKNESS],MATCH(TRIM[[#This Row],[NAME TYPE]],Table5[DESCRIPTION],0)),"") -> 0.5 | K15: =INDEX(lumber[Rough],MATCH(TRIM[[#This Row],[Thickness]],lumber[Finish],1)) -> 1 | L15: =IFERROR(INDEX(Table5[LF],MATCH(TRIM[[#This Row],[NAME TYPE]],Table5[DESCRIPTION],0)),0) -> 350 | M15: =IFERROR((IF(TRIM[[#This Row],[Rough Thick]]=1,INDEX(Table1[4/4],MATCH(TRIM[[#This Row],[Width]],Table1[RIP SIZE],0)),IF(TRIM[[#This Row],[Rough Thick]]=1.25,INDEX(Table1[5/4],MATCH(TRIM[[#This Row],[Width]],Table1[RIP SIZE],0)),IF(TRIM[[#This Row],[Rough Thick]]=1.5,INDEX(Table1[6/4],MATCH(TRIM[[#This Row],[Width]],Table1[RIP SIZE],0)),IF(TRIM[[#This Row],[Rough Thick]]=2,INDEX(Table1[8/4],MATCH(TRIM[[#This Row],[Width]],Table1[RIP SIZE],0)),"")))))*(1+$I$2),0) -> 0.7314 | N15: =IF(TRIM[[#This Row],[Width]]>6,INDEX(Table10[1 sorted],MATCH(TRIM[[#This Row],[Species]],Table10[Species],0)),INDEX(Table10[1],MATCH(TRIM[[#This Row],[Species]],Table10[Species],0))) -> 2.3 | O15: =TRIM[[#This Row],[Factor]]*TRIM[[#This Row],[Lin.Ft.]] -> 255.99 | P15: =TRIM[[#This Row],[BF]]*TRIM[[#This Row],[Cost/BF]] -> 588.777 | Q15: =IF(TRIM[[#This Row],[BF]]="","",P15*I$3) -> 147.19425 | R15: =$I$4 -> 175 | S15: =TRIM[[#This Row],[Lin.Ft.]]*$I$5 -> 297.5 | T15: =IF('Trim Take Off'!$C$17="custom",(TRIM[[#This Row],[Width]]+0.25)*$I$6,0) -> 550 | U15: =IFERROR(TRIM[[#This Row],[LF Add]]+TRIM[[#This Row],[Material Mark Up]]+TRIM[[#This Row],[Total Cost]],0) -> 1033.4713 | V15: =IFERROR(TRIM[[#This Row],[Total Raw]]/TRIM[[#This Row],[Lin.Ft.]],"") -> 2.952775 | W15: =INDEX(finish[Rate],MATCH(TRIM[[#This Row],[FINISH HELP]],finish[Finish],0)) -> 1 | X15: =IFERROR((TRIM[[#This Row],[cost/L.F.]]*(1+$I$7)),"") -> 3.2480525 | Y15: =IFERROR(TRIM[[#This Row],[Knife Grind]]+TRIM[[#This Row],[Set-up]],"") -> 725
A16: =IF(TRIM[[#This Row],[Species]]=0,"",IF(TRIM[[#This Row],[Lin.Ft.]]>1,(MAX($A$14:$A15)+1),"")) -> 2 | B16: ='Trim Take Off'!$C$20 -> Poplar | C16: =IF(TRIM[[#This Row],[Width]]>5.25,"LARGE",IF(TRIM[[#This Row],[Width]]>3,"AVG",IF(TRIM[[#This Row],[Width]]="","","SMALL"))) -> AVG | D16: =IF(TRIM[[#This Row],[Species]]="","",IF(TRIM[[#This Row],[Species]]="POPLAR","PRIMED",IF(TRIM[[#This Row],[Species]]="MDF","PRIMED","STAINED"))) -> PRIMED | E16: =TRIM[[#This Row],[Finish]]&" "&TRIM[[#This Row],[Finish Size]] -> PRIMED AVG | F16: CASE | G16: ='Trim Take Off'!$C$16&" "&TRIM[[#This Row],[Type]] -> CRAFTSMAN CASE | H16: =IFERROR(TRIM[[#This Row],[Species]]&" "&TRIM[[#This Row],[Finish]]&" "&TRIM[[#This Row],[Type]]&" "&TRIM[[#This Row],[Width]]&" x "&TRIM[[#This Row],[Thickness]],"") -> Poplar PRIMED CASE 3.25 x 0.625 | I16: =IFERROR(INDEX(Table5[ACTUAL WIDTH],MATCH(TRIM[[#This Row],[NAME TYPE]],Table5[DESCRIPTION],0)),) -> 3.25 | J16: =IFERROR(INDEX(Table5[ACTUAL THICKNESS],MATCH(TRIM[[#This Row],[NAME TYPE]],Table5[DESCRIPTION],0)),"") -> 0.625 | K16: =INDEX(lumber[Rough],MATCH(TRIM[[#This Row],[Thickness]],lumber[Finish],1)) -> 1 | L16: =IFERROR(INDEX(Table5[LF],MATCH(TRIM[[#This Row],[NAME TYPE]],Table5[DESCRIPTION],0)),0) -> 714 | M16: =IFERROR((IF(TRIM[[#This Row],[Rough Thick]]=1,INDEX(Table1[4/4],MATCH(TRIM[[#This Row],[Width]],Table1[RIP SIZE],0)),IF(TRIM[[#This Row],[Rough Thick]]=1.25,INDEX(Table1[5/4],MATCH(TRIM[[#This Row],[Width]],Table1[RIP SIZE],0)),IF(TRIM[[#This Row],[Rough Thick]]=1.5,INDEX(Table1[6/4],MATCH(TRIM[[#This Row],[Width]],Table1[RIP SIZE],0)),IF(TRIM[[#This Row],[Rough Thick]]=2,INDEX(Table1[8/4],MATCH(TRIM[[#This Row],[Width]],Table1[RIP SIZE],0)),"")))))*(1+$I$2),0) -> 0.50025 | N16: =IF(TRIM[[#This Row],[Width]]>6,INDEX(Table10[1 sorted],MATCH(TRIM[[#This Row],[Species]],Table10[Species],0)),INDEX(Table10[1],MATCH(TRIM[[#This Row],[Species]],Table10[Species],0))) -> 2.3 | O16: =TRIM[[#This Row],[Factor]]*TRIM[[#This Row],[Lin.Ft.]] -> 357.1785 | P16: =TRIM[[#This Row],[BF]]*TRIM[[#This Row],[Cost/BF]] -> 821.51055 | Q16: =IF(TRIM[[#This Row],[BF]]="","",P16*I$3) -> 205.37764 | R16: =$I$4 -> 175 | S16: =TRIM[[#This Row],[Lin.Ft.]]*$I$5 -> 606.9 | T16: =IF('Trim Take Off'!$C$17="custom",(TRIM[[#This Row],[Width]]+0.25)*$I$6,0) -> 350 | U16: =IFERROR(TRIM[[#This Row],[LF Add]]+TRIM[[#This Row],[Material Mark Up]]+TRIM[[#This Row],[Total Cost]],0) -> 1633.7882 | V16: =IFERROR(TRIM[[#This Row],[Total Raw]]/TRIM[[#This Row],[Lin.Ft.]],"") -> 2.2882187 | W16: =INDEX(finish[Rate],MATCH(TRIM[[#This Row],[FINISH HELP]],finish[Finish],0)) -> 1 | X16: =IFERROR((TRIM[[#This Row],[cost/L.F.]]*(1+$I$7)),"") -> 2.5170406 | Y16: =IFERROR(TRIM[[#This Row],[Knife Grind]]+TRIM[[#This Row],[Set-up]],"") -> 525
A17: =IF(TRIM[[#This Row],[Species]]=0,"",IF(TRIM[[#This Row],[Lin.Ft.]]>1,(MAX($A$14:$A16)+1),"")) -> 3 | B17: ='Trim Take Off'!$C$20 -> Poplar | C17: =IF(TRIM[[#This Row],[Width]]>5.25,"LARGE",IF(TRIM[[#This Row],[Width]]>3,"AVG",IF(TRIM[[#This Row],[Width]]="","","SMALL"))) -> AVG | D17: =IF(TRIM[[#This Row],[Species]]="","",IF(TRIM[[#This Row],[Species]]="POPLAR","PRIMED",IF(TRIM[[#This Row],[Species]]="MDF","PRIMED","STAINED"))) -> PRIMED | E17: =TRIM[[#This Row],[Finish]]&" "&TRIM[[#This Row],[Finish Size]] -> PRIMED AVG | F17: HEADER | G17: ='Trim Take Off'!$C$16&" "&TRIM[[#This Row],[Type]] -> CRAFTSMAN HEADER | H17: =IFERROR(TRIM[[#This Row],[Species]]&" "&TRIM[[#This Row],[Finish]]&" "&TRIM[[#This Row],[Type]]&" "&TRIM[[#This Row],[Width]]&" x "&TRIM[[#This Row],[Thickness]],"") -> Poplar PRIMED HEADER 5.25 x 0.875 | I17: =IFERROR(INDEX(Table5[ACTUAL WIDTH],MATCH(TRIM[[#This Row],[NAME TYPE]],Table5[DESCRIPTION],0)),) -> 5.25 | J17: =IFERROR(INDEX(Table5[ACTUAL THICKNESS],MATCH(TRIM[[#This Row],[NAME TYPE]],Table5[DESCRIPTION],0)),"") -> 0.875 | K17: =INDEX(lumber[Rough],MATCH(TRIM[[#This Row],[Thickness]],lumber[Finish],1)) -> 1 | L17: =IFERROR(INDEX(Table5[LF],MATCH(TRIM[[#This Row],[NAME TYPE]],Table5[DESCRIPTION],0)),0) -> 139.5 | M17: =IFERROR((IF(TRIM[[#This Row],[Rough Thick]]=1,INDEX(Table1[4/4],MATCH(TRIM[[#This Row],[Width]],Table1[RIP SIZE],0)),IF(TRIM[[#This Row],[Rough Thick]]=1.25,INDEX(Table1[5/4],MATCH(TRIM[[#This Row],[Width]],Table1[RIP SIZE],0)),IF(TRIM[[#This Row],[Rough Thick]]=1.5,INDEX(Table1[6/4],MATCH(TRIM[[#This Row],[Width]],Table1[RIP SIZE],0)),IF(TRIM[[#This Row],[Rough Thick]]=2,INDEX(Table1[8/4],MATCH(TRIM[[#This Row],[Width]],Table1[RIP SIZE],0)),"")))))*(1+$I$2),0) -> 0.7314 | N17: =IF(TRIM[[#This Row],[Width]]>6,INDEX(Table10[1 sorted],MATCH(TRIM[[#This Row],[Species]],Table10[Species],0)),INDEX(Table10[1],MATCH(TRIM[[#This Row],[Species]],Table10[Species],0))) -> 2.3 | O17: =TRIM[[#This Row],[Factor]]*TRIM[[#This Row],[Lin.Ft.]] -> 102.0303 | P17: =TRIM[[#This Row],[BF]]*TRIM[[#This Row],[Cost/BF]] -> 234.66969 | Q17: =IF(TRIM[[#This Row],[BF]]="","",P17*I$3) -> 58.667422 | R17: =$I$4 -> 175 | S17: =TRIM[[#This Row],[Lin.Ft.]]*$I$5 -> 118.575 | T17: =IF('Trim Take Off'!$C$17="custom",(TRIM[[#This Row],[Width]]+0.25)*$I$6,0) -> 550 | U17: =IFERROR(TRIM[[#This Row],[LF Add]]+TRIM[[#This Row],[Material Mark Up]]+TRIM[[#This Row],[Total Cost]],0) -> 411.91211 | V17: =IFERROR(TRIM[[#This Row],[Total Raw]]/TRIM[[#This Row],[Lin.Ft.]],"") -> 2.952775 | W17: =INDEX(finish[Rate],MATCH(TRIM[[#This Row],[FINISH HELP]],finish[Finish],0)) -> 1 | X17: =IFERROR((TRIM[[#This Row],[cost/L.F.]]*(1+$I$7)),"") -> 3.2480525 | Y17: =IFERROR(TRIM[[#This Row],[Knife Grind]]+TRIM[[#This Row],[Set-up]],"") -> 725
A18: =IF(TRIM[[#This Row],[Species]]=0,"",IF(TRIM[[#This Row],[Lin.Ft.]]>1,(MAX($A$14:$A17)+1),"")) -> 4 | B18: ='Trim Take Off'!$C$20 -> Poplar | C18: =IF(TRIM[[#This Row],[Width]]>5.25,"LARGE",IF(TRIM[[#This Row],[Width]]>3,"AVG",IF(TRIM[[#This Row],[Width]]="","","SMALL"))) -> AVG | D18: =IF(TRIM[[#This Row],[Species]]="","",IF(TRIM[[#This Row],[Species]]="POPLAR","PRIMED",IF(TRIM[[#This Row],[Species]]="MDF","PRIMED","STAINED"))) -> PRIMED | E18: =TRIM[[#This Row],[Finish]]&" "&TRIM[[#This Row],[Finish Size]] -> PRIMED AVG | F18: INT JAMB | G18: ='Trim Take Off'!$C$16&" "&TRIM[[#This Row],[Type]] -> CRAFTSMAN INT JAMB | H18: =IFERROR(TRIM[[#This Row],[Species]]&" "&TRIM[[#This Row],[Finish]]&" "&TRIM[[#This Row],[Type]]&" "&TRIM[[#This Row],[Width]]&" x "&TRIM[[#This Row],[Thickness]],"") -> Poplar PRIMED INT JAMB 4.75 x 0.75 | I18: =IFERROR(INDEX(Table5[ACTUAL WIDTH],MATCH(TRIM[[#This Row],[NAME TYPE]],Table5[DESCRIPTION],0)),) -> 4.75 | J18: =IFERROR(INDEX(Table5[ACTUAL THICKNESS],MATCH(TRIM[[#This Row],[NAME TYPE]],Table5[DESCRIPTION],0)),"") -> 0.75 | K18: =INDEX(lumber[Rough],MATCH(TRIM[[#This Row],[Thickness]],lumber[Finish],1)) -> 1 | L18: =IFERROR(INDEX(Table5[LF],MATCH(TRIM[[#This Row],[NAME TYPE]],Table5[DESCRIPTION],0)),0) -> 21 | M18: =IFERROR((IF(TRIM[[#This Row],[Rough Thick]]=1,INDEX(Table1[4/4],MATCH(TRIM[[#This Row],[Width]],Table1[RIP SIZE],0)),IF(TRIM[[#This Row],[Rough Thick]]=1.25,INDEX(Table1[5/4],MATCH(TRIM[[#This Row],[Width]],Table1[RIP SIZE],0)),IF(TRIM[[#This Row],[Rough Thick]]=1.5,INDEX(Table1[6/4],MATCH(TRIM[[#This Row],[Width]],Table1[RIP SIZE],0)),IF(TRIM[[#This Row],[Rough Thick]]=2,INDEX(Table1[8/4],MATCH(TRIM[[#This Row],[Width]],Table1[RIP SIZE],0)),"")))))*(1+$I$2),0) -> 0.65665 | N18: =IF(TRIM[[#This Row],[Width]]>6,INDEX(Table10[1 sorted],MATCH(TRIM[[#This Row],[Species]],Table10[Species],0)),INDEX(Table10[1],MATCH(TRIM[[#This Row],[Species]],Table10[Species],0))) -> 2.3 | O18: =TRIM[[#This Row],[Factor]]*TRIM[[#This Row],[Lin.Ft.]] -> 13.78965 | P18: =TRIM[[#This Row],[BF]]*TRIM[[#This Row],[Cost/BF]] -> 31.716195 | Q18: =IF(TRIM[[#This Row],[BF]]="","",P18*I$3) -> 7.9290487 | R18: =$I$4 -> 175 | S18: =TRIM[[#This Row],[Lin.Ft.]]*$I$5 -> 17.85 | T18: =IF('Trim Take Off'!$C$17="custom",(TRIM[[#This Row],[Width]]+0.25)*$I$6,0) -> 500 | U18: =IFERROR(TRIM[[#This Row],[LF Add]]+TRIM[[#This Row],[Material Mark Up]]+TRIM[[#This Row],[Total Cost]],0) -> 57.495244 | V18: =IFERROR(TRIM[[#This Row],[Total Raw]]/TRIM[[#This Row],[Lin.Ft.]],"") -> 2.7378687 | W18: =INDEX(finish[Rate],MATCH(TRIM[[#This Row],[FINISH HELP]],finish[Finish],0)) -> 1 | X18: =IFERROR((TRIM[[#This Row],[cost/L.F.]]*(1+$I$7)),"") -> 3.0116556 | Y18: =IFERROR(TRIM[[#This Row],[Knife Grind]]+TRIM[[#This Row],[Set-up]],"") -> 675
A19: =IF(TRIM[[#This Row],[Species]]=0,"",IF(TRIM[[#This Row],[Lin.Ft.]]>1,(MAX($A$14:$A18)+1),"")) -> 5 | B19: ='Trim Take Off'!$C$20 -> Poplar | C19: =IF(TRIM[[#This Row],[Width]]>5.25,"LARGE",IF(TRIM[[#This Row],[Width]]>3,"AVG",IF(TRIM[[#This Row],[Width]]="","","SMALL"))) -> LARGE | D19: =IF(TRIM[[#This Row],[Species]]="","",IF(TRIM[[#This Row],[Species]]="POPLAR","PRIMED",IF(TRIM[[#This Row],[Species]]="MDF","PRIMED","STAINED"))) -> PRIMED | E19: =TRIM[[#This Row],[Finish]]&" "&TRIM[[#This Row],[Finish Size]] -> PRIMED LARGE | F19: WINDOW JAMB | G19: ='Trim Take Off'!$C$16&" "&TRIM[[#This Row],[Type]] -> CRAFTSMAN WINDOW JAMB | H19: =IFERROR(TRIM[[#This Row],[Species]]&" "&TRIM[[#This Row],[Finish]]&" "&TRIM[[#This Row],[Type]]&" "&TRIM[[#This Row],[Width]]&" x "&TRIM[[#This Row],[Thickness]],"") -> Poplar PRIMED WINDOW JAMB 6 x 0.75 | I19: =IFERROR(INDEX(Table5[ACTUAL WIDTH],MATCH(TRIM[[#This Row],[NAME TYPE]],Table5[DESCRIPTION],0)),) -> 6 | J19: =IFERROR(INDEX(Table5[ACTUAL THICKNESS],MATCH(TRIM[[#This Row],[NAME TYPE]],Table5[DESCRIPTION],0)),"") -> 0.75 | K19: =INDEX(lumber[Rough],MATCH(TRIM[[#This Row],[Thickness]],lumber[Finish],1)) -> 1 | L19: =IFERROR(INDEX(Table5[LF],MATCH(TRIM[[#This Row],[NAME TYPE]],Table5[DESCRIPTION],0)),0) -> 273 | M19: =IFERROR((IF(TRIM[[#This Row],[Rough Thick]]=1,INDEX(Table1[4/4],MATCH(TRIM[[#This Row],[Width]],Table1[RIP SIZE],0)),IF(TRIM[[#This Row],[Rough Thick]]=1.25,INDEX(Table1[5/4],MATCH(TRIM[[#This Row],[Width]],Table1[RIP SIZE],0)),IF(TRIM[[#This Row],[Rough Thick]]=1.5,INDEX(Table1[6/4],MATCH(TRIM[[#This Row],[Width]],Table1[RIP SIZE],0)),IF(TRIM[[#This Row],[Rough Thick]]=2,INDEX(Table1[8/4],MATCH(TRIM[[#This Row],[Width]],Table1[RIP SIZE],0)),"")))))*(1+$I$2),0) -> 0.805 | N19: =IF(TRIM[[#This Row],[Width]]>6,INDEX(Table10[1 sorted],MATCH(TRIM[[#This Row],[Species]],Table10[Species],0)),INDEX(Table10[1],MATCH(TRIM[[#This Row],[Species]],Table10[Species],0))) -> 2.3 | O19: =TRIM[[#This Row],[Factor]]*TRIM[[#This Row],[Lin.Ft.]] -> 219.765 | P19: =TRIM[[#This Row],[BF]]*TRIM[[#This Row],[Cost/BF]] -> 505.4595 | Q19: =IF(TRIM[[#This Row],[BF]]="","",P19*I$3) -> 126.36487 | R19: =$I$4 -> 175 | S19: =TRIM[[#This Row],[Lin.Ft.]]*$I$5 -> 232.05 | T19: =IF('Trim Take Off'!$C$17="custom",(TRIM[[#This Row],[Width]]+0.25)*$I$6,0) -> 625 | U19: =IFERROR(TRIM[[#This Row],[LF Add]]+TRIM[[#This Row],[Material Mark Up]]+TRIM[[#This Row],[Total Cost]],0) -> 863.87437 | V19: =IFERROR(TRIM[[#This Row],[Total Raw]]/TRIM[[#This Row],[Lin.Ft.]],"") -> 3.164375 | W19: =INDEX(finish[Rate],MATCH(TRIM[[#This Row],[FINISH HELP]],finish[Finish],0)) -> 1.15 | X19: =IFERROR((TRIM[[#This Row],[cost/L.F.]]*(1+$I$7)),"") -> 3.4808125 | Y19: =IFERROR(TRIM[[#This Row],[Knife Grind]]+TRIM[[#This Row],[Set-up]],"") -> 800
A20: =IF(TRIM[[#This Row],[Species]]=0,"",IF(TRIM[[#This Row],[Lin.Ft.]]>1,(MAX($A$14:$A19)+1),"")) -> 6 | B20: ='Trim Take Off'!$C$20 -> Poplar | C20: =IF(TRIM[[#This Row],[Width]]>5.25,"LARGE",IF(TRIM[[#This Row],[Width]]>3,"AVG",IF(TRIM[[#This Row],[Width]]="","","SMALL"))) -> LARGE | D20: =IF(TRIM[[#This Row],[Species]]="","",IF(TRIM[[#This Row],[Species]]="POPLAR","PRIMED",IF(TRIM[[#This Row],[Species]]="MDF","PRIMED","STAINED"))) -> PRIMED | E20: =TRIM[[#This Row],[Finish]]&" "&TRIM[[#This Row],[Finish Size]] -> PRIMED LARGE | F20: SILL | G20: ='Trim Take Off'!$C$16&" "&TRIM[[#This Row],[Type]] -> CRAFTSMAN SILL | H20: =IFERROR(TRIM[[#This Row],[Species]]&" "&TRIM[[#This Row],[Finish]]&" "&TRIM[[#This Row],[Type]]&" "&TRIM[[#This Row],[Width]]&" x "&TRIM[[#This Row],[Thickness]],"") -> Poplar PRIMED SILL 7.25 x 0.75 | I20: =IFERROR(INDEX(Table5[ACTUAL WIDTH],MATCH(TRIM[[#This Row],[NAME TYPE]],Table5[DESCRIPTION],0)),) -> 7.25 | J20: =IFERROR(INDEX(Table5[ACTUAL THICKNESS],MATCH(TRIM[[#This Row],[NAME TYPE]],Table5[DESCRIPTION],0)),"") -> 0.75 | K20: =INDEX(lumber[Rough],MATCH(TRIM[[#This Row],[Thickness]],lumber[Finish],1)) -> 1 | L20: =IFERROR(INDEX(Table5[LF],MATCH(TRIM[[#This Row],[NAME TYPE]],Table5[DESCRIPTION],0)),0) -> 139.5 | M20: =IFERROR((IF(TRIM[[#This Row],[Rough Thick]]=1,INDEX(Table1[4/4],MATCH(TRIM[[#This Row],[Width]],Table1[RIP SIZE],0)),IF(TRIM[[#This Row],[Rough Thick]]=1.25,INDEX(Table1[5/4],MATCH(TRIM[[#This Row],[Width]],Table1[RIP SIZE],0)),IF(TRIM[[#This Row],[Rough Thick]]=1.5,INDEX(Table1[6/4],MATCH(TRIM[[#This Row],[Width]],Table1[RIP SIZE],0)),IF(TRIM[[#This Row],[Rough Thick]]=2,INDEX(Table1[8/4],MATCH(TRIM[[#This Row],[Width]],Table1[RIP SIZE],0)),"")))))*(1+$I$2),0) -> 0.93035 | N20: =IF(TRIM[[#This Row],[Width]]>6,INDEX(Table10[1 sorted],MATCH(TRIM[[#This Row],[Species]],Table10[Species],0)),INDEX(Table10[1],MATCH(TRIM[[#This Row],[Species]],Table10[Species],0))) -> 2.3 | O20: =TRIM[[#This Row],[Factor]]*TRIM[[#This Row],[Lin.Ft.]] -> 129.78383 | P20: =TRIM[[#This Row],[BF]]*TRIM[[#This Row],[Cost/BF]] -> 298.5028 | Q20: =IF(TRIM[[#This Row],[BF]]="","",P20*I$3) -> 74.625699 | R20: =$I$4 -> 175 | S20: =TRIM[[#This Row],[Lin.Ft.]]*$I$5 -> 118.575 | T20: =IF('Trim Take Off'!$C$17="custom",(TRIM[[#This Row],[Width]]+0.25)*$I$6,0) -> 750 | U20: =IFERROR(TRIM[[#This Row],[LF Add]]+TRIM[[#This Row],[Material Mark Up]]+TRIM[[#This Row],[Total Cost]],0) -> 491.7035 | V20: =IFERROR(TRIM[[#This Row],[Total Raw]]/TRIM[[#This Row],[Lin.Ft.]],"") -> 3.5247562 | W20: =INDEX(finish[Rate],MATCH(TRIM[[#This Row],[FINISH HELP]],finish[Finish],0)) -> 1.15 | X20: =IFERROR((TRIM[[#This Row],[cost/L.F.]]*(1+$I$7)),"") -> 3.8772319 | Y20: =IFERROR(TRIM[[#This Row],[Knife Grind]]+TRIM[[#This Row],[Set-up]],"") -> 925
A21: =IF(TRIM[[#This Row],[Species]]=0,"",IF(TRIM[[#This Row],[Lin.Ft.]]>1,(MAX($A$14:$A20)+1),"")) -> 7 | B21: ='Trim Take Off'!$C$20 -> Poplar | C21: =IF(TRIM[[#This Row],[Width]]>5.25,"LARGE",IF(TRIM[[#This Row],[Width]]>3,"AVG",IF(TRIM[[#This Row],[Width]]="","","SMALL"))) -> AVG | D21: =IF(TRIM[[#This Row],[Species]]="","",IF(TRIM[[#This Row],[Species]]="POPLAR","PRIMED",IF(TRIM[[#This Row],[Species]]="MDF","PRIMED","STAINED"))) -> PRIMED | E21: =TRIM[[#This Row],[Finish]]&" "&TRIM[[#This Row],[Finish Size]] -> PRIMED AVG | F21: APRON | G21: ='Trim Take Off'!$C$16&" "&TRIM[[#This Row],[Type]] -> CRAFTSMAN APRON | H21: =IFERROR(TRIM[[#This Row],[Species]]&" "&TRIM[[#This Row],[Finish]]&" "&TRIM[[#This Row],[Type]]&" "&TRIM[[#This Row],[Width]]&" x "&TRIM[[#This Row],[Thickness]],"") -> Poplar PRIMED APRON 5.25 x 0.5 | I21: =IFERROR(INDEX(Table5[ACTUAL WIDTH],MATCH(TRIM[[#This Row],[NAME TYPE]],Table5[DESCRIPTION],0)),) -> 5.25 | J21: =IFERROR(INDEX(Table5[ACTUAL THICKNESS],MATCH(TRIM[[#This Row],[NAME TYPE]],Table5[DESCRIPTION],0)),"") -> 0.5 | K21: =INDEX(lumber[Rough],MATCH(TRIM[[#This Row],[Thickness]],lumber[Finish],1)) -> 1 | L21: =IFERROR(INDEX(Table5[LF],MATCH(TRIM[[#This Row],[NAME TYPE]],Table5[DESCRIPTION],0)),0) -> 139.5 | M21: =IFERROR((IF(TRIM[[#This Row],[Rough Thick]]=1,INDEX(Table1[4/4],MATCH(TRIM[[#This Row],[Width]],Table1[RIP SIZE],0)),IF(TRIM[[#This Row],[Rough Thick]]=1.25,INDEX(Table1[5/4],MATCH(TRIM[[#This Row],[Width]],Table1[RIP SIZE],0)),IF(TRIM[[#This Row],[Rough Thick]]=1.5,INDEX(Table1[6/4],MATCH(TRIM[[#This Row],[Width]],Table1[RIP SIZE],0)),IF(TRIM[[#This Row],[Rough Thick]]=2,INDEX(Table1[8/4],MATCH(TRIM[[#This Row],[Width]],Table1[RIP SIZE],0)),"")))))*(1+$I$2),0) -> 0.7314 | N21: =IF(TRIM[[#This Row],[Width]]>6,INDEX(Table10[1 sorted],MATCH(TRIM[[#This Row],[Species]],Table10[Species],0)),INDEX(Table10[1],MATCH(TRIM[[#This Row],[Species]],Table10[Species],0))) -> 2.3 | O21: =TRIM[[#This Row],[Factor]]*TRIM[[#This Row],[Lin.Ft.]] -> 102.0303 | P21: =TRIM[[#This Row],[BF]]*TRIM[[#This Row],[Cost/BF]] -> 234.66969 | Q21: =IF(TRIM[[#This Row],[BF]]="","",P21*I$3) -> 58.667422 | R21: =$I$4 -> 175 | S21: =TRIM[[#This Row],[Lin.Ft.]]*$I$5 -> 118.575 | T21: =IF('Trim Take Off'!$C$17="custom",(TRIM[[#This Row],[Width]]+0.25)*$I$6,0) -> 550 | U21: =IFERROR(TRIM[[#This Row],[LF Add]]+TRIM[[#This Row],[Material Mark Up]]+TRIM[[#This Row],[Total Cost]],0) -> 411.91211 | V21: =IFERROR(TRIM[[#This Row],[Total Raw]]/TRIM[[#This Row],[Lin.Ft.]],"") -> 2.952775 | W21: =INDEX(finish[Rate],MATCH(TRIM[[#This Row],[FINISH HELP]],finish[Finish],0)) -> 1 | X21: =IFERROR((TRIM[[#This Row],[cost/L.F.]]*(1+$I$7)),"") -> 3.2480525 | Y21: =IFERROR(TRIM[[#This Row],[Knife Grind]]+TRIM[[#This Row],[Set-up]],"") -> 725
A22: =IF(TRIM[[#This Row],[Species]]=0,"",IF(TRIM[[#This Row],[Lin.Ft.]]>1,(MAX($A$14:$A21)+1),"")) | B22: ='Trim Take Off'!$C$20 -> Poplar | C22: =IF(TRIM[[#This Row],[Width]]>5.25,"LARGE",IF(TRIM[[#This Row],[Width]]>3,"AVG",IF(TRIM[[#This Row],[Width]]="","","SMALL"))) -> SMALL | D22: =IF(TRIM[[#This Row],[Species]]="","",IF(TRIM[[#This Row],[Species]]="POPLAR","PRIMED",IF(TRIM[[#This Row],[Species]]="MDF","PRIMED","STAINED"))) -> PRIMED | E22: =TRIM[[#This Row],[Finish]]&" "&TRIM[[#This Row],[Finish Size]] -> PRIMED SMALL | F22: DENTIL | G22: ='Trim Take Off'!$C$16&" "&TRIM[[#This Row],[Type]] -> CRAFTSMAN DENTIL | H22: =IFERROR(TRIM[[#This Row],[Species]]&" "&TRIM[[#This Row],[Finish]]&" "&TRIM[[#This Row],[Type]]&" "&TRIM[[#This Row],[Width]]&" x "&TRIM[[#This Row],[Thickness]],"") -> Poplar PRIMED DENTIL 0 x | I22: =IFERROR(INDEX(Table5[ACTUAL WIDTH],MATCH(TRIM[[#This Row],[NAME TYPE]],Table5[DESCRIPTION],0)),) -> 0 | J22: =IFERROR(INDEX(Table5[ACTUAL THICKNESS],MATCH(TRIM[[#This Row],[NAME TYPE]],Table5[DESCRIPTION],0)),"") | K22: =INDEX(lumber[Rough],MATCH(TRIM[[#This Row],[Thickness]],lumber[Finish],1)) -> #N/A | L22: =IFERROR(INDEX(Table5[LF],MATCH(TRIM[[#This Row],[NAME TYPE]],Table5[DESCRIPTION],0)),0) -> 0 | M22: =IFERROR((IF(TRIM[[#This Row],[Rough Thick]]=1,INDEX(Table1[4/4],MATCH(TRIM[[#This Row],[Width]],Table1[RIP SIZE],0)),IF(TRIM[[#This Row],[Rough Thick]]=1.25,INDEX(Table1[5/4],MATCH(TRIM[[#This Row],[Width]],Table1[RIP SIZE],0)),IF(TRIM[[#This Row],[Rough Thick]]=1.5,INDEX(Table1[6/4],MATCH(TRIM[[#This Row],[Width]],Table1[RIP SIZE],0)),IF(TRIM[[#This Row],[Rough Thick]]=2,INDEX(Table1[8/4],MATCH(TRIM[[#This Row],[Width]],Table1[RIP SIZE],0)),"")))))*(1+$I$2),0) -> 0 | N22: =IF(TRIM[[#This Row],[Width]]>6,INDEX(Table10[1 sorted],MATCH(TRIM[[#This Row],[Species]],Table10[Species],0)),INDEX(Table10[1],MATCH(TRIM[[#This Row],[Species]],Table10[Species],0))) -> 2.3 | O22: =TRIM[[#This Row],[Factor]]*TRIM[[#This Row],[Lin.Ft.]] -> 0 | P22: =TRIM[[#This Row],[BF]]*TRIM[[#This Row],[Cost/BF]] -> 0 | Q22: =IF(TRIM[[#This Row],[BF]]="","",P22*I$3) -> 0 | R22: =$I$4 -> 175 | S22: =TRIM[[#This Row],[Lin.Ft.]]*$I$5 -> 0 | T22: =IF('Trim Take Off'!$C$17="custom",(TRIM[[#This Row],[Width]]+0.25)*$I$6,0) -> 25 | U22: =IFERROR(TRIM[[#This Row],[LF Add]]+TRIM[[#This Row],[Material Mark Up]]+TRIM[[#This Row],[Total Cost]],0) -> 0 | V22: =IFERROR(TRIM[[#This Row],[Total Raw]]/TRIM[[#This Row],[Lin.Ft.]],"") | W22: =INDEX(finish[Rate],MATCH(TRIM[[#This Row],[FINISH HELP]],finish[Finish],0)) -> 0.85 | X22: =IFERROR((TRIM[[#This Row],[cost/L.F.]]*(1+$I$7)),"") | Y22: =IFERROR(TRIM[[#This Row],[Knife Grind]]+TRIM[[#This Row],[Set-up]],"") -> 200
A23: =IF(TRIM[[#This Row],[Species]]=0,"",IF(TRIM[[#This Row],[Lin.Ft.]]>1,(MAX($A$14:$A22)+1),"")) | B23: ='Trim Take Off'!$C$21 -> 0 | C23: =IF(TRIM[[#This Row],[Width]]>5.25,"LARGE",IF(TRIM[[#This Row],[Width]]>3,"AVG",IF(TRIM[[#This Row],[Width]]="","","SMALL"))) -> AVG | D23: =IF(TRIM[[#This Row],[Species]]="","",IF(TRIM[[#This Row],[Species]]="POPLAR","PRIMED",IF(TRIM[[#This Row],[Species]]="MDF","PRIMED","STAINED"))) -> STAINED | E23: =TRIM[[#This Row],[Finish]]&" "&TRIM[[#This Row],[Finish Size]] -> STAINED AVG | F23: BASE | G23: ='Trim Take Off'!$C$16&" "&TRIM[[#This Row],[Type]] -> CRAFTSMAN BASE | H23: =IFERROR(TRIM[[#This Row],[Species]]&" "&TRIM[[#This Row],[Finish]]&" "&TRIM[[#This Row],[Type]]&" "&TRIM[[#This Row],[Width]]&" x "&TRIM[[#This Row],[Thickness]],"") -> 0 STAINED BASE 5.25 x 0.5 | I23: =IFERROR(INDEX(Table5[ACTUAL WIDTH],MATCH(TRIM[[#This Row],[NAME TYPE]],Table5[DESCRIPTION],0)),) -> 5.25 | J23: =IFERROR(INDEX(Table5[ACTUAL THICKNESS],MATCH(TRIM[[#This Row],[NAME TYPE]],Table5[DESCRIPTION],0)),"") -> 0.5 | K23: =INDEX(lumber[Rough],MATCH(TRIM[[#This Row],[Thickness]],lumber[Finish],1)) -> 1 | L23: =IFERROR(INDEX(Table5[LF],MATCH(TRIM[[#This Row],[NAME TYPE]],Table5[DESCRIPTION],0)),0) -> 350 | M23: =IFERROR((IF(TRIM[[#This Row],[Rough Thick]]=1,INDEX(Table1[4/4],MATCH(TRIM[[#This Row],[Width]],Table1[RIP SIZE],0)),IF(TRIM[[#This Row],[Rough Thick]]=1.25,INDEX(Table1[5/4],MATCH(TRIM[[#This Row],[Width]],Table1[RIP SIZE],0)),IF(TRIM[[#This Row],[Rough Thick]]=1.5,INDEX(Table1[6/4],MATCH(TRIM[[#This Row],[Width]],Table1[RIP SIZE],0)),IF(TRIM[[#This Row],[Rough Thick]]=2,INDEX(Table1[8/4],MATCH(TRIM[[#This Row],[Width]],Table1[RIP SIZE],0)),"")))))*(1+$I$2),0) -> 0.7314 | N23: =IF(TRIM[[#This Row],[Width]]>6,INDEX(Table10[1 sorted],MATCH(TRIM[[#This Row],[Species]],Table10[Species],0)),INDEX(Table10[1],MATCH(TRIM[[#This Row],[Species]],Table10[Species],0))) -> #N/A | O23: =TRIM[[#This Row],[Factor]]*TRIM[[#This Row],[Lin.Ft.]] -> 255.99 | P23: =TRIM[[#This Row],[BF]]*TRIM[[#This Row],[Cost/BF]] -> #N/A | Q23: =IF(TRIM[[#This Row],[BF]]="","",P23*I$3) -> #N/A | R23: =$I$4 -> 175 | S23: =TRIM[[#This Row],[Lin.Ft.]]*$I$5 -> 297.5 | T23: =IF('Trim Take Off'!$C$17="custom",(TRIM[[#This Row],[Width]]+0.25)*$I$6,0) -> 550 | U23: =IFERROR(TRIM[[#This Row],[LF Add]]+TRIM[[#This Row],[Material Mark Up]]+TRIM[[#This Row],[Total Cost]],0) -> 0 | V23: =IFERROR(TRIM[[#This Row],[Total Raw]]/TRIM[[#This Row],[Lin.Ft.]],"") -> 0 | W23: =INDEX(finish[Rate],MATCH(TRIM[[#This Row],[FINISH HELP]],finish[Finish],0)) -> 2.25 | X23: =IFERROR((TRIM[[#This Row],[cost/L.F.]]*(1+$I$7)),"") -> 0 | Y23: =IFERROR(TRIM[[#This Row],[Knife Grind]]+TRIM[[#This Row],[Set-up]],"") -> 725
A24: =IF(TRIM[[#This Row],[Species]]=0,"",IF(TRIM[[#This Row],[Lin.Ft.]]>1,(MAX($A$14:$A23)+1),"")) | B24: ='Trim Take Off'!$C$21 -> 0 | C24: =IF(TRIM[[#This Row],[Width]]>5.25,"LARGE",IF(TRIM[[#This Row],[Width]]>3,"AVG",IF(TRIM[[#This Row],[Width]]="","","SMALL"))) -> AVG | D24: =IF(TRIM[[#This Row],[Species]]="","",IF(TRIM[[#This Row],[Species]]="POPLAR","PRIMED",IF(TRIM[[#This Row],[Species]]="MDF","PRIMED","STAINED"))) -> STAINED | E24: =TRIM[[#This Row],[Finish]]&" "&TRIM[[#This Row],[Finish Size]] -> STAINED AVG | F24: CASE | G24: ='Trim Take Off'!$C$16&" "&TRIM[[#This Row],[Type]] -> CRAFTSMAN CASE | H24: =IFERROR(TRIM[[#This Row],[Species]]&" "&TRIM[[#This Row],[Finish]]&" "&TRIM[[#This Row],[Type]]&" "&TRIM[[#This Row],[Width]]&" x "&TRIM[[#This Row],[Thickness]],"") -> 0 STAINED CASE 3.25 x 0.625 | I24: =IFERROR(INDEX(Table5[ACTUAL WIDTH],MATCH(TRIM[[#This Row],[NAME TYPE]],Table5[DESCRIPTION],0)),) -> 3.25 | J24: =IFERROR(INDEX(Table5[ACTUAL THICKNESS],MATCH(TRIM[[#This Row],[NAME TYPE]],Table5[DESCRIPTION],0)),"") -> 0.625 | K24: =INDEX(lumber[Rough],MATCH(TRIM[[#This Row],[Thickness]],lumber[Finish],1)) -> 1 | L24: =IFERROR(INDEX(Table5[LF],MATCH(TRIM[[#This Row],[NAME TYPE]],Table5[DESCRIPTION],0)),0) -> 714 | M24: =IFERROR((IF(TRIM[[#This Row],[Rough Thick]]=1,INDEX(Table1[4/4],MATCH(TRIM[[#This Row],[Width]],Table1[RIP SIZE],0)),IF(TRIM[[#This Row],[Rough Thick]]=1.25,INDEX(Table1[5/4],MATCH(TRIM[[#This Row],[Width]],Table1[RIP SIZE],0)),IF(TRIM[[#This Row],[Rough Thick]]=1.5,INDEX(Table1[6/4],MATCH(TRIM[[#This Row],[Width]],Table1[RIP SIZE],0)),IF(TRIM[[#This Row],[Rough Thick]]=2,INDEX(Table1[8/4],MATCH(TRIM[[#This Row],[Width]],Table1[RIP SIZE],0)),"")))))*(1+$I$2),0) -> 0.50025 | N24: =IF(TRIM[[#This Row],[Width]]>6,INDEX(Table10[1 sorted],MATCH(TRIM[[#This Row],[Species]],Table10[Species],0)),INDEX(Table10[1],MATCH(TRIM[[#This Row],[Species]],Table10[Species],0))) -> #N/A | O24: =TRIM[[#This Row],[Factor]]*TRIM[[#This Row],[Lin.Ft.]] -> 357.1785 | P24: =TRIM[[#This Row],[BF]]*TRIM[[#This Row],[Cost/BF]] -> #N/A | Q24: =IF(TRIM[[#This Row],[BF]]="","",P24*I$3) -> #N/A | R24: =$I$4 -> 175 | S24: =TRIM[[#This Row],[Lin.Ft.]]*$I$5 -> 606.9 | T24: =IF('Trim Take Off'!$C$17="custom",(TRIM[[#This Row],[Width]]+0.25)*$I$6,0) -> 350 | U24: =IFERROR(TRIM[[#This Row],[LF Add]]+TRIM[[#This Row],[Material Mark Up]]+TRIM[[#This Row],[Total Cost]],0) -> 0 | V24: =IFERROR(TRIM[[#This Row],[Total Raw]]/TRIM[[#This Row],[Lin.Ft.]],"") -> 0 | W24: =INDEX(finish[Rate],MATCH(TRIM[[#This Row],[FINISH HELP]],finish[Finish],0)) -> 2.25 | X24: =IFERROR((TRIM[[#This Row],[cost/L.F.]]*(1+$I$7)),"") -> 0 | Y24: =IFERROR(TRIM[[#This Row],[Knife Grind]]+TRIM[[#This Row],[Set-up]],"") -> 525
A25: =IF(TRIM[[#This Row],[Species]]=0,"",IF(TRIM[[#This Row],[Lin.Ft.]]>1,(MAX($A$14:$A24)+1),"")) | B25: ='Trim Take Off'!$C$21 -> 0 | C25: =IF(TRIM[[#This Row],[Width]]>5.25,"LARGE",IF(TRIM[[#This Row],[Width]]>3,"AVG",IF(TRIM[[#This Row],[Width]]="","","SMALL"))) -> AVG | D25: =IF(TRIM[[#This Row],[Species]]="","",IF(TRIM[[#This Row],[Species]]="POPLAR","PRIMED",IF(TRIM[[#This Row],[Species]]="MDF","PRIMED","STAINED"))) -> STAINED | E25: =TRIM[[#This Row],[Finish]]&" "&TRIM[[#This Row],[Finish Size]] -> STAINED AVG | F25: HEADER | G25: ='Trim Take Off'!$C$16&" "&TRIM[[#This Row],[Type]] -> CRAFTSMAN HEADER | H25: =IFERROR(TRIM[[#This Row],[Species]]&" "&TRIM[[#This Row],[Finish]]&" "&TRIM[[#This Row],[Type]]&" "&TRIM[[#This Row],[Width]]&" x "&TRIM[[#This Row],[Thickness]],"") -> 0 STAINED HEADER 5.25 x 0.875 | I25: =IFERROR(INDEX(Table5[ACTUAL WIDTH],MATCH(TRIM[[#This Row],[NAME TYPE]],Table5[DESCRIPTION],0)),) -> 5.25 | J25: =IFERROR(INDEX(Table5[ACTUAL THICKNESS],MATCH(TRIM[[#This Row],[NAME TYPE]],Table5[DESCRIPTION],0)),"") -> 0.875 | K25: =INDEX(lumber[Rough],MATCH(TRIM[[#This Row],[Thickness]],lumber[Finish],1)) -> 1 | L25: =IFERROR(INDEX(Table5[LF],MATCH(TRIM[[#This Row],[NAME TYPE]],Table5[DESCRIPTION],0)),0) -> 139.5 | M25: =IFERROR((IF(TRIM[[#This Row],[Rough Thick]]=1,INDEX(Table1[4/4],MATCH(TRIM[[#This Row],[Width]],Table1[RIP SIZE],0)),IF(TRIM[[#This Row],[Rough Thick]]=1.25,INDEX(Table1[5/4],MATCH(TRIM[[#This Row],[Width]],Table1[RIP SIZE],0)),IF(TRIM[[#This Row],[Rough Thick]]=1.5,INDEX(Table1[6/4],MATCH(TRIM[[#This Row],[Width]],Table1[RIP SIZE],0)),IF(TRIM[[#This Row],[Rough Thick]]=2,INDEX(Table1[8/4],MATCH(TRIM[[#This Row],[Width]],Table1[RIP SIZE],0)),"")))))*(1+$I$2),0) -> 0.7314 | N25: =IF(TRIM[[#This Row],[Width]]>6,INDEX(Table10[1 sorted],MATCH(TRIM[[#This Row],[Species]],Table10[Species],0)),INDEX(Table10[1],MATCH(TRIM[[#This Row],[Species]],Table10[Species],0))) -> #N/A | O25: =TRIM[[#This Row],[Factor]]*TRIM[[#This Row],[Lin.Ft.]] -> 102.0303 | P25: =TRIM[[#This Row],[BF]]*TRIM[[#This Row],[Cost/BF]] -> #N/A | Q25: =IF(TRIM[[#This Row],[BF]]="","",P25*I$3) -> #N/A | R25: =$I$4 -> 175 | S25: =TRIM[[#This Row],[Lin.Ft.]]*$I$5 -> 118.575 | T25: =IF('Trim Take Off'!$C$17="custom",(TRIM[[#This Row],[Width]]+0.25)*$I$6,0) -> 550 | U25: =IFERROR(TRIM[[#This Row],[LF Add]]+TRIM[[#This Row],[Material Mark Up]]+TRIM[[#This Row],[Total Cost]],0) -> 0 | V25: =IFERROR(TRIM[[#This Row],[Total Raw]]/TRIM[[#This Row],[Lin.Ft.]],"") -> 0 | W25: =INDEX(finish[Rate],MATCH(TRIM[[#This Row],[FINISH HELP]],finish[Finish],0)) -> 2.25 | X25: =IFERROR((TRIM[[#This Row],[cost/L.F.]]*(1+$I$7)),"") -> 0 | Y25: =IFERROR(TRIM[[#This Row],[Knife Grind]]+TRIM[[#This Row],[Set-up]],"") -> 725
A26: =IF(TRIM[[#This Row],[Species]]=0,"",IF(TRIM[[#This Row],[Lin.Ft.]]>1,(MAX($A$14:$A25)+1),"")) | B26: ='Trim Take Off'!$C$21 -> 0 | C26: =IF(TRIM[[#This Row],[Width]]>5.25,"LARGE",IF(TRIM[[#This Row],[Width]]>3,"AVG",IF(TRIM[[#This Row],[Width]]="","","SMALL"))) -> AVG | D26: =IF(TRIM[[#This Row],[Species]]="","",IF(TRIM[[#This Row],[Species]]="POPLAR","PRIMED",IF(TRIM[[#This Row],[Species]]="MDF","PRIMED","STAINED"))) -> STAINED | E26: =TRIM[[#This Row],[Finish]]&" "&TRIM[[#This Row],[Finish Size]] -> STAINED AVG | F26: INT JAMB | G26: ='Trim Take Off'!$C$16&" "&TRIM[[#This Row],[Type]] -> CRAFTSMAN INT JAMB | H26: =IFERROR(TRIM[[#This Row],[Species]]&" "&TRIM[[#This Row],[Finish]]&" "&TRIM[[#This Row],[Type]]&" "&TRIM[[#This Row],[Width]]&" x "&TRIM[[#This Row],[Thickness]],"") -> 0 STAINED INT JAMB 4.75 x 0.75 | I26: =IFERROR(INDEX(Table5[ACTUAL WIDTH],MATCH(TRIM[[#This Row],[NAME TYPE]],Table5[DESCRIPTION],0)),) -> 4.75 | J26: =IFERROR(INDEX(Table5[ACTUAL THICKNESS],MATCH(TRIM[[#This Row],[NAME TYPE]],Table5[DESCRIPTION],0)),"") -> 0.75 | K26: =INDEX(lumber[Rough],MATCH(TRIM[[#This Row],[Thickness]],lumber[Finish],1)) -> 1 | L26: =IFERROR(INDEX(Table5[LF],MATCH(TRIM[[#This Row],[NAME TYPE]],Table5[DESCRIPTION],0)),0) -> 21 | M26: =IFERROR((IF(TRIM[[#This Row],[Rough Thick]]=1,INDEX(Table1[4/4],MATCH(TRIM[[#This Row],[Width]],Table1[RIP SIZE],0)),IF(TRIM[[#This Row],[Rough Thick]]=1.25,INDEX(Table1[5/4],MATCH(TRIM[[#This Row],[Width]],Table1[RIP SIZE],0)),IF(TRIM[[#This Row],[Rough Thick]]=1.5,INDEX(Table1[6/4],MATCH(TRIM[[#This Row],[Width]],Table1[RIP SIZE],0)),IF(TRIM[[#This Row],[Rough Thick]]=2,INDEX(Table1[8/4],MATCH(TRIM[[#This Row],[Width]],Table1[RIP SIZE],0)),"")))))*(1+$I$2),0) -> 0.65665 | N26: =IF(TRIM[[#This Row],[Width]]>6,INDEX(Table10[1 sorted],MATCH(TRIM[[#This Row],[Species]],Table10[Species],0)),INDEX(Table10[1],MATCH(TRIM[[#This Row],[Species]],Table10[Species],0))) -> #N/A | O26: =TRIM[[#This Row],[Factor]]*TRIM[[#This Row],[Lin.Ft.]] -> 13.78965 | P26: =TRIM[[#This Row],[BF]]*TRIM[[#This Row],[Cost/BF]] -> #N/A | Q26: =IF(TRIM[[#This Row],[BF]]="","",P26*I$3) -> #N/A | R26: =$I$4 -> 175 | S26: =TRIM[[#This Row],[Lin.Ft.]]*$I$5 -> 17.85 | T26: =IF('Trim Take Off'!$C$17="custom",(TRIM[[#This Row],[Width]]+0.25)*$I$6,0) -> 500 | U26: =IFERROR(TRIM[[#This Row],[LF Add]]+TRIM[[#This Row],[Material Mark Up]]+TRIM[[#This Row],[Total Cost]],0) -> 0 | V26: =IFERROR(TRIM[[#This Row],[Total Raw]]/TRIM[[#This Row],[Lin.Ft.]],"") -> 0 | W26: =INDEX(finish[Rate],MATCH(TRIM[[#This Row],[FINISH HELP]],finish[Finish],0)) -> 2.25 | X26: =IFERROR((TRIM[[#This Row],[cost/L.F.]]*(1+$I$7)),"") -> 0 | Y26: =IFERROR(TRIM[[#This Row],[Knife Grind]]+TRIM[[#This Row],[Set-up]],"") -> 675
A27: =IF(TRIM[[#This Row],[Species]]=0,"",IF(TRIM[[#This Row],[Lin.Ft.]]>1,(MAX($A$14:$A26)+1),"")) | B27: ='Trim Take Off'!$C$21 -> 0 | C27: =IF(TRIM[[#This Row],[Width]]>5.25,"LARGE",IF(TRIM[[#This Row],[Width]]>3,"AVG",IF(TRIM[[#This Row],[Width]]="","","SMALL"))) -> LARGE | D27: =IF(TRIM[[#This Row],[Species]]="","",IF(TRIM[[#This Row],[Species]]="POPLAR","PRIMED",IF(TRIM[[#This Row],[Species]]="MDF","PRIMED","STAINED"))) -> STAINED | E27: =TRIM[[#This Row],[Finish]]&" "&TRIM[[#This Row],[Finish Size]] -> STAINED LARGE | F27: WINDOW JAMB | G27: ='Trim Take Off'!$C$16&" "&TRIM[[#This Row],[Type]] -> CRAFTSMAN WINDOW JAMB | H27: =IFERROR(TRIM[[#This Row],[Species]]&" "&TRIM[[#This Row],[Finish]]&" "&TRIM[[#This Row],[Type]]&" "&TRIM[[#This Row],[Width]]&" x "&TRIM[[#This Row],[Thickness]],"") -> 0 STAINED WINDOW JAMB 6 x 0.75 | I27: =IFERROR(INDEX(Table5[ACTUAL WIDTH],MATCH(TRIM[[#This Row],[NAME TYPE]],Table5[DESCRIPTION],0)),) -> 6 | J27: =IFERROR(INDEX(Table5[ACTUAL THICKNESS],MATCH(TRIM[[#This Row],[NAME TYPE]],Table5[DESCRIPTION],0)),"") -> 0.75 | K27: =INDEX(lumber[Rough],MATCH(TRIM[[#This Row],[Thickness]],lumber[Finish],1)) -> 1 | L27: =IFERROR(INDEX(Table5[LF],MATCH(TRIM[[#This Row],[NAME TYPE]],Table5[DESCRIPTION],0)),0) -> 273 | M27: =IFERROR((IF(TRIM[[#This Row],[Rough Thick]]=1,INDEX(Table1[4/4],MATCH(TRIM[[#This Row],[Width]],Table1[RIP SIZE],0)),IF(TRIM[[#This Row],[Rough Thick]]=1.25,INDEX(Table1[5/4],MATCH(TRIM[[#This Row],[Width]],Table1[RIP SIZE],0)),IF(TRIM[[#This Row],[Rough Thick]]=1.5,INDEX(Table1[6/4],MATCH(TRIM[[#This Row],[Width]],Table1[RIP SIZE],0)),IF(TRIM[[#This Row],[Rough Thick]]=2,INDEX(Table1[8/4],MATCH(TRIM[[#This Row],[Width]],Table1[RIP SIZE],0)),"")))))*(1+$I$2),0) -> 0.805 | N27: =IF(TRIM[[#This Row],[Width]]>6,INDEX(Table10[1 sorted],MATCH(TRIM[[#This Row],[Species]],Table10[Species],0)),INDEX(Table10[1],MATCH(TRIM[[#This Row],[Species]],Table10[Species],0))) -> #N/A | O27: =TRIM[[#This Row],[Factor]]*TRIM[[#This Row],[Lin.Ft.]] -> 219.765 | P27: =TRIM[[#This Row],[BF]]*TRIM[[#This Row],[Cost/BF]] -> #N/A | Q27: =IF(TRIM[[#This Row],[BF]]="","",P27*I$3) -> #N/A | R27: =$I$4 -> 175 | S27: =TRIM[[#This Row],[Lin.Ft.]]*$I$5 -> 232.05 | T27: =IF('Trim Take Off'!$C$17="custom",(TRIM[[#This Row],[Width]]+0.25)*$I$6,0) -> 625 | U27: =IFERROR(TRIM[[#This Row],[LF Add]]+TRIM[[#This Row],[Material Mark Up]]+TRIM[[#This Row],[Total Cost]],0) -> 0 | V27: =IFERROR(TRIM[[#This Row],[Total Raw]]/TRIM[[#This Row],[Lin.Ft.]],"") -> 0 | W27: =INDEX(finish[Rate],MATCH(TRIM[[#This Row],[FINISH HELP]],finish[Finish],0)) -> 2.5 | X27: =IFERROR((TRIM[[#This Row],[cost/L.F.]]*(1+$I$7)),"") -> 0 | Y27: =IFERROR(TRIM[[#This Row],[Knife Grind]]+TRIM[[#This Row],[Set-up]],"") -> 800
A28: =IF(TRIM[[#This Row],[Species]]=0,"",IF(TRIM[[#This Row],[Lin.Ft.]]>1,(MAX($A$14:$A27)+1),"")) | B28: ='Trim Take Off'!$C$21 -> 0 | C28: =IF(TRIM[[#This Row],[Width]]>5.25,"LARGE",IF(TRIM[[#This Row],[Width]]>3,"AVG",IF(TRIM[[#This Row],[Width]]="","","SMALL"))) -> LARGE | D28: =IF(TRIM[[#This Row],[Species]]="","",IF(TRIM[[#This Row],[Species]]="POPLAR","PRIMED",IF(TRIM[[#This Row],[Species]]="MDF","PRIMED","STAINED"))) -> STAINED | E28: =TRIM[[#This Row],[Finish]]&" "&TRIM[[#This Row],[Finish Size]] -> STAINED LARGE | F28: SILL | G28: ='Trim Take Off'!$C$16&" "&TRIM[[#This Row],[Type]] -> CRAFTSMAN SILL | H28: =IFERROR(TRIM[[#This Row],[Species]]&" "&TRIM[[#This Row],[Finish]]&" "&TRIM[[#This Row],[Type]]&" "&TRIM[[#This Row],[Width]]&" x "&TRIM[[#This Row],[Thickness]],"") -> 0 STAINED SILL 7.25 x 0.75 | I28: =IFERROR(INDEX(Table5[ACTUAL WIDTH],MATCH(TRIM[[#This Row],[NAME TYPE]],Table5[DESCRIPTION],0)),) -> 7.25 | J28: =IFERROR(INDEX(Table5[ACTUAL THICKNESS],MATCH(TRIM[[#This Row],[NAME TYPE]],Table5[DESCRIPTION],0)),"") -> 0.75 | K28: =INDEX(lumber[Rough],MATCH(TRIM[[#This Row],[Thickness]],lumber[Finish],1)) -> 1 | L28: =IFERROR(INDEX(Table5[LF],MATCH(TRIM[[#This Row],[NAME TYPE]],Table5[DESCRIPTION],0)),0) -> 139.5 | M28: =IFERROR((IF(TRIM[[#This Row],[Rough Thick]]=1,INDEX(Table1[4/4],MATCH(TRIM[[#This Row],[Width]],Table1[RIP SIZE],0)),IF(TRIM[[#This Row],[Rough Thick]]=1.25,INDEX(Table1[5/4],MATCH(TRIM[[#This Row],[Width]],Table1[RIP SIZE],0)),IF(TRIM[[#This Row],[Rough Thick]]=1.5,INDEX(Table1[6/4],MATCH(TRIM[[#This Row],[Width]],Table1[RIP SIZE],0)),IF(TRIM[[#This Row],[Rough Thick]]=2,INDEX(Table1[8/4],MATCH(TRIM[[#This Row],[Width]],Table1[RIP SIZE],0)),"")))))*(1+$I$2),0) -> 0.93035 | N28: =IF(TRIM[[#This Row],[Width]]>6,INDEX(Table10[1 sorted],MATCH(TRIM[[#This Row],[Species]],Table10[Species],0)),INDEX(Table10[1],MATCH(TRIM[[#This Row],[Species]],Table10[Species],0))) -> #N/A | O28: =TRIM[[#This Row],[Factor]]*TRIM[[#This Row],[Lin.Ft.]] -> 129.78383 | P28: =TRIM[[#This Row],[BF]]*TRIM[[#This Row],[Cost/BF]] -> #N/A | Q28: =IF(TRIM[[#This Row],[BF]]="","",P28*I$3) -> #N/A | R28: =$I$4 -> 175 | S28: =TRIM[[#This Row],[Lin.Ft.]]*$I$5 -> 118.575 | T28: =IF('Trim Take Off'!$C$17="custom",(TRIM[[#This Row],[Width]]+0.25)*$I$6,0) -> 750 | U28: =IFERROR(TRIM[[#This Row],[LF Add]]+TRIM[[#This Row],[Material Mark Up]]+TRIM[[#This Row],[Total Cost]],0) -> 0 | V28: =IFERROR(TRIM[[#This Row],[Total Raw]]/TRIM[[#This Row],[Lin.Ft.]],"") -> 0 | W28: =INDEX(finish[Rate],MATCH(TRIM[[#This Row],[FINISH HELP]],finish[Finish],0)) -> 2.5 | X28: =IFERROR((TRIM[[#This Row],[cost/L.F.]]*(1+$I$7)),"") -> 0 | Y28: =IFERROR(TRIM[[#This Row],[Knife Grind]]+TRIM[[#This Row],[Set-up]],"") -> 925
A29: =IF(TRIM[[#This Row],[Species]]=0,"",IF(TRIM[[#This Row],[Lin.Ft.]]>1,(MAX($A$14:$A28)+1),"")) | B29: ='Trim Take Off'!$C$21 -> 0 | C29: =IF(TRIM[[#This Row],[Width]]>5.25,"LARGE",IF(TRIM[[#This Row],[Width]]>3,"AVG",IF(TRIM[[#This Row],[Width]]="","","SMALL"))) -> AVG | D29: =IF(TRIM[[#This Row],[Species]]="","",IF(TRIM[[#This Row],[Species]]="POPLAR","PRIMED",IF(TRIM[[#This Row],[Species]]="MDF","PRIMED","STAINED"))) -> STAINED | E29: =TRIM[[#This Row],[Finish]]&" "&TRIM[[#This Row],[Finish Size]] -> STAINED AVG | F29: APRON | G29: ='Trim Take Off'!$C$16&" "&TRIM[[#This Row],[Type]] -> CRAFTSMAN APRON | H29: =IFERROR(TRIM[[#This Row],[Species]]&" "&TRIM[[#This Row],[Finish]]&" "&TRIM[[#This Row],[Type]]&" "&TRIM[[#This Row],[Width]]&" x "&TRIM[[#This Row],[Thickness]],"") -> 0 STAINED APRON 5.25 x 0.5 | I29: =IFERROR(INDEX(Table5[ACTUAL WIDTH],MATCH(TRIM[[#This Row],[NAME TYPE]],Table5[DESCRIPTION],0)),) -> 5.25 | J29: =IFERROR(INDEX(Table5[ACTUAL THICKNESS],MATCH(TRIM[[#This Row],[NAME TYPE]],Table5[DESCRIPTION],0)),"") -> 0.5 | K29: =INDEX(lumber[Rough],MATCH(TRIM[[#This Row],[Thickness]],lumber[Finish],1)) -> 1 | L29: =IFERROR(INDEX(Table5[LF],MATCH(TRIM[[#This Row],[NAME TYPE]],Table5[DESCRIPTION],0)),0) -> 139.5 | M29: =IFERROR((IF(TRIM[[#This Row],[Rough Thick]]=1,INDEX(Table1[4/4],MATCH(TRIM[[#This Row],[Width]],Table1[RIP SIZE],0)),IF(TRIM[[#This Row],[Rough Thick]]=1.25,INDEX(Table1[5/4],MATCH(TRIM[[#This Row],[Width]],Table1[RIP SIZE],0)),IF(TRIM[[#This Row],[Rough Thick]]=1.5,INDEX(Table1[6/4],MATCH(TRIM[[#This Row],[Width]],Table1[RIP SIZE],0)),IF(TRIM[[#This Row],[Rough Thick]]=2,INDEX(Table1[8/4],MATCH(TRIM[[#This Row],[Width]],Table1[RIP SIZE],0)),"")))))*(1+$I$2),0) -> 0.7314 | N29: =IF(TRIM[[#This Row],[Width]]>6,INDEX(Table10[1 sorted],MATCH(TRIM[[#This Row],[Species]],Table10[Species],0)),INDEX(Table10[1],MATCH(TRIM[[#This Row],[Species]],Table10[Species],0))) -> #N/A | O29: =TRIM[[#This Row],[Factor]]*TRIM[[#This Row],[Lin.Ft.]] -> 102.0303 | P29: =TRIM[[#This Row],[BF]]*TRIM[[#This Row],[Cost/BF]] -> #N/A | Q29: =IF(TRIM[[#This Row],[BF]]="","",P29*I$3) -> #N/A | R29: =$I$4 -> 175 | S29: =TRIM[[#This Row],[Lin.Ft.]]*$I$5 -> 118.575 | T29: =IF('Trim Take Off'!$C$17="custom",(TRIM[[#This Row],[Width]]+0.25)*$I$6,0) -> 550 | U29: =IFERROR(TRIM[[#This Row],[LF Add]]+TRIM[[#This Row],[Material Mark Up]]+TRIM[[#This Row],[Total Cost]],0) -> 0 | V29: =IFERROR(TRIM[[#This Row],[Total Raw]]/TRIM[[#This Row],[Lin.Ft.]],"") -> 0 | W29: =INDEX(finish[Rate],MATCH(TRIM[[#This Row],[FINISH HELP]],finish[Finish],0)) -> 2.25 | X29: =IFERROR((TRIM[[#This Row],[cost/L.F.]]*(1+$I$7)),"") -> 0 | Y29: =IFERROR(TRIM[[#This Row],[Knife Grind]]+TRIM[[#This Row],[Set-up]],"") -> 725
A30: =IF(TRIM[[#This Row],[Species]]=0,"",IF(TRIM[[#This Row],[Lin.Ft.]]>1,(MAX($A$14:$A29)+1),"")) | B30: ='Trim Take Off'!$C$21 -> 0 | C30: =IF(TRIM[[#This Row],[Width]]>5.25,"LARGE",IF(TRIM[[#This Row],[Width]]>3,"AVG",IF(TRIM[[#This Row],[Width]]="","","SMALL"))) -> SMALL | D30: =IF(TRIM[[#This Row],[Species]]="","",IF(TRIM[[#This Row],[Species]]="POPLAR","PRIMED",IF(TRIM[[#This Row],[Species]]="MDF","PRIMED","STAINED"))) -> STAINED | E30: =TRIM[[#This Row],[Finish]]&" "&TRIM[[#This Row],[Finish Size]] -> STAINED SMALL | F30: DENTIL | G30: ='Trim Take Off'!$C$16&" "&TRIM[[#This Row],[Type]] -> CRAFTSMAN DENTIL | H30: =IFERROR(TRIM[[#This Row],[Species]]&" "&TRIM[[#This Row],[Finish]]&" "&TRIM[[#This Row],[Type]]&" "&TRIM[[#This Row],[Width]]&" x "&TRIM[[#This Row],[Thickness]],"") -> 0 STAINED DENTIL 0 x | I30: =IFERROR(INDEX(Table5[ACTUAL WIDTH],MATCH(TRIM[[#This Row],[NAME TYPE]],Table5[DESCRIPTION],0)),) -> 0 | J30: =IFERROR(INDEX(Table5[ACTUAL THICKNESS],MATCH(TRIM[[#This Row],[NAME TYPE]],Table5[DESCRIPTION],0)),"") | K30: =INDEX(lumber[Rough],MATCH(TRIM[[#This Row],[Thickness]],lumber[Finish],1)) -> #N/A | L30: =IFERROR(INDEX(Table5[LF],MATCH(TRIM[[#This Row],[NAME TYPE]],Table5[DESCRIPTION],0)),0) -> 0 | M30: =IFERROR((IF(TRIM[[#This Row],[Rough Thick]]=1,INDEX(Table1[4/4],MATCH(TRIM[[#This Row],[Width]],Table1[RIP SIZE],0)),IF(TRIM[[#This Row],[Rough Thick]]=1.25,INDEX(Table1[5/4],MATCH(TRIM[[#This Row],[Width]],Table1[RIP SIZE],0)),IF(TRIM[[#This Row],[Rough Thick]]=1.5,INDEX(Table1[6/4],MATCH(TRIM[[#This Row],[Width]],Table1[RIP SIZE],0)),IF(TRIM[[#This Row],[Rough Thick]]=2,INDEX(Table1[8/4],MATCH(TRIM[[#This Row],[Width]],Table1[RIP SIZE],0)),"")))))*(1+$I$2),0) -> 0 | N30: =IF(TRIM[[#This Row],[Width]]>6,INDEX(Table10[1 sorted],MATCH(TRIM[[#This Row],[Species]],Table10[Species],0)),INDEX(Table10[1],MATCH(TRIM[[#This Row],[Species]],Table10[Species],0))) -> #N/A | O30: =TRIM[[#This Row],[Factor]]*TRIM[[#This Row],[Lin.Ft.]] -> 0 | P30: =TRIM[[#This Row],[BF]]*TRIM[[#This Row],[Cost/BF]] -> #N/A | Q30: =IF(TRIM[[#This Row],[BF]]="","",P30*I$3) -> #N/A | R30: =$I$4 -> 175 | S30: =TRIM[[#This Row],[Lin.Ft.]]*$I$5 -> 0 | T30: =IF('Trim Take Off'!$C$17="custom",(TRIM[[#This Row],[Width]]+0.25)*$I$6,0) -> 25 | U30: =IFERROR(TRIM[[#This Row],[LF Add]]+TRIM[[#This Row],[Material Mark Up]]+TRIM[[#This Row],[Total Cost]],0) -> 0 | V30: =IFERROR(TRIM[[#This Row],[Total Raw]]/TRIM[[#This Row],[Lin.Ft.]],"") | W30: =INDEX(finish[Rate],MATCH(TRIM[[#This Row],[FINISH HELP]],finish[Finish],0)) -> 2 | X30: =IFERROR((TRIM[[#This Row],[cost/L.F.]]*(1+$I$7)),"") | Y30: =IFERROR(TRIM[[#This Row],[Knife Grind]]+TRIM[[#This Row],[Set-up]],"") -> 200
A31: =IF(TRIM[[#This Row],[Species]]=0,"",IF(TRIM[[#This Row],[Lin.Ft.]]>1,(MAX($A$14:$A30)+1),"")) | B31: ='Trim Take Off'!$C$22 -> 0 | C31: =IF(TRIM[[#This Row],[Width]]>5.25,"LARGE",IF(TRIM[[#This Row],[Width]]>3,"AVG",IF(TRIM[[#This Row],[Width]]="","","SMALL"))) -> AVG | D31: =IF(TRIM[[#This Row],[Species]]="","",IF(TRIM[[#This Row],[Species]]="POPLAR","PRIMED",IF(TRIM[[#This Row],[Species]]="MDF","PRIMED","STAINED"))) -> STAINED | E31: =TRIM[[#This Row],[Finish]]&" "&TRIM[[#This Row],[Finish Size]] -> STAINED AVG | F31: BASE | G31: ='Trim Take Off'!$C$16&" "&TRIM[[#This Row],[Type]] -> CRAFTSMAN BASE | H31: =IFERROR(TRIM[[#This Row],[Species]]&" "&TRIM[[#This Row],[Finish]]&" "&TRIM[[#This Row],[Type]]&" "&TRIM[[#This Row],[Width]]&" x "&TRIM[[#This Row],[Thickness]],"") -> 0 STAINED BASE 5.25 x 0.5 | I31: =IFERROR(INDEX(Table5[ACTUAL WIDTH],MATCH(TRIM[[#This Row],[NAME TYPE]],Table5[DESCRIPTION],0)),) -> 5.25 | J31: =IFERROR(INDEX(Table5[ACTUAL THICKNESS],MATCH(TRIM[[#This Row],[NAME TYPE]],Table5[DESCRIPTION],0)),"") -> 0.5 | K31: =INDEX(lumber[Rough],MATCH(TRIM[[#This Row],[Thickness]],lumber[Finish],1)) -> 1 | L31: =IFERROR(INDEX(Table5[LF],MATCH(TRIM[[#This Row],[NAME TYPE]],Table5[DESCRIPTION],0)),0) -> 350 | M31: =IFERROR((IF(TRIM[[#This Row],[Rough Thick]]=1,INDEX(Table1[4/4],MATCH(TRIM[[#This Row],[Width]],Table1[RIP SIZE],0)),IF(TRIM[[#This Row],[Rough Thick]]=1.25,INDEX(Table1[5/4],MATCH(TRIM[[#This Row],[Width]],Table1[RIP SIZE],0)),IF(TRIM[[#This Row],[Rough Thick]]=1.5,INDEX(Table1[6/4],MATCH(TRIM[[#This Row],[Width]],Table1[RIP SIZE],0)),IF(TRIM[[#This Row],[Rough Thick]]=2,INDEX(Table1[8/4],MATCH(TRIM[[#This Row],[Width]],Table1[RIP SIZE],0)),"")))))*(1+$I$2),0) -> 0.7314 | N31: =IF(TRIM[[#This Row],[Width]]>6,INDEX(Table10[1 sorted],MATCH(TRIM[[#This Row],[Species]],Table10[Species],0)),INDEX(Table10[1],MATCH(TRIM[[#This Row],[Species]],Table10[Species],0))) -> #N/A | O31: =TRIM[[#This Row],[Factor]]*TRIM[[#This Row],[Lin.Ft.]] -> 255.99 | P31: =TRIM[[#This Row],[BF]]*TRIM[[#This Row],[Cost/BF]] -> #N/A | Q31: =IF(TRIM[[#This Row],[BF]]="","",P31*I$3) -> #N/A | R31: =$I$4 -> 175 | S31: =TRIM[[#This Row],[Lin.Ft.]]*$I$5 -> 297.5 | T31: =IF('Trim Take Off'!$C$17="custom",(TRIM[[#This Row],[Width]]+0.25)*$I$6,0) -> 550 | U31: =IFERROR(TRIM[[#This Row],[LF Add]]+TRIM[[#This Row],[Material Mark Up]]+TRIM[[#This Row],[Total Cost]],0) -> 0 | V31: =IFERROR(TRIM[[#This Row],[Total Raw]]/TRIM[[#This Row],[Lin.Ft.]],"") -> 0 | W31: =INDEX(finish[Rate],MATCH(TRIM[[#This Row],[FINISH HELP]],finish[Finish],0)) -> 2.25 | X31: =IFERROR((TRIM[[#This Row],[cost/L.F.]]*(1+$I$7)),"") -> 0 | Y31: =IFERROR(TRIM[[#This Row],[Knife Grind]]+TRIM[[#This Row],[Set-up]],"") -> 725
A32: =IF(TRIM[[#This Row],[Species]]=0,"",IF(TRIM[[#This Row],[Lin.Ft.]]>1,(MAX($A$14:$A31)+1),"")) | B32: ='Trim Take Off'!$C$22 -> 0 | C32: =IF(TRIM[[#This Row],[Width]]>5.25,"LARGE",IF(TRIM[[#This Row],[Width]]>3,"AVG",IF(TRIM[[#This Row],[Width]]="","","SMALL"))) -> AVG | D32: =IF(TRIM[[#This Row],[Species]]="","",IF(TRIM[[#This Row],[Species]]="POPLAR","PRIMED",IF(TRIM[[#This Row],[Species]]="MDF","PRIMED","STAINED"))) -> STAINED | E32: =TRIM[[#This Row],[Finish]]&" "&TRIM[[#This Row],[Finish Size]] -> STAINED AVG | F32: CASE | G32: ='Trim Take Off'!$C$16&" "&TRIM[[#This Row],[Type]] -> CRAFTSMAN CASE | H32: =IFERROR(TRIM[[#This Row],[Species]]&" "&TRIM[[#This Row],[Finish]]&" "&TRIM[[#This Row],[Type]]&" "&TRIM[[#This Row],[Width]]&" x "&TRIM[[#This Row],[Thickness]],"") -> 0 STAINED CASE 3.25 x 0.625 | I32: =IFERROR(INDEX(Table5[ACTUAL WIDTH],MATCH(TRIM[[#This Row],[NAME TYPE]],Table5[DESCRIPTION],0)),) -> 3.25 | J32: =IFERROR(INDEX(Table5[ACTUAL THICKNESS],MATCH(TRIM[[#This Row],[NAME TYPE]],Table5[DESCRIPTION],0)),"") -> 0.625 | K32: =INDEX(lumber[Rough],MATCH(TRIM[[#This Row],[Thickness]],lumber[Finish],1)) -> 1 | L32: =IFERROR(INDEX(Table5[LF],MATCH(TRIM[[#This Row],[NAME TYPE]],Table5[DESCRIPTION],0)),0) -> 714 | M32: =IFERROR((IF(TRIM[[#This Row],[Rough Thick]]=1,INDEX(Table1[4/4],MATCH(TRIM[[#This Row],[Width]],Table1[RIP SIZE],0)),IF(TRIM[[#This Row],[Rough Thick]]=1.25,INDEX(Table1[5/4],MATCH(TRIM[[#This Row],[Width]],Table1[RIP SIZE],0)),IF(TRIM[[#This Row],[Rough Thick]]=1.5,INDEX(Table1[6/4],MATCH(TRIM[[#This Row],[Width]],Table1[RIP SIZE],0)),IF(TRIM[[#This Row],[Rough Thick]]=2,INDEX(Table1[8/4],MATCH(TRIM[[#This Row],[Width]],Table1[RIP SIZE],0)),"")))))*(1+$I$2),0) -> 0.50025 | N32: =IF(TRIM[[#This Row],[Width]]>6,INDEX(Table10[1 sorted],MATCH(TRIM[[#This Row],[Species]],Table10[Species],0)),INDEX(Table10[1],MATCH(TRIM[[#This Row],[Species]],Table10[Species],0))) -> #N/A | O32: =TRIM[[#This Row],[Factor]]*TRIM[[#This Row],[Lin.Ft.]] -> 357.1785 | P32: =TRIM[[#This Row],[BF]]*TRIM[[#This Row],[Cost/BF]] -> #N/A | Q32: =IF(TRIM[[#This Row],[BF]]="","",P32*I$3) -> #N/A | R32: =$I$4 -> 175 | S32: =TRIM[[#This Row],[Lin.Ft.]]*$I$5 -> 606.9 | T32: =IF('Trim Take Off'!$C$17="custom",(TRIM[[#This Row],[Width]]+0.25)*$I$6,0) -> 350 | U32: =IFERROR(TRIM[[#This Row],[LF Add]]+TRIM[[#This Row],[Material Mark Up]]+TRIM[[#This Row],[Total Cost]],0) -> 0 | V32: =IFERROR(TRIM[[#This Row],[Total Raw]]/TRIM[[#This Row],[Lin.Ft.]],"") -> 0 | W32: =INDEX(finish[Rate],MATCH(TRIM[[#This Row],[FINISH HELP]],finish[Finish],0)) -> 2.25 | X32: =IFERROR((TRIM[[#This Row],[cost/L.F.]]*(1+$I$7)),"") -> 0 | Y32: =IFERROR(TRIM[[#This Row],[Knife Grind]]+TRIM[[#This Row],[Set-up]],"") -> 525
A33: =IF(TRIM[[#This Row],[Species]]=0,"",IF(TRIM[[#This Row],[Lin.Ft.]]>1,(MAX($A$14:$A32)+1),"")) | B33: ='Trim Take Off'!$C$22 -> 0 | C33: =IF(TRIM[[#This Row],[Width]]>5.25,"LARGE",IF(TRIM[[#This Row],[Width]]>3,"AVG",IF(TRIM[[#This Row],[Width]]="","","SMALL"))) -> AVG | D33: =IF(TRIM[[#This Row],[Species]]="","",IF(TRIM[[#This Row],[Species]]="POPLAR","PRIMED",IF(TRIM[[#This Row],[Species]]="MDF","PRIMED","STAINED"))) -> STAINED | E33: =TRIM[[#This Row],[Finish]]&" "&TRIM[[#This Row],[Finish Size]] -> STAINED AVG | F33: HEADER | G33: ='Trim Take Off'!$C$16&" "&TRIM[[#This Row],[Type]] -> CRAFTSMAN HEADER | H33: =IFERROR(TRIM[[#This Row],[Species]]&" "&TRIM[[#This Row],[Finish]]&" "&TRIM[[#This Row],[Type]]&" "&TRIM[[#This Row],[Width]]&" x "&TRIM[[#This Row],[Thickness]],"") -> 0 STAINED HEADER 5.25 x 0.875 | I33: =IFERROR(INDEX(Table5[ACTUAL WIDTH],MATCH(TRIM[[#This Row],[NAME TYPE]],Table5[DESCRIPTION],0)),) -> 5.25 | J33: =IFERROR(INDEX(Table5[ACTUAL THICKNESS],MATCH(TRIM[[#This Row],[NAME TYPE]],Table5[DESCRIPTION],0)),"") -> 0.875 | K33: =INDEX(lumber[Rough],MATCH(TRIM[[#This Row],[Thickness]],lumber[Finish],1)) -> 1 | L33: =IFERROR(INDEX(Table5[LF],MATCH(TRIM[[#This Row],[NAME TYPE]],Table5[DESCRIPTION],0)),0) -> 139.5 | M33: =IFERROR((IF(TRIM[[#This Row],[Rough Thick]]=1,INDEX(Table1[4/4],MATCH(TRIM[[#This Row],[Width]],Table1[RIP SIZE],0)),IF(TRIM[[#This Row],[Rough Thick]]=1.25,INDEX(Table1[5/4],MATCH(TRIM[[#This Row],[Width]],Table1[RIP SIZE],0)),IF(TRIM[[#This Row],[Rough Thick]]=1.5,INDEX(Table1[6/4],MATCH(TRIM[[#This Row],[Width]],Table1[RIP SIZE],0)),IF(TRIM[[#This Row],[Rough Thick]]=2,INDEX(Table1[8/4],MATCH(TRIM[[#This Row],[Width]],Table1[RIP SIZE],0)),"")))))*(1+$I$2),0) -> 0.7314 | N33: =IF(TRIM[[#This Row],[Width]]>6,INDEX(Table10[1 sorted],MATCH(TRIM[[#This Row],[Species]],Table10[Species],0)),INDEX(Table10[1],MATCH(TRIM[[#This Row],[Species]],Table10[Species],0))) -> #N/A | O33: =TRIM[[#This Row],[Factor]]*TRIM[[#This Row],[Lin.Ft.]] -> 102.0303 | P33: =TRIM[[#This Row],[BF]]*TRIM[[#This Row],[Cost/BF]] -> #N/A | Q33: =IF(TRIM[[#This Row],[BF]]="","",P33*I$3) -> #N/A | R33: =$I$4 -> 175 | S33: =TRIM[[#This Row],[Lin.Ft.]]*$I$5 -> 118.575 | T33: =IF('Trim Take Off'!$C$17="custom",(TRIM[[#This Row],[Width]]+0.25)*$I$6,0) -> 550 | U33: =IFERROR(TRIM[[#This Row],[LF Add]]+TRIM[[#This Row],[Material Mark Up]]+TRIM[[#This Row],[Total Cost]],0) -> 0 | V33: =IFERROR(TRIM[[#This Row],[Total Raw]]/TRIM[[#This Row],[Lin.Ft.]],"") -> 0 | W33: =INDEX(finish[Rate],MATCH(TRIM[[#This Row],[FINISH HELP]],finish[Finish],0)) -> 2.25 | X33: =IFERROR((TRIM[[#This Row],[cost/L.F.]]*(1+$I$7)),"") -> 0 | Y33: =IFERROR(TRIM[[#This Row],[Knife Grind]]+TRIM[[#This Row],[Set-up]],"") -> 725
A34: =IF(TRIM[[#This Row],[Species]]=0,"",IF(TRIM[[#This Row],[Lin.Ft.]]>1,(MAX($A$14:$A33)+1),"")) | B34: ='Trim Take Off'!$C$22 -> 0 | C34: =IF(TRIM[[#This Row],[Width]]>5.25,"LARGE",IF(TRIM[[#This Row],[Width]]>3,"AVG",IF(TRIM[[#This Row],[Width]]="","","SMALL"))) -> AVG | D34: =IF(TRIM[[#This Row],[Species]]="","",IF(TRIM[[#This Row],[Species]]="POPLAR","PRIMED",IF(TRIM[[#This Row],[Species]]="MDF","PRIMED","STAINED"))) -> STAINED | E34: =TRIM[[#This Row],[Finish]]&" "&TRIM[[#This Row],[Finish Size]] -> STAINED AVG | F34: INT JAMB | G34: ='Trim Take Off'!$C$16&" "&TRIM[[#This Row],[Type]] -> CRAFTSMAN INT JAMB | H34: =IFERROR(TRIM[[#This Row],[Species]]&" "&TRIM[[#This Row],[Finish]]&" "&TRIM[[#This Row],[Type]]&" "&TRIM[[#This Row],[Width]]&" x "&TRIM[[#This Row],[Thickness]],"") -> 0 STAINED INT JAMB 4.75 x 0.75 | I34: =IFERROR(INDEX(Table5[ACTUAL WIDTH],MATCH(TRIM[[#This Row],[NAME TYPE]],Table5[DESCRIPTION],0)),) -> 4.75 | J34: =IFERROR(INDEX(Table5[ACTUAL THICKNESS],MATCH(TRIM[[#This Row],[NAME TYPE]],Table5[DESCRIPTION],0)),"") -> 0.75 | K34: =INDEX(lumber[Rough],MATCH(TRIM[[#This Row],[Thickness]],lumber[Finish],1)) -> 1 | L34: =IFERROR(INDEX(Table5[LF],MATCH(TRIM[[#This Row],[NAME TYPE]],Table5[DESCRIPTION],0)),0) -> 21 | M34: =IFERROR((IF(TRIM[[#This Row],[Rough Thick]]=1,INDEX(Table1[4/4],MATCH(TRIM[[#This Row],[Width]],Table1[RIP SIZE],0)),IF(TRIM[[#This Row],[Rough Thick]]=1.25,INDEX(Table1[5/4],MATCH(TRIM[[#This Row],[Width]],Table1[RIP SIZE],0)),IF(TRIM[[#This Row],[Rough Thick]]=1.5,INDEX(Table1[6/4],MATCH(TRIM[[#This Row],[Width]],Table1[RIP SIZE],0)),IF(TRIM[[#This Row],[Rough Thick]]=2,INDEX(Table1[8/4],MATCH(TRIM[[#This Row],[Width]],Table1[RIP SIZE],0)),"")))))*(1+$I$2),0) -> 0.65665 | N34: =IF(TRIM[[#This Row],[Width]]>6,INDEX(Table10[1 sorted],MATCH(TRIM[[#This Row],[Species]],Table10[Species],0)),INDEX(Table10[1],MATCH(TRIM[[#This Row],[Species]],Table10[Species],0))) -> #N/A | O34: =TRIM[[#This Row],[Factor]]*TRIM[[#This Row],[Lin.Ft.]] -> 13.78965 | P34: =TRIM[[#This Row],[BF]]*TRIM[[#This Row],[Cost/BF]] -> #N/A | Q34: =IF(TRIM[[#This Row],[BF]]="","",P34*I$3) -> #N/A | R34: =$I$4 -> 175 | S34: =TRIM[[#This Row],[Lin.Ft.]]*$I$5 -> 17.85 | T34: =IF('Trim Take Off'!$C$17="custom",(TRIM[[#This Row],[Width]]+0.25)*$I$6,0) -> 500 | U34: =IFERROR(TRIM[[#This Row],[LF Add]]+TRIM[[#This Row],[Material Mark Up]]+TRIM[[#This Row],[Total Cost]],0) -> 0 | V34: =IFERROR(TRIM[[#This Row],[Total Raw]]/TRIM[[#This Row],[Lin.Ft.]],"") -> 0 | W34: =INDEX(finish[Rate],MATCH(TRIM[[#This Row],[FINISH HELP]],finish[Finish],0)) -> 2.25 | X34: =IFERROR((TRIM[[#This Row],[cost/L.F.]]*(1+$I$7)),"") -> 0 | Y34: =IFERROR(TRIM[[#This Row],[Knife Grind]]+TRIM[[#This Row],[Set-up]],"") -> 675
A35: =IF(TRIM[[#This Row],[Species]]=0,"",IF(TRIM[[#This Row],[Lin.Ft.]]>1,(MAX($A$14:$A34)+1),"")) | B35: ='Trim Take Off'!$C$22 -> 0 | C35: =IF(TRIM[[#This Row],[Width]]>5.25,"LARGE",IF(TRIM[[#This Row],[Width]]>3,"AVG",IF(TRIM[[#This Row],[Width]]="","","SMALL"))) -> LARGE | D35: =IF(TRIM[[#This Row],[Species]]="","",IF(TRIM[[#This Row],[Species]]="POPLAR","PRIMED",IF(TRIM[[#This Row],[Species]]="MDF","PRIMED","STAINED"))) -> STAINED | E35: =TRIM[[#This Row],[Finish]]&" "&TRIM[[#This Row],[Finish Size]] -> STAINED LARGE | F35: WINDOW JAMB | G35: ='Trim Take Off'!$C$16&" "&TRIM[[#This Row],[Type]] -> CRAFTSMAN WINDOW JAMB | H35: =IFERROR(TRIM[[#This Row],[Species]]&" "&TRIM[[#This Row],[Finish]]&" "&TRIM[[#This Row],[Type]]&" "&TRIM[[#This Row],[Width]]&" x "&TRIM[[#This Row],[Thickness]],"") -> 0 STAINED WINDOW JAMB 6 x 0.75 | I35: =IFERROR(INDEX(Table5[ACTUAL WIDTH],MATCH(TRIM[[#This Row],[NAME TYPE]],Table5[DESCRIPTION],0)),) -> 6 | J35: =IFERROR(INDEX(Table5[ACTUAL THICKNESS],MATCH(TRIM[[#This Row],[NAME TYPE]],Table5[DESCRIPTION],0)),"") -> 0.75 | K35: =INDEX(lumber[Rough],MATCH(TRIM[[#This Row],[Thickness]],lumber[Finish],1)) -> 1 | L35: =IFERROR(INDEX(Table5[LF],MATCH(TRIM[[#This Row],[NAME TYPE]],Table5[DESCRIPTION],0)),0) -> 273 | M35: =IFERROR((IF(TRIM[[#This Row],[Rough Thick]]=1,INDEX(Table1[4/4],MATCH(TRIM[[#This Row],[Width]],Table1[RIP SIZE],0)),IF(TRIM[[#This Row],[Rough Thick]]=1.25,INDEX(Table1[5/4],MATCH(TRIM[[#This Row],[Width]],Table1[RIP SIZE],0)),IF(TRIM[[#This Row],[Rough Thick]]=1.5,INDEX(Table1[6/4],MATCH(TRIM[[#This Row],[Width]],Table1[RIP SIZE],0)),IF(TRIM[[#This Row],[Rough Thick]]=2,INDEX(Table1[8/4],MATCH(TRIM[[#This Row],[Width]],Table1[RIP SIZE],0)),"")))))*(1+$I$2),0) -> 0.805 | N35: =IF(TRIM[[#This Row],[Width]]>6,INDEX(Table10[1 sorted],MATCH(TRIM[[#This Row],[Species]],Table10[Species],0)),INDEX(Table10[1],MATCH(TRIM[[#This Row],[Species]],Table10[Species],0))) -> #N/A | O35: =TRIM[[#This Row],[Factor]]*TRIM[[#This Row],[Lin.Ft.]] -> 219.765 | P35: =TRIM[[#This Row],[BF]]*TRIM[[#This Row],[Cost/BF]] -> #N/A | Q35: =IF(TRIM[[#This Row],[BF]]="","",P35*I$3) -> #N/A | R35: =$I$4 -> 175 | S35: =TRIM[[#This Row],[Lin.Ft.]]*$I$5 -> 232.05 | T35: =IF('Trim Take Off'!$C$17="custom",(TRIM[[#This Row],[Width]]+0.25)*$I$6,0) -> 625 | U35: =IFERROR(TRIM[[#This Row],[LF Add]]+TRIM[[#This Row],[Material Mark Up]]+TRIM[[#This Row],[Total Cost]],0) -> 0 | V35: =IFERROR(TRIM[[#This Row],[Total Raw]]/TRIM[[#This Row],[Lin.Ft.]],"") -> 0 | W35: =INDEX(finish[Rate],MATCH(TRIM[[#This Row],[FINISH HELP]],finish[Finish],0)) -> 2.5 | X35: =IFERROR((TRIM[[#This Row],[cost/L.F.]]*(1+$I$7)),"") -> 0 | Y35: =IFERROR(TRIM[[#This Row],[Knife Grind]]+TRIM[[#This Row],[Set-up]],"") -> 800
A36: =IF(TRIM[[#This Row],[Species]]=0,"",IF(TRIM[[#This Row],[Lin.Ft.]]>1,(MAX($A$14:$A35)+1),"")) | B36: ='Trim Take Off'!$C$22 -> 0 | C36: =IF(TRIM[[#This Row],[Width]]>5.25,"LARGE",IF(TRIM[[#This Row],[Width]]>3,"AVG",IF(TRIM[[#This Row],[Width]]="","","SMALL"))) -> LARGE | D36: =IF(TRIM[[#This Row],[Species]]="","",IF(TRIM[[#This Row],[Species]]="POPLAR","PRIMED",IF(TRIM[[#This Row],[Species]]="MDF","PRIMED","STAINED"))) -> STAINED | E36: =TRIM[[#This Row],[Finish]]&" "&TRIM[[#This Row],[Finish Size]] -> STAINED LARGE | F36: SILL | G36: ='Trim Take Off'!$C$16&" "&TRIM[[#This Row],[Type]] -> CRAFTSMAN SILL | H36: =IFERROR(TRIM[[#This Row],[Species]]&" "&TRIM[[#This Row],[Finish]]&" "&TRIM[[#This Row],[Type]]&" "&TRIM[[#This Row],[Width]]&" x "&TRIM[[#This Row],[Thickness]],"") -> 0 STAINED SILL 7.25 x 0.75 | I36: =IFERROR(INDEX(Table5[ACTUAL WIDTH],MATCH(TRIM[[#This Row],[NAME TYPE]],Table5[DESCRIPTION],0)),) -> 7.25 | J36: =IFERROR(INDEX(Table5[ACTUAL THICKNESS],MATCH(TRIM[[#This Row],[NAME TYPE]],Table5[DESCRIPTION],0)),"") -> 0.75 | K36: =INDEX(lumber[Rough],MATCH(TRIM[[#This Row],[Thickness]],lumber[Finish],1)) -> 1 | L36: =IFERROR(INDEX(Table5[LF],MATCH(TRIM[[#This Row],[NAME TYPE]],Table5[DESCRIPTION],0)),0) -> 139.5 | M36: =IFERROR((IF(TRIM[[#This Row],[Rough Thick]]=1,INDEX(Table1[4/4],MATCH(TRIM[[#This Row],[Width]],Table1[RIP SIZE],0)),IF(TRIM[[#This Row],[Rough Thick]]=1.25,INDEX(Table1[5/4],MATCH(TRIM[[#This Row],[Width]],Table1[RIP SIZE],0)),IF(TRIM[[#This Row],[Rough Thick]]=1.5,INDEX(Table1[6/4],MATCH(TRIM[[#This Row],[Width]],Table1[RIP SIZE],0)),IF(TRIM[[#This Row],[Rough Thick]]=2,INDEX(Table1[8/4],MATCH(TRIM[[#This Row],[Width]],Table1[RIP SIZE],0)),"")))))*(1+$I$2),0) -> 0.93035 | N36: =IF(TRIM[[#This Row],[Width]]>6,INDEX(Table10[1 sorted],MATCH(TRIM[[#This Row],[Species]],Table10[Species],0)),INDEX(Table10[1],MATCH(TRIM[[#This Row],[Species]],Table10[Species],0))) -> #N/A | O36: =TRIM[[#This Row],[Factor]]*TRIM[[#This Row],[Lin.Ft.]] -> 129.78383 | P36: =TRIM[[#This Row],[BF]]*TRIM[[#This Row],[Cost/BF]] -> #N/A | Q36: =IF(TRIM[[#This Row],[BF]]="","",P36*I$3) -> #N/A | R36: =$I$4 -> 175 | S36: =TRIM[[#This Row],[Lin.Ft.]]*$I$5 -> 118.575 | T36: =IF('Trim Take Off'!$C$17="custom",(TRIM[[#This Row],[Width]]+0.25)*$I$6,0) -> 750 | U36: =IFERROR(TRIM[[#This Row],[LF Add]]+TRIM[[#This Row],[Material Mark Up]]+TRIM[[#This Row],[Total Cost]],0) -> 0 | V36: =IFERROR(TRIM[[#This Row],[Total Raw]]/TRIM[[#This Row],[Lin.Ft.]],"") -> 0 | W36: =INDEX(finish[Rate],MATCH(TRIM[[#This Row],[FINISH HELP]],finish[Finish],0)) -> 2.5 | X36: =IFERROR((TRIM[[#This Row],[cost/L.F.]]*(1+$I$7)),"") -> 0 | Y36: =IFERROR(TRIM[[#This Row],[Knife Grind]]+TRIM[[#This Row],[Set-up]],"") -> 925
A37: =IF(TRIM[[#This Row],[Species]]=0,"",IF(TRIM[[#This Row],[Lin.Ft.]]>1,(MAX($A$14:$A36)+1),"")) | B37: ='Trim Take Off'!$C$22 -> 0 | C37: =IF(TRIM[[#This Row],[Width]]>5.25,"LARGE",IF(TRIM[[#This Row],[Width]]>3,"AVG",IF(TRIM[[#This Row],[Width]]="","","SMALL"))) -> AVG | D37: =IF(TRIM[[#This Row],[Species]]="","",IF(TRIM[[#This Row],[Species]]="POPLAR","PRIMED",IF(TRIM[[#This Row],[Species]]="MDF","PRIMED","STAINED"))) -> STAINED | E37: =TRIM[[#This Row],[Finish]]&" "&TRIM[[#This Row],[Finish Size]] -> STAINED AVG | F37: APRON | G37: ='Trim Take Off'!$C$16&" "&TRIM[[#This Row],[Type]] -> CRAFTSMAN APRON | H37: =IFERROR(TRIM[[#This Row],[Species]]&" "&TRIM[[#This Row],[Finish]]&" "&TRIM[[#This Row],[Type]]&" "&TRIM[[#This Row],[Width]]&" x "&TRIM[[#This Row],[Thickness]],"") -> 0 STAINED APRON 5.25 x 0.5 | I37: =IFERROR(INDEX(Table5[ACTUAL WIDTH],MATCH(TRIM[[#This Row],[NAME TYPE]],Table5[DESCRIPTION],0)),) -> 5.25 | J37: =IFERROR(INDEX(Table5[ACTUAL THICKNESS],MATCH(TRIM[[#This Row],[NAME TYPE]],Table5[DESCRIPTION],0)),"") -> 0.5 | K37: =INDEX(lumber[Rough],MATCH(TRIM[[#This Row],[Thickness]],lumber[Finish],1)) -> 1 | L37: =IFERROR(INDEX(Table5[LF],MATCH(TRIM[[#This Row],[NAME TYPE]],Table5[DESCRIPTION],0)),0) -> 139.5 | M37: =IFERROR((IF(TRIM[[#This Row],[Rough Thick]]=1,INDEX(Table1[4/4],MATCH(TRIM[[#This Row],[Width]],Table1[RIP SIZE],0)),IF(TRIM[[#This Row],[Rough Thick]]=1.25,INDEX(Table1[5/4],MATCH(TRIM[[#This Row],[Width]],Table1[RIP SIZE],0)),IF(TRIM[[#This Row],[Rough Thick]]=1.5,INDEX(Table1[6/4],MATCH(TRIM[[#This Row],[Width]],Table1[RIP SIZE],0)),IF(TRIM[[#This Row],[Rough Thick]]=2,INDEX(Table1[8/4],MATCH(TRIM[[#This Row],[Width]],Table1[RIP SIZE],0)),"")))))*(1+$I$2),0) -> 0.7314 | N37: =IF(TRIM[[#This Row],[Width]]>6,INDEX(Table10[1 sorted],MATCH(TRIM[[#This Row],[Species]],Table10[Species],0)),INDEX(Table10[1],MATCH(TRIM[[#This Row],[Species]],Table10[Species],0))) -> #N/A | O37: =TRIM[[#This Row],[Factor]]*TRIM[[#This Row],[Lin.Ft.]] -> 102.0303 | P37: =TRIM[[#This Row],[BF]]*TRIM[[#This Row],[Cost/BF]] -> #N/A | Q37: =IF(TRIM[[#This Row],[BF]]="","",P37*I$3) -> #N/A | R37: =$I$4 -> 175 | S37: =TRIM[[#This Row],[Lin.Ft.]]*$I$5 -> 118.575 | T37: =IF('Trim Take Off'!$C$17="custom",(TRIM[[#This Row],[Width]]+0.25)*$I$6,0) -> 550 | U37: =IFERROR(TRIM[[#This Row],[LF Add]]+TRIM[[#This Row],[Material Mark Up]]+TRIM[[#This Row],[Total Cost]],0) -> 0 | V37: =IFERROR(TRIM[[#This Row],[Total Raw]]/TRIM[[#This Row],[Lin.Ft.]],"") -> 0 | W37: =INDEX(finish[Rate],MATCH(TRIM[[#This Row],[FINISH HELP]],finish[Finish],0)) -> 2.25 | X37: =IFERROR((TRIM[[#This Row],[cost/L.F.]]*(1+$I$7)),"") -> 0 | Y37: =IFERROR(TRIM[[#This Row],[Knife Grind]]+TRIM[[#This Row],[Set-up]],"") -> 725
A38: =IF(TRIM[[#This Row],[Species]]=0,"",IF(TRIM[[#This Row],[Lin.Ft.]]>1,(MAX($A$14:$A37)+1),"")) | B38: ='Trim Take Off'!$C$22 -> 0 | C38: =IF(TRIM[[#This Row],[Width]]>5.25,"LARGE",IF(TRIM[[#This Row],[Width]]>3,"AVG",IF(TRIM[[#This Row],[Width]]="","","SMALL"))) -> SMALL | D38: =IF(TRIM[[#This Row],[Species]]="","",IF(TRIM[[#This Row],[Species]]="POPLAR","PRIMED",IF(TRIM[[#This Row],[Species]]="MDF","PRIMED","STAINED"))) -> STAINED | E38: =TRIM[[#This Row],[Finish]]&" "&TRIM[[#This Row],[Finish Size]] -> STAINED SMALL | F38: DENTIL | G38: ='Trim Take Off'!$C$16&" "&TRIM[[#This Row],[Type]] -> CRAFTSMAN DENTIL | H38: =IFERROR(TRIM[[#This Row],[Species]]&" "&TRIM[[#This Row],[Finish]]&" "&TRIM[[#This Row],[Type]]&" "&TRIM[[#This Row],[Width]]&" x "&TRIM[[#This Row],[Thickness]],"") -> 0 STAINED DENTIL 0 x | I38: =IFERROR(INDEX(Table5[ACTUAL WIDTH],MATCH(TRIM[[#This Row],[NAME TYPE]],Table5[DESCRIPTION],0)),) -> 0 | J38: =IFERROR(INDEX(Table5[ACTUAL THICKNESS],MATCH(TRIM[[#This Row],[NAME TYPE]],Table5[DESCRIPTION],0)),"") | K38: =INDEX(lumber[Rough],MATCH(TRIM[[#This Row],[Thickness]],lumber[Finish],1)) -> #N/A | L38: =IFERROR(INDEX(Table5[LF],MATCH(TRIM[[#This Row],[NAME TYPE]],Table5[DESCRIPTION],0)),0) -> 0 | M38: =IFERROR((IF(TRIM[[#This Row],[Rough Thick]]=1,INDEX(Table1[4/4],MATCH(TRIM[[#This Row],[Width]],Table1[RIP SIZE],0)),IF(TRIM[[#This Row],[Rough Thick]]=1.25,INDEX(Table1[5/4],MATCH(TRIM[[#This Row],[Width]],Table1[RIP SIZE],0)),IF(TRIM[[#This Row],[Rough Thick]]=1.5,INDEX(Table1[6/4],MATCH(TRIM[[#This Row],[Width]],Table1[RIP SIZE],0)),IF(TRIM[[#This Row],[Rough Thick]]=2,INDEX(Table1[8/4],MATCH(TRIM[[#This Row],[Width]],Table1[RIP SIZE],0)),"")))))*(1+$I$2),0) -> 0 | N38: =IF(TRIM[[#This Row],[Width]]>6,INDEX(Table10[1 sorted],MATCH(TRIM[[#This Row],[Species]],Table10[Species],0)),INDEX(Table10[1],MATCH(TRIM[[#This Row],[Species]],Table10[Species],0))) -> #N/A | O38: =TRIM[[#This Row],[Factor]]*TRIM[[#This Row],[Lin.Ft.]] -> 0 | P38: =TRIM[[#This Row],[BF]]*TRIM[[#This Row],[Cost/BF]] -> #N/A | Q38: =IF(TRIM[[#This Row],[BF]]="","",P38*I$3) -> #N/A | R38: =$I$4 -> 175 | S38: =TRIM[[#This Row],[Lin.Ft.]]*$I$5 -> 0 | T38: =IF('Trim Take Off'!$C$17="custom",(TRIM[[#This Row],[Width]]+0.25)*$I$6,0) -> 25 | U38: =IFERROR(TRIM[[#This Row],[LF Add]]+TRIM[[#This Row],[Material Mark Up]]+TRIM[[#This Row],[Total Cost]],0) -> 0 | V38: =IFERROR(TRIM[[#This Row],[Total Raw]]/TRIM[[#This Row],[Lin.Ft.]],"") | W38: =INDEX(finish[Rate],MATCH(TRIM[[#This Row],[FINISH HELP]],finish[Finish],0)) -> 2 | X38: =IFERROR((TRIM[[#This Row],[cost/L.F.]]*(1+$I$7)),"") | Y38: =IFERROR(TRIM[[#This Row],[Knife Grind]]+TRIM[[#This Row],[Set-up]],"") -> 200
A39: =IF(TRIM[[#This Row],[Species]]=0,"",IF(TRIM[[#This Row],[Lin.Ft.]]>1,(MAX($A$14:$A38)+1),"")) | C39: =IF(TRIM[[#This Row],[Width]]>5.25,"LARGE",IF(TRIM[[#This Row],[Width]]>3,"AVG",IF(TRIM[[#This Row],[Width]]="","","SMALL"))) -> SMALL | D39: =IF(TRIM[[#This Row],[Species]]="","",IF(TRIM[[#This Row],[Species]]="POPLAR","PRIMED",IF(TRIM[[#This Row],[Species]]="MDF","PRIMED","STAINED"))) | E39: =TRIM[[#This Row],[Finish]]&" "&TRIM[[#This Row],[Finish Size]] -> SMALL | G39: ='Trim Take Off'!$C$16&" "&TRIM[[#This Row],[Type]] -> CRAFTSMAN | H39: =IFERROR(TRIM[[#This Row],[Species]]&" "&TRIM[[#This Row],[Finish]]&" "&TRIM[[#This Row],[Type]]&" "&TRIM[[#This Row],[Width]]&" x "&TRIM[[#This Row],[Thickness]],"") -> 0 x | I39: =IFERROR(INDEX(Table5[ACTUAL WIDTH],MATCH(TRIM[[#This Row],[NAME TYPE]],Table5[DESCRIPTION],0)),) -> 0 | J39: =IFERROR(INDEX(Table5[ACTUAL THICKNESS],MATCH(TRIM[[#This Row],[NAME TYPE]],Table5[DESCRIPTION],0)),"") | K39: =INDEX(lumber[Rough],MATCH(TRIM[[#This Row],[Thickness]],lumber[Finish],1)) -> #N/A | L39: =IFERROR(INDEX(Table5[LF],MATCH(TRIM[[#This Row],[NAME TYPE]],Table5[DESCRIPTION],0)),0) -> 0 | M39: =IFERROR((IF(TRIM[[#This Row],[Rough Thick]]=1,INDEX(Table1[4/4],MATCH(TRIM[[#This Row],[Width]],Table1[RIP SIZE],0)),IF(TRIM[[#This Row],[Rough Thick]]=1.25,INDEX(Table1[5/4],MATCH(TRIM[[#This Row],[Width]],Table1[RIP SIZE],0)),IF(TRIM[[#This Row],[Rough Thick]]=1.5,INDEX(Table1[6/4],MATCH(TRIM[[#This Row],[Width]],Table1[RIP SIZE],0)),IF(TRIM[[#This Row],[Rough Thick]]=2,INDEX(Table1[8/4],MATCH(TRIM[[#This Row],[Width]],Table1[RIP SIZE],0)),"")))))*(1+$I$2),0) -> 0 | N39: =IF(TRIM[[#This Row],[Width]]>6,INDEX(Table10[1 sorted],MATCH(TRIM[[#This Row],[Species]],Table10[Species],0)),INDEX(Table10[1],MATCH(TRIM[[#This Row],[Species]],Table10[Species],0))) -> #N/A | O39: =TRIM[[#This Row],[Factor]]*TRIM[[#This Row],[Lin.Ft.]] -> 0 | P39: =TRIM[[#This Row],[BF]]*TRIM[[#This Row],[Cost/BF]] -> #N/A | Q39: =IF(TRIM[[#This Row],[BF]]="","",P39*I$3) -> #N/A | R39: =$I$4 -> 175 | S39: =TRIM[[#This Row],[Lin.Ft.]]*$I$5 -> 0 | T39: =IF('Trim Take Off'!$C$17="custom",(TRIM[[#This Row],[Width]]+0.25)*$I$6,0) -> 25 | U39: =IFERROR(TRIM[[#This Row],[LF Add]]+TRIM[[#This Row],[Material Mark Up]]+TRIM[[#This Row],[Total Cost]],0) -> 0 | V39: =IFERROR(TRIM[[#This Row],[Total Raw]]/TRIM[[#This Row],[Lin.Ft.]],"") | W39: =INDEX(finish[Rate],MATCH(TRIM[[#This Row],[FINISH HELP]],finish[Finish],0)) -> #N/A | X39: =IFERROR((TRIM[[#This Row],[cost/L.F.]]*(1+$I$7)),"") | Y39: =IFERROR(TRIM[[#This Row],[Knife Grind]]+TRIM[[#This Row],[Set-up]],"") -> 200
A40: =IF(TRIM[[#This Row],[Species]]=0,"",IF(TRIM[[#This Row],[Lin.Ft.]]>1,(MAX($A$14:$A39)+1),"")) | C40: =IF(TRIM[[#This Row],[Width]]>5.25,"LARGE",IF(TRIM[[#This Row],[Width]]>3,"AVG",IF(TRIM[[#This Row],[Width]]="","","SMALL"))) -> SMALL | D40: =IF(TRIM[[#This Row],[Species]]="","",IF(TRIM[[#This Row],[Species]]="POPLAR","PRIMED",IF(TRIM[[#This Row],[Species]]="MDF","PRIMED","STAINED"))) | E40: =TRIM[[#This Row],[Finish]]&" "&TRIM[[#This Row],[Finish Size]] -> SMALL | G40: ='Trim Take Off'!$C$16&" "&TRIM[[#This Row],[Type]] -> CRAFTSMAN | H40: =IFERROR(TRIM[[#This Row],[Species]]&" "&TRIM[[#This Row],[Finish]]&" "&TRIM[[#This Row],[Type]]&" "&TRIM[[#This Row],[Width]]&" x "&TRIM[[#This Row],[Thickness]],"") -> 0 x | I40: =IFERROR(INDEX(Table5[ACTUAL WIDTH],MATCH(TRIM[[#This Row],[NAME TYPE]],Table5[DESCRIPTION],0)),) -> 0 | J40: =IFERROR(INDEX(Table5[ACTUAL THICKNESS],MATCH(TRIM[[#This Row],[NAME TYPE]],Table5[DESCRIPTION],0)),"") | K40: =INDEX(lumber[Rough],MATCH(TRIM[[#This Row],[Thickness]],lumber[Finish],1)) -> #N/A | L40: =IFERROR(INDEX(Table5[LF],MATCH(TRIM[[#This Row],[NAME TYPE]],Table5[DESCRIPTION],0)),0) -> 0 | M40: =IFERROR((IF(TRIM[[#This Row],[Rough Thick]]=1,INDEX(Table1[4/4],MATCH(TRIM[[#This Row],[Width]],Table1[RIP SIZE],0)),IF(TRIM[[#This Row],[Rough Thick]]=1.25,INDEX(Table1[5/4],MATCH(TRIM[[#This Row],[Width]],Table1[RIP SIZE],0)),IF(TRIM[[#This Row],[Rough Thick]]=1.5,INDEX(Table1[6/4],MATCH(TRIM[[#This Row],[Width]],Table1[RIP SIZE],0)),IF(TRIM[[#This Row],[Rough Thick]]=2,INDEX(Table1[8/4],MATCH(TRIM[[#This Row],[Width]],Table1[RIP SIZE],0)),"")))))*(1+$I$2),0) -> 0 | N40: =IF(TRIM[[#This Row],[Width]]>6,INDEX(Table10[1 sorted],MATCH(TRIM[[#This Row],[Species]],Table10[Species],0)),INDEX(Table10[1],MATCH(TRIM[[#This Row],[Species]],Table10[Species],0))) -> #N/A | O40: =TRIM[[#This Row],[Factor]]*TRIM[[#This Row],[Lin.Ft.]] -> 0 | P40: =TRIM[[#This Row],[BF]]*TRIM[[#This Row],[Cost/BF]] -> #N/A | Q40: =IF(TRIM[[#This Row],[BF]]="","",P40*I$3) -> #N/A | R40: =$I$4 -> 175 | S40: =TRIM[[#This Row],[Lin.Ft.]]*$I$5 -> 0 | T40: =IF('Trim Take Off'!$C$17="custom",(TRIM[[#This Row],[Width]]+0.25)*$I$6,0) -> 25 | U40: =IFERROR(TRIM[[#This Row],[LF Add]]+TRIM[[#This Row],[Material Mark Up]]+TRIM[[#This Row],[Total Cost]],0) -> 0 | V40: =IFERROR(TRIM[[#This Row],[Total Raw]]/TRIM[[#This Row],[Lin.Ft.]],"") | W40: =INDEX(finish[Rate],MATCH(TRIM[[#This Row],[FINISH HELP]],finish[Finish],0)) -> #N/A | X40: =IFERROR((TRIM[[#This Row],[cost/L.F.]]*(1+$I$7)),"") | Y40: =IFERROR(TRIM[[#This Row],[Knife Grind]]+TRIM[[#This Row],[Set-up]],"") -> 200
A41: =IF(TRIM[[#This Row],[Species]]=0,"",IF(TRIM[[#This Row],[Lin.Ft.]]>1,(MAX($A$14:$A40)+1),"")) | C41: =IF(TRIM[[#This Row],[Width]]>5.25,"LARGE",IF(TRIM[[#This Row],[Width]]>3,"AVG",IF(TRIM[[#This Row],[Width]]="","","SMALL"))) -> SMALL | D41: =IF(TRIM[[#This Row],[Species]]="","",IF(TRIM[[#This Row],[Species]]="POPLAR","PRIMED",IF(TRIM[[#This Row],[Species]]="MDF","PRIMED","STAINED"))) | E41: =TRIM[[#This Row],[Finish]]&" "&TRIM[[#This Row],[Finish Size]] -> SMALL | G41: ='Trim Take Off'!$C$16&" "&TRIM[[#This Row],[Type]] -> CRAFTSMAN | H41: =IFERROR(TRIM[[#This Row],[Species]]&" "&TRIM[[#This Row],[Finish]]&" "&TRIM[[#This Row],[Type]]&" "&TRIM[[#This Row],[Width]]&" x "&TRIM[[#This Row],[Thickness]],"") -> 0 x | I41: =IFERROR(INDEX(Table5[ACTUAL WIDTH],MATCH(TRIM[[#This Row],[NAME TYPE]],Table5[DESCRIPTION],0)),) -> 0 | J41: =IFERROR(INDEX(Table5[ACTUAL THICKNESS],MATCH(TRIM[[#This Row],[NAME TYPE]],Table5[DESCRIPTION],0)),"") | K41: =INDEX(lumber[Rough],MATCH(TRIM[[#This Row],[Thickness]],lumber[Finish],1)) -> #N/A | L41: =IFERROR(INDEX(Table5[LF],MATCH(TRIM[[#This Row],[NAME TYPE]],Table5[DESCRIPTION],0)),0) -> 0 | M41: =IFERROR((IF(TRIM[[#This Row],[Rough Thick]]=1,INDEX(Table1[4/4],MATCH(TRIM[[#This Row],[Width]],Table1[RIP SIZE],0)),IF(TRIM[[#This Row],[Rough Thick]]=1.25,INDEX(Table1[5/4],MATCH(TRIM[[#This Row],[Width]],Table1[RIP SIZE],0)),IF(TRIM[[#This Row],[Rough Thick]]=1.5,INDEX(Table1[6/4],MATCH(TRIM[[#This Row],[Width]],Table1[RIP SIZE],0)),IF(TRIM[[#This Row],[Rough Thick]]=2,INDEX(Table1[8/4],MATCH(TRIM[[#This Row],[Width]],Table1[RIP SIZE],0)),"")))))*(1+$I$2),0) -> 0 | N41: =IF(TRIM[[#This Row],[Width]]>6,INDEX(Table10[1 sorted],MATCH(TRIM[[#This Row],[Species]],Table10[Species],0)),INDEX(Table10[1],MATCH(TRIM[[#This Row],[Species]],Table10[Species],0))) -> #N/A | O41: =TRIM[[#This Row],[Factor]]*TRIM[[#This Row],[Lin.Ft.]] -> 0 | P41: =TRIM[[#This Row],[BF]]*TRIM[[#This Row],[Cost/BF]] -> #N/A | Q41: =IF(TRIM[[#This Row],[BF]]="","",P41*I$3) -> #N/A | R41: =$I$4 -> 175 | S41: =TRIM[[#This Row],[Lin.Ft.]]*$I$5 -> 0 | T41: =IF('Trim Take Off'!$C$17="custom",(TRIM[[#This Row],[Width]]+0.25)*$I$6,0) -> 25 | U41: =IFERROR(TRIM[[#This Row],[LF Add]]+TRIM[[#This Row],[Material Mark Up]]+TRIM[[#This Row],[Total Cost]],0) -> 0 | V41: =IFERROR(TRIM[[#This Row],[Total Raw]]/TRIM[[#This Row],[Lin.Ft.]],"") | W41: =INDEX(finish[Rate],MATCH(TRIM[[#This Row],[FINISH HELP]],finish[Finish],0)) -> #N/A | X41: =IFERROR((TRIM[[#This Row],[cost/L.F.]]*(1+$I$7)),"") | Y41: =IFERROR(TRIM[[#This Row],[Knife Grind]]+TRIM[[#This Row],[Set-up]],"") -> 200

Sheet Vlookup
J1: RIP SIZE FACTOR CHART
J2: RIP SIZE | K2: 4/4 | L2: 5/4 | M2: 6/4 | N2: 8/4
E3: 0.75 | F3: 1 | G3: =CONCATENATE(E3,",",F3) -> 0.75,1 | H3: =0.111*1.15 -> 0.12765 | J3: 0.75 | K3: =0.111*1.15 -> 0.12765 | L3: =0.138*1.15 -> 0.1587 | M3: =0.166*1.15 -> 0.1909 | N3: =0.222*1.15 -> 0.2553 | Q3: =0.111*1.15 -> 0.12765 | R3: =0.148*1.15 -> 0.1702 | S3: =0.166/1.15 -> 0.14434783 | T3: =0.185*1.15 -> 0.21275 | U3: =0.203*1.15 -> 0.23345 | V3: =0.222*1.15 -> 0.2553 | W3: =0.24*1.15 -> 0.276 | X3: =0.258*1.15 -> 0.2967 | Y3: =0.277*1.15 -> 0.31855 | Z3: =0.28*1.15 -> 0.322 | AA3: =0.285*1.15 -> 0.32775 | AB3: =0.301*1.15 -> 0.34615 | AC3: =0.318*1.15 -> 0.3657 | AD3: =0.335*1.15 -> 0.38525 | AE3: =0.351*1.15 -> 0.40365 | AF3: =0.368*1.15 -> 0.4232 | AG3: =0.385*1.15 -> 0.44275 | AH3: =0.402*1.15 -> 0.4623 | AI3: =0.418*1.15 -> 0.4807 | AJ3: =0.435*1.15 -> 0.50025 | AK3: =0.452*1.15 -> 0.5198 | AL3: =0.469*1.15 -> 0.53935 | AM3: =0.485*1.15 -> 0.55775 | AN3: =0.502*1.15 -> 0.5773 | AO3: =0.519*1.15 -> 0.59685 | AP3: =0.529*1.15 -> 0.60835 | AQ3: =0.55*1.15 -> 0.6325 | AR3: =0.571*1.15 -> 0.65665
E4: 0.75 | F4: 1.25 | G4: =CONCATENATE(E4,",",F4) -> 0.75,1.25 | H4: =0.138*1.15 -> 0.1587 | J4: 1 | K4: =0.148*1.15 -> 0.1702 | L4: =0.185*1.15 -> 0.21275 | M4: =0.222*1.15 -> 0.2553 | N4: =0.295*1.15 -> 0.33925 | Q4: =0.138*1.15 -> 0.1587 | R4: =0.185*1.15 -> 0.21275 | S4: =0.208*1.15 -> 0.2392 | T4: =0.231*1.15 -> 0.26565 | U4: =0.254*1.15 -> 0.2921 | V4: =0.277*1.15 -> 0.31855 | W4: =0.3*1.15 -> 0.345 | X4: =0.323*1.15 -> 0.37145 | Y4: =0.346*1.15 -> 0.3979 | Z4: =0.351*1.15 -> 0.40365 | AA4: =0.356*1.15 -> 0.4094 | AB4: =0.377*1.15 -> 0.43355 | AC4: =0.397*1.15 -> 0.45655 | AD4: =0.418*1.15 -> 0.4807 | AE4: =0.439*1.15 -> 0.50485 | AF4: =0.46*1.15 -> 0.529 | AG4: =0.481*1.15 -> 0.55315 | AH4: =0.502*1.15 -> 0.5773 | AI4: =0.523*1.15 -> 0.60145 | AJ4: =0.544*1.15 -> 0.6256 | AK4: =0.565*1.15 -> 0.64975 | AL4: =0.586*1.15 -> 0.6739 | AM4: =0.607*1.15 -> 0.69805 | AN4: =0.628*1.15 -> 0.7222 | AO4: =0.649*1.15 -> 0.74635 | AP4: =0.661*1.15 -> 0.76015 | AQ4: =0.687*1.15 -> 0.79005 | AR4: =0.714*1.15 -> 0.8211
E5: 0.75 | F5: 1.5 | G5: =CONCATENATE(E5,",",F5) -> 0.75,1.5 | H5: =0.166*1.15 -> 0.1909 | J5: 1.125 | K5: =0.166/1.15 -> 0.14434783 | L5: =0.208*1.15 -> 0.2392 | M5: =0.249*1.15 -> 0.28635 | N5: =0.332*1.15 -> 0.3818 | Q5: =0.166*1.15 -> 0.1909 | R5: =0.222*1.15 -> 0.2553 | S5: =0.249*1.15 -> 0.28635 | T5: =0.277*1.15 -> 0.31855 | U5: =0.305*1.15 -> 0.35075 | V5: =0.332*1.15 -> 0.3818 | W5: =0.36*1.15 -> 0.414 | X5: =0.388*1.15 -> 0.4462 | Y5: =0.415*1.15 -> 0.47725 | Z5: =0.421*1.15 -> 0.48415 | AA5: =0.427*1.15 -> 0.49105 | AB5: =0.452*1.15 -> 0.5198 | AC5: =0.477*1.15 -> 0.54855 | AD5: =0.502*1.15 -> 0.5773 | AE5: =0.527*1.15 -> 0.60605 | AF5: =0.552*1.15 -> 0.6348 | AG5: =0.577*1.15 -> 0.66355 | AH5: =0.603*1.15 -> 0.69345 | AI5: =0.628*1.15 -> 0.7222 | AJ5: =0.653*1.15 -> 0.75095 | AK5: =0.678*1.15 -> 0.7797 | AL5: =0.703*1.15 -> 0.80845 | AM5: =0.728*1.15 -> 0.8372 | AN5: =0.753*1.15 -> 0.86595 | AO5: =0.778*1.15 -> 0.8947 | AP5: =0.793*1.15 -> 0.91195 | AQ5: =0.825*1.15 -> 0.94875 | AR5: =0.857*1.15 -> 0.98555
E6: 0.75 | F6: 2 | G6: =CONCATENATE(E6,",",F6) -> 0.75,2 | H6: =0.222*1.15 -> 0.2553 | J6: 1.25 | K6: =0.185*1.15 -> 0.21275 | L6: =0.231*1.15 -> 0.26565 | M6: =0.277*1.15 -> 0.31855 | N6: =0.369*1.15 -> 0.42435 | Q6: =0.222*1.15 -> 0.2553 | R6: =0.295*1.15 -> 0.33925 | S6: =0.332*1.15 -> 0.3818 | T6: =0.369*1.15 -> 0.42435 | U6: =0.406*1.15 -> 0.4669 | V6: =0.443*1.15 -> 0.50945 | W6: =0.48*1.15 -> 0.552 | X6: =0.517*1.15 -> 0.59455 | Y6: =0.554*1.15 -> 0.6371 | Z6: =0.561*1.15 -> 0.64515 | AA6: =0.569*1.15 -> 0.65435 | AB6: =0.603*1.15 -> 0.69345 | AC6: =0.636*1.15 -> 0.7314 | AD6: =0.669*1.15 -> 0.76935 | AE6: =0.703*1.15 -> 0.80845 | AF6: =0.736*1.15 -> 0.8464 | AG6: =0.77*1.15 -> 0.8855 | AH6: =0.803*1.15 -> 0.92345 | AI6: =0.837*1.15 -> 0.96255 | AJ6: =0.87*1.15 -> 1.0005 | AK6: =0.904*1.15 -> 1.0396 | AL6: =0.937*1.15 -> 1.07755 | AM6: =0.971*1.15 -> 1.11665 | AN6: =1.004*1.15 -> 1.1546 | AO6: =1.038*1.15 -> 1.1937 | AP6: =1.058*1.15 -> 1.2167 | AQ6: =1.1*1.15 -> 1.265 | AR6: =1.143*1.15 -> 1.31445
E7: 1 | F7: 1 | G7: =CONCATENATE(E7,",",F7) -> 1,1 | H7: =0.148*1.15 -> 0.1702 | J7: 1.375 | K7: =0.203*1.15 -> 0.23345 | L7: =0.254*1.15 -> 0.2921 | M7: =0.305*1.15 -> 0.35075 | N7: =0.406*1.15 -> 0.4669
E8: 1 | F8: 1.25 | G8: =CONCATENATE(E8,",",F8) -> 1,1.25 | H8: =0.185*1.15 -> 0.21275 | J8: 1.5 | K8: =0.222*1.15 -> 0.2553 | L8: =0.277*1.15 -> 0.31855 | M8: =0.332*1.15 -> 0.3818 | N8: =0.443*1.15 -> 0.50945
E9: 1 | F9: 1.5 | G9: =CONCATENATE(E9,",",F9) -> 1,1.5 | H9: =0.222*1.15 -> 0.2553 | J9: 1.625 | K9: =0.24*1.15 -> 0.276 | L9: =0.3*1.15 -> 0.345 | M9: =0.36*1.15 -> 0.414 | N9: =0.48*1.15 -> 0.552
E10: 1 | F10: 2 | G10: =CONCATENATE(E10,",",F10) -> 1,2 | H10: =0.295*1.15 -> 0.33925 | J10: 1.75 | K10: =0.258*1.15 -> 0.2967 | L10: =0.323*1.15 -> 0.37145 | M10: =0.388*1.15 -> 0.4462 | N10: =0.517*1.15 -> 0.59455
E11: 1.125 | F11: 1 | G11: =CONCATENATE(E11,",",F11) -> 1.125,1 | H11: =0.166/1.15 -> 0.14434783 | J11: 1.875 | K11: =0.277*1.15 -> 0.31855 | L11: =0.346*1.15 -> 0.3979 | M11: =0.415*1.15 -> 0.47725 | N11: =0.554*1.15 -> 0.6371
E12: 1.125 | F12: 1.25 | G12: =CONCATENATE(E12,",",F12) -> 1.125,1.25 | H12: =0.208*1.15 -> 0.2392 | J12: 2 | K12: =0.28*1.15 -> 0.322 | L12: =0.351*1.15 -> 0.40365 | M12: =0.421*1.15 -> 0.48415 | N12: =0.561*1.15 -> 0.64515
E13: 1.125 | F13: 1.5 | G13: =CONCATENATE(E13,",",F13) -> 1.125,1.5 | H13: =0.249*1.15 -> 0.28635 | J13: 2.125 | K13: =0.285*1.15 -> 0.32775 | L13: =0.356*1.15 -> 0.4094 | M13: =0.427*1.15 -> 0.49105 | N13: =0.569*1.15 -> 0.65435
E14: 1.125 | F14: 2 | G14: =CONCATENATE(E14,",",F14) -> 1.125,2 | H14: =0.332*1.15 -> 0.3818 | J14: 2.25 | K14: =0.301*1.15 -> 0.34615 | L14: =0.377*1.15 -> 0.43355 | M14: =0.452*1.15 -> 0.5198 | N14: =0.603*1.15 -> 0.69345
E15: 1.25 | F15: 1 | G15: =CONCATENATE(E15,",",F15) -> 1.25,1 | H15: =0.185*1.15 -> 0.21275 | J15: 2.375 | K15: =0.318*1.15 -> 0.3657 | L15: =0.397*1.15 -> 0.45655 | M15: =0.477*1.15 -> 0.54855 | N15: =0.636*1.15 -> 0.7314
E16: 1.25 | F16: 1.25 | G16: =CONCATENATE(E16,",",F16) -> 1.25,1.25 | H16: =0.231*1.15 -> 0.26565 | J16: 2.5 | K16: =0.335*1.15 -> 0.38525 | L16: =0.418*1.15 -> 0.4807 | M16: =0.502*1.15 -> 0.5773 | N16: =0.669*1.15 -> 0.76935
E17: 1.25 | F17: 1.5 | G17: =CONCATENATE(E17,",",F17) -> 1.25,1.5 | H17: =0.277*1.15 -> 0.31855 | J17: 2.625 | K17: =0.351*1.15 -> 0.40365 | L17: =0.439*1.15 -> 0.50485 | M17: =0.527*1.15 -> 0.60605 | N17: =0.703*1.15 -> 0.80845
E18: 1.25 | F18: 2 | G18: =CONCATENATE(E18,",",F18) -> 1.25,2 | H18: =0.369*1.15 -> 0.42435 | J18: 2.75 | K18: =0.368*1.15 -> 0.4232 | L18: =0.46*1.15 -> 0.529 | M18: =0.552*1.15 -> 0.6348 | N18: =0.736*1.15 -> 0.8464
E19: 1.375 | F19: 1 | G19: =CONCATENATE(E19,",",F19) -> 1.375,1 | H19: =0.203*1.15 -> 0.23345 | J19: 2.875 | K19: =0.385*1.15 -> 0.44275 | L19: =0.481*1.15 -> 0.55315 | M19: =0.577*1.15 -> 0.66355 | N19: =0.77*1.15 -> 0.8855
E20: 1.375 | F20: 1.25 | G20: =CONCATENATE(E20,",",F20) -> 1.375,1.25 | H20: =0.254*1.15 -> 0.2921 | J20: 3 | K20: =0.402*1.15 -> 0.4623 | L20: =0.502*1.15 -> 0.5773 | M20: =0.603*1.15 -> 0.69345 | N20: =0.803*1.15 -> 0.92345
E21: 1.375 | F21: 1.5 | G21: =CONCATENATE(E21,",",F21) -> 1.375,1.5 | H21: =0.305*1.15 -> 0.35075 | J21: 3.125 | K21: =0.418*1.15 -> 0.4807 | L21: =0.523*1.15 -> 0.60145 | M21: =0.628*1.15 -> 0.7222 | N21: =0.837*1.15 -> 0.96255
E22: 1.375 | F22: 2 | G22: =CONCATENATE(E22,",",F22) -> 1.375,2 | H22: =0.406*1.15 -> 0.4669 | J22: 3.25 | K22: =0.435*1.15 -> 0.50025 | L22: =0.544*1.15 -> 0.6256 | M22: =0.653*1.15 -> 0.75095 | N22: =0.87*1.15 -> 1.0005
E23: 1.5 | F23: 1 | G23: =CONCATENATE(E23,",",F23) -> 1.5,1 | H23: =0.222*1.15 -> 0.2553 | J23: 3.375 | K23: =0.452*1.15 -> 0.5198 | L23: =0.565*1.15 -> 0.64975 | M23: =0.678*1.15 -> 0.7797 | N23: =0.904*1.15 -> 1.0396
E24: 1.5 | F24: 1.25 | G24: =CONCATENATE(E24,",",F24) -> 1.5,1.25 | H24: =0.277*1.15 -> 0.31855 | J24: 3.5 | K24: =0.469*1.15 -> 0.53935 | L24: =0.586*1.15 -> 0.6739 | M24: =0.703*1.15 -> 0.80845 | N24: =0.937*1.15 -> 1.07755
E25: 1.5 | F25: 1.5 | G25: =CONCATENATE(E25,",",F25) -> 1.5,1.5 | H25: =0.332*1.15 -> 0.3818 | J25: 3.625 | K25: =0.485*1.15 -> 0.55775 | L25: =0.607*1.15 -> 0.69805 | M25: =0.728*1.15 -> 0.8372 | N25: =0.971*1.15 -> 1.11665
E26: 1.5 | F26: 2 | G26: =CONCATENATE(E26,",",F26) -> 1.5,2 | H26: =0.443*1.15 -> 0.50945 | J26: 3.75 | K26: =0.502*1.15 -> 0.5773 | L26: =0.628*1.15 -> 0.7222 | M26: =0.753*1.15 -> 0.86595 | N26: =1.004*1.15 -> 1.1546
E27: 1.625 | F27: 1 | G27: =CONCATENATE(E27,",",F27) -> 1.625,1 | H27: =0.24*1.15 -> 0.276 | J27: 3.875 | K27: =0.519*1.15 -> 0.59685 | L27: =0.649*1.15 -> 0.74635 | M27: =0.778*1.15 -> 0.8947 | N27: =1.038*1.15 -> 1.1937
E28: 1.625 | F28: 1.25 | G28: =CONCATENATE(E28,",",F28) -> 1.625,1.25 | H28: =0.3*1.15 -> 0.345 | J28: 4 | K28: =0.529*1.15 -> 0.60835 | L28: =0.661*1.15 -> 0.76015 | M28: =0.793*1.15 -> 0.91195 | N28: =1.058*1.15 -> 1.2167
E29: 1.625 | F29: 1.5 | G29: =CONCATENATE(E29,",",F29) -> 1.625,1.5 | H29: =0.36*1.15 -> 0.414 | J29: 4.25 | K29: =0.55*1.15 -> 0.6325 | L29: =0.687*1.15 -> 0.79005 | M29: =0.825*1.15 -> 0.94875 | N29: =1.1*1.15 -> 1.265
E30: 1.625 | F30: 2 | G30: =CONCATENATE(E30,",",F30) -> 1.625,2 | H30: =0.48*1.15 -> 0.552 | J30: 4.5 | K30: =0.571*1.15 -> 0.65665 | L30: =0.714*1.15 -> 0.8211 | M30: =0.857*1.15 -> 0.98555 | N30: =1.143*1.15 -> 1.31445
E31: 1.75 | F31: 1 | G31: =CONCATENATE(E31,",",F31) -> 1.75,1 | H31: =0.258*1.15 -> 0.2967
E32: 1.75 | F32: 1.25 | G32: =CONCATENATE(E32,",",F32) -> 1.75,1.25 | H32: =0.323*1.15 -> 0.37145
E33: 1.75 | F33: 1.5 | G33: =CONCATENATE(E33,",",F33) -> 1.75,1.5 | H33: =0.388*1.15 -> 0.4462
E34: 1.75 | F34: 2 | G34: =CONCATENATE(E34,",",F34) -> 1.75,2 | H34: =0.517*1.15 -> 0.59455
E35: 1.875 | F35: 1 | G35: =CONCATENATE(E35,",",F35) -> 1.875,1 | H35: =0.277*1.15 -> 0.31855
E36: 1.875 | F36: 1.25 | G36: =CONCATENATE(E36,",",F36) -> 1.875,1.25 | H36: =0.346*1.15 -> 0.3979
E37: 1.875 | F37: 1.5 | G37: =CONCATENATE(E37,",",F37) -> 1.875,1.5 | H37: =0.415*1.15 -> 0.47725
E38: 1.875 | F38: 2 | G38: =CONCATENATE(E38,",",F38) -> 1.875,2 | H38: =0.554*1.15 -> 0.6371
E39: 2 | F39: 1 | G39: =CONCATENATE(E39,",",F39) -> 2,1 | H39: =0.28*1.15 -> 0.322
E40: 2 | F40: 1.25 | G40: =CONCATENATE(E40,",",F40) -> 2,1.25 | H40: =0.351*1.15 -> 0.40365
E41: 2 | F41: 1.5 | G41: =CONCATENATE(E41,",",F41) -> 2,1.5 | H41: =0.421*1.15 -> 0.48415
E42: 2 | F42: 2 | G42: =CONCATENATE(E42,",",F42) -> 2,2 | H42: =0.561*1.15 -> 0.64515
E43: 2.125 | F43: 1 | G43: =CONCATENATE(E43,",",F43) -> 2.125,1 | H43: =0.285*1.15 -> 0.32775
E44: 2.125 | F44: 1.25 | G44: =CONCATENATE(E44,",",F44) -> 2.125,1.25 | H44: =0.356*1.15 -> 0.4094
E45: 2.125 | F45: 1.5 | G45: =CONCATENATE(E45,",",F45) -> 2.125,1.5 | H45: =0.427*1.15 -> 0.49105
E46: 2.125 | F46: 2 | G46: =CONCATENATE(E46,",",F46) -> 2.125,2 | H46: =0.569*1.15 -> 0.65435
E47: 2.25 | F47: 1 | G47: =CONCATENATE(E47,",",F47) -> 2.25,1 | H47: =0.301*1.15 -> 0.34615
E48: 2.25 | F48: 1.25 | G48: =CONCATENATE(E48,",",F48) -> 2.25,1.25 | H48: =0.377*1.15 -> 0.43355
E49: 2.25 | F49: 1.5 | G49: =CONCATENATE(E49,",",F49) -> 2.25,1.5 | H49: =0.452*1.15 -> 0.5198
E50: 2.25 | F50: 2 | G50: =CONCATENATE(E50,",",F50) -> 2.25,2 | H50: =0.603*1.15 -> 0.69345
E51: 2.375 | F51: 1 | G51: =CONCATENATE(E51,",",F51) -> 2.375,1 | H51: =0.318*1.15 -> 0.3657
E52: 2.375 | F52: 1.25 | G52: =CONCATENATE(E52,",",F52) -> 2.375,1.25 | H52: =0.397*1.15 -> 0.45655
E53: 2.375 | F53: 1.5 | G53: =CONCATENATE(E53,",",F53) -> 2.375,1.5 | H53: =0.477*1.15 -> 0.54855
E54: 2.375 | F54: 2 | G54: =CONCATENATE(E54,",",F54) -> 2.375,2 | H54: =0.636*1.15 -> 0.7314
E55: 2.5 | F55: 1 | G55: =CONCATENATE(E55,",",F55) -> 2.5,1 | H55: =0.335*1.15 -> 0.38525
E56: 2.5 | F56: 1.25 | G56: =CONCATENATE(E56,",",F56) -> 2.5,1.25 | H56: =0.418*1.15 -> 0.4807
E57: 2.5 | F57: 1.5 | G57: =CONCATENATE(E57,",",F57) -> 2.5,1.5 | H57: =0.502*1.15 -> 0.5773
E58: 2.5 | F58: 2 | G58: =CONCATENATE(E58,",",F58) -> 2.5,2 | H58: =0.669*1.15 -> 0.76935
E59: 2.625 | F59: 1 | G59: =CONCATENATE(E59,",",F59) -> 2.625,1 | H59: =0.351*1.15 -> 0.40365
E60: 2.625 | F60: 1.25 | G60: =CONCATENATE(E60,",",F60) -> 2.625,1.25 | H60: =0.439*1.15 -> 0.50485
E61: 2.625 | F61: 1.5 | G61: =CONCATENATE(E61,",",F61) -> 2.625,1.5 | H61: =0.527*1.15 -> 0.60605
E62: 2.625 | F62: 2 | G62: =CONCATENATE(E62,",",F62) -> 2.625,2 | H62: =0.703*1.15 -> 0.80845
E63: 2.75 | F63: 1 | G63: =CONCATENATE(E63,",",F63) -> 2.75,1 | H63: =0.368*1.15 -> 0.4232 | Q63: =0.318*1.15 -> 0.3657 | R63: =0.335*1.15 -> 0.38525 | S63: =0.351*1.15 -> 0.40365 | T63: =0.368*1.15 -> 0.4232 | U63: =0.385*1.15 -> 0.44275 | V63: =0.402*1.15 -> 0.4623 | W63: =0.418*1.15 -> 0.4807 | X63: =0.435*1.15 -> 0.50025 | Y63: =0.452*1.15 -> 0.5198 | Z63: =0.469*1.15 -> 0.53935 | AA63: =0.485*1.15 -> 0.55775 | AB63: =0.502*1.15 -> 0.5773 | AC63: =0.519*1.15 -> 0.59685 | AD63: =0.529*1.15 -> 0.60835 | AE63: =0.55*1.15 -> 0.6325 | AF63: =0.571*1.15 -> 0.65665
E64: 2.75 | F64: 1.25 | G64: =CONCATENATE(E64,",",F64) -> 2.75,1.25 | H64: =0.46*1.15 -> 0.529 | Q64: =0.397*1.15 -> 0.45655 | R64: =0.418*1.15 -> 0.4807 | S64: =0.439*1.15 -> 0.50485 | T64: =0.46*1.15 -> 0.529 | U64: =0.481*1.15 -> 0.55315 | V64: =0.502*1.15 -> 0.5773 | W64: =0.523*1.15 -> 0.60145 | X64: =0.544*1.15 -> 0.6256 | Y64: =0.565*1.15 -> 0.64975 | Z64: =0.586*1.15 -> 0.6739 | AA64: =0.607*1.15 -> 0.69805 | AB64: =0.628*1.15 -> 0.7222 | AC64: =0.649*1.15 -> 0.74635 | AD64: =0.661*1.15 -> 0.76015 | AE64: =0.687*1.15 -> 0.79005 | AF64: =0.714*1.15 -> 0.8211
E65: 2.75 | F65: 1.5 | G65: =CONCATENATE(E65,",",F65) -> 2.75,1.5 | H65: =0.552*1.15 -> 0.6348 | Q65: =0.477*1.15 -> 0.54855 | R65: =0.502*1.15 -> 0.5773 | S65: =0.527*1.15 -> 0.60605 | T65: =0.552*1.15 -> 0.6348 | U65: =0.577*1.15 -> 0.66355 | V65: =0.603*1.15 -> 0.69345 | W65: =0.628*1.15 -> 0.7222 | X65: =0.653*1.15 -> 0.75095 | Y65: =0.678*1.15 -> 0.7797 | Z65: =0.703*1.15 -> 0.80845 | AA65: =0.728*1.15 -> 0.8372 | AB65: =0.753*1.15 -> 0.86595 | AC65: =0.778*1.15 -> 0.8947 | AD65: =0.793*1.15 -> 0.91195 | AE65: =0.825*1.15 -> 0.94875 | AF65: =0.857*1.15 -> 0.98555
E66: 2.75 | F66: 2 | G66: =CONCATENATE(E66,",",F66) -> 2.75,2 | H66: =0.736*1.15 -> 0.8464 | Q66: =0.636*1.15 -> 0.7314 | R66: =0.669*1.15 -> 0.76935 | S66: =0.703*1.15 -> 0.80845 | T66: =0.736*1.15 -> 0.8464 | U66: =0.77*1.15 -> 0.8855 | V66: =0.803*1.15 -> 0.92345 | W66: =0.837*1.15 -> 0.96255 | X66: =0.87*1.15 -> 1.0005 | Y66: =0.904*1.15 -> 1.0396 | Z66: =0.937*1.15 -> 1.07755 | AA66: =0.971*1.15 -> 1.11665 | AB66: =1.004*1.15 -> 1.1546 | AC66: =1.038*1.15 -> 1.1937 | AD66: =1.058*1.15 -> 1.2167 | AE66: =1.1*1.15 -> 1.265 | AF66: =1.143*1.15 -> 1.31445
E67: 2.875 | F67: 1 | G67: =CONCATENATE(E67,",",F67) -> 2.875,1 | H67: =0.385*1.15 -> 0.44275
E68: 2.875 | F68: 1.25 | G68: =CONCATENATE(E68,",",F68) -> 2.875,1.25 | H68: =0.481*1.15 -> 0.55315
E69: 2.875 | F69: 1.5 | G69: =CONCATENATE(E69,",",F69) -> 2.875,1.5 | H69: =0.577*1.15 -> 0.66355
E70: 2.875 | F70: 2 | G70: =CONCATENATE(E70,",",F70) -> 2.875,2 | H70: =0.77*1.15 -> 0.8855
E71: 3 | F71: 1 | G71: =CONCATENATE(E71,",",F71) -> 3,1 | H71: =0.402*1.15 -> 0.4623
E72: 3 | F72: 1.25 | G72: =CONCATENATE(E72,",",F72) -> 3,1.25 | H72: =0.502*1.15 -> 0.5773
E73: 3 | F73: 1.5 | G73: =CONCATENATE(E73,",",F73) -> 3,1.5 | H73: =0.603*1.15 -> 0.69345
E74: 3 | F74: 2 | G74: =CONCATENATE(E74,",",F74) -> 3,2 | H74: =0.803*1.15 -> 0.92345
E75: 3.125 | F75: 1 | G75: =CONCATENATE(E75,",",F75) -> 3.125,1 | H75: =0.418*1.15 -> 0.4807
E76: 3.125 | F76: 1.25 | G76: =CONCATENATE(E76,",",F76) -> 3.125,1.25 | H76: =0.523*1.15 -> 0.60145
E77: 3.125 | F77: 1.5 | G77: =CONCATENATE(E77,",",F77) -> 3.125,1.5 | H77: =0.628*1.15 -> 0.7222
E78: 3.125 | F78: 2 | G78: =CONCATENATE(E78,",",F78) -> 3.125,2 | H78: =0.837*1.15 -> 0.96255
E79: 3.25 | F79: 1 | G79: =CONCATENATE(E79,",",F79) -> 3.25,1 | H79: =0.435*1.15 -> 0.50025
E80: 3.25 | F80: 1.25 | G80: =CONCATENATE(E80,",",F80) -> 3.25,1.25 | H80: =0.544*1.15 -> 0.6256
E81: 3.25 | F81: 1.5 | G81: =CONCATENATE(E81,",",F81) -> 3.25,1.5 | H81: =0.653*1.15 -> 0.75095
E82: 3.25 | F82: 2 | G82: =CONCATENATE(E82,",",F82) -> 3.25,2 | H82: =0.87*1.15 -> 1.0005
E83: 3.375 | F83: 1 | G83: =CONCATENATE(E83,",",F83) -> 3.375,1 | H83: =0.452*1.15 -> 0.5198
E84: 3.375 | F84: 1.25 | G84: =CONCATENATE(E84,",",F84) -> 3.375,1.25 | H84: =0.565*1.15 -> 0.64975
E85: 3.375 | F85: 1.5 | G85: =CONCATENATE(E85,",",F85) -> 3.375,1.5 | H85: =0.678*1.15 -> 0.7797
E86: 3.375 | F86: 2 | G86: =CONCATENATE(E86,",",F86) -> 3.375,2 | H86: =0.904*1.15 -> 1.0396
E87: 3.5 | F87: 1 | G87: =CONCATENATE(E87,",",F87) -> 3.5,1 | H87: =0.469*1.15 -> 0.53935
E88: 3.5 | F88: 1.25 | G88: =CONCATENATE(E88,",",F88) -> 3.5,1.25 | H88: =0.586*1.15 -> 0.6739
E89: 3.5 | F89: 1.5 | G89: =CONCATENATE(E89,",",F89) -> 3.5,1.5 | H89: =0.703*1.15 -> 0.80845
E90: 3.5 | F90: 2 | G90: =CONCATENATE(E90,",",F90) -> 3.5,2 | H90: =0.937*1.15 -> 1.07755
E91: 3.625 | F91: 1 | G91: =CONCATENATE(E91,",",F91) -> 3.625,1 | H91: =0.485*1.15 -> 0.55775
E92: 3.625 | F92: 1.25 | G92: =CONCATENATE(E92,",",F92) -> 3.625,1.25 | H92: =0.607*1.15 -> 0.69805
E93: 3.625 | F93: 1.5 | G93: =CONCATENATE(E93,",",F93) -> 3.625,1.5 | H93: =0.728*1.15 -> 0.8372
E94: 3.625 | F94: 2 | G94: =CONCATENATE(E94,",",F94) -> 3.625,2 | H94: =0.971*1.15 -> 1.11665
E95: 3.75 | F95: 1 | G95: =CONCATENATE(E95,",",F95) -> 3.75,1 | H95: =0.502*1.15 -> 0.5773
E96: 3.75 | F96: 1.25 | G96: =CONCATENATE(E96,",",F96) -> 3.75,1.25 | H96: =0.628*1.15 -> 0.7222
E97: 3.75 | F97: 1.5 | G97: =CONCATENATE(E97,",",F97) -> 3.75,1.5 | H97: =0.753*1.15 -> 0.86595
E98: 3.75 | F98: 2 | G98: =CONCATENATE(E98,",",F98) -> 3.75,2 | H98: =1.004*1.15 -> 1.1546
E99: 3.875 | F99: 1 | G99: =CONCATENATE(E99,",",F99) -> 3.875,1 | H99: =0.519*1.15 -> 0.59685
E100: 3.875 | F100: 1.25 | G100: =CONCATENATE(E100,",",F100) -> 3.875,1.25 | H100: =0.649*1.15 -> 0.74635
...

Sheet Door Estimate
C2: Logo placeholder is in this cell. | E2: Estimate
G3: Date: | H3: =TODAY() -> 45827
G4: Job: | H4: ='Trim Take Off'!$C$2 -> GREENE | J4: Sales Tax
G5: Customer: | H5: ='Trim Take Off'!$C$3 -> BAR 17 | J5: 0.06 | K5: **Sales Tax is included in the totals at the bottom and can be adjusted here**
B6: Line Number | C6: Qty | D6: Description | E6: Unit Price | F6: Set Up | G6: Unit Finish Price | H6: Line Total
B7: 1 | C7: =INDEX(Table17[Total],MATCH(InvoiceDetails713[[#This Row],[Line Number]],Table17[Line Number],0)) -> 1 | D7: =INDEX(Table17[Door Name],MATCH(InvoiceDetails713[[#This Row],[Line Number]],Table17[Line Number],0)) -> 2' 2"/6' 8" Swing | E7: =INDEX(Table17[Door Price],MATCH(InvoiceDetails713[[#This Row],[Line Number]],Table17[Line Number],0)) -> 0 | G7: =INDEX(Table17[Finish Price],MATCH(InvoiceDetails713[[#This Row],[Line Number]],Table17[Line Number],0)) -> 0 | H7: =IF(InvoiceDetails713[[#This Row],[Description]]="","",(IFERROR(InvoiceDetails713[[#This Row],[Unit Price]]*InvoiceDetails713[[#This Row],[Qty]]+InvoiceDetails713[[#This Row],[Set Up]],"")+IFERROR(InvoiceDetails713[[#This Row],[Unit Finish Price]]*InvoiceDetails713[[#This Row],[Qty]],0))) -> 0
B8: 2 | C8: =INDEX(Table17[Total],MATCH(InvoiceDetails713[[#This Row],[Line Number]],Table17[Line Number],0)) -> 2 | D8: =INDEX(Table17[Door Name],MATCH(InvoiceDetails713[[#This Row],[Line Number]],Table17[Line Number],0)) -> 2' 4"/6' 8" Swing | E8: =INDEX(Table17[Door Price],MATCH(InvoiceDetails713[[#This Row],[Line Number]],Table17[Line Number],0)) -> 0 | G8: =INDEX(Table17[Finish Price],MATCH(InvoiceDetails713[[#This Row],[Line Number]],Table17[Line Number],0)) -> 0 | H8: =IF(InvoiceDetails713[[#This Row],[Description]]="","",(IFERROR(InvoiceDetails713[[#This Row],[Unit Price]]*InvoiceDetails713[[#This Row],[Qty]]+InvoiceDetails713[[#This Row],[Set Up]],"")+IFERROR(InvoiceDetails713[[#This Row],[Unit Finish Price]]*InvoiceDetails713[[#This Row],[Qty]],0))) -> 0
B9: 3 | C9: =INDEX(Table17[Total],MATCH(InvoiceDetails713[[#This Row],[Line Number]],Table17[Line Number],0)) -> 3 | D9: =INDEX(Table17[Door Name],MATCH(InvoiceDetails713[[#This Row],[Line Number]],Table17[Line Number],0)) -> 2' 6"/7' 0" Swing | E9: =INDEX(Table17[Door Price],MATCH(InvoiceDetails713[[#This Row],[Line Number]],Table17[Line Number],0)) -> 0 | G9: =INDEX(Table17[Finish Price],MATCH(InvoiceDetails713[[#This Row],[Line Number]],Table17[Line Number],0)) -> 0 | H9: =IF(InvoiceDetails713[[#This Row],[Description]]="","",(IFERROR(InvoiceDetails713[[#This Row],[Unit Price]]*InvoiceDetails713[[#This Row],[Qty]]+InvoiceDetails713[[#This Row],[Set Up]],"")+IFERROR(InvoiceDetails713[[#This Row],[Unit Finish Price]]*InvoiceDetails713[[#This Row],[Qty]],0))) -> 0
B10: 4 | C10: =INDEX(Table17[Total],MATCH(InvoiceDetails713[[#This Row],[Line Number]],Table17[Line Number],0)) -> 2 | D10: =INDEX(Table17[Door Name],MATCH(InvoiceDetails713[[#This Row],[Line Number]],Table17[Line Number],0)) -> 2' 8"/7' 0" Swing | E10: =INDEX(Table17[Door Price],MATCH(InvoiceDetails713[[#This Row],[Line Number]],Table17[Line Number],0)) -> 0 | G10: =INDEX(Table17[Finish Price],MATCH(InvoiceDetails713[[#This Row],[Line Number]],Table17[Line Number],0)) -> 0 | H10: =IF(InvoiceDetails713[[#This Row],[Description]]="","",(IFERROR(InvoiceDetails713[[#This Row],[Unit Price]]*InvoiceDetails713[[#This Row],[Qty]]+InvoiceDetails713[[#This Row],[Set Up]],"")+IFERROR(InvoiceDetails713[[#This Row],[Unit Finish Price]]*InvoiceDetails713[[#This Row],[Qty]],0))) -> 0
B11: 5 | C11: =INDEX(Table17[Total],MATCH(InvoiceDetails713[[#This Row],[Line Number]],Table17[Line Number],0)) -> 1 | D11: =INDEX(Table17[Door Name],MATCH(InvoiceDetails713[[#This Row],[Line Number]],Table17[Line Number],0)) -> 3' 0"/8' 0" Swing | E11: =INDEX(Table17[Door Price],MATCH(InvoiceDetails713[[#This Row],[Line Number]],Table17[Line Number],0)) -> 0 | G11: =INDEX(Table17[Finish Price],MATCH(InvoiceDetails713[[#This Row],[Line Number]],Table17[Line Number],0)) -> 0 | H11: =IF(InvoiceDetails713[[#This Row],[Description]]="","",(IFERROR(InvoiceDetails713[[#This Row],[Unit Price]]*InvoiceDetails713[[#This Row],[Qty]]+InvoiceDetails713[[#This Row],[Set Up]],"")+IFERROR(InvoiceDetails713[[#This Row],[Unit Finish Price]]*InvoiceDetails713[[#This Row],[Qty]],0))) -> 0
B12: 6 | C12: =INDEX(Table17[Total],MATCH(InvoiceDetails713[[#This Row],[Line Number]],Table17[Line Number],0)) | D12: =INDEX(Table17[Door Name],MATCH(InvoiceDetails713[[#This Row],[Line Number]],Table17[Line Number],0)) | E12: =INDEX(Table17[Door Price],MATCH(InvoiceDetails713[[#This Row],[Line Number]],Table17[Line Number],0)) -> 0 | G12: =INDEX(Table17[Finish Price],MATCH(InvoiceDetails713[[#This Row],[Line Number]],Table17[Line Number],0)) -> 0 | H12: =IF(InvoiceDetails713[[#This Row],[Description]]="","",(IFERROR(InvoiceDetails713[[#This Row],[Unit Price]]*InvoiceDetails713[[#This Row],[Qty]]+InvoiceDetails713[[#This Row],[Set Up]],"")+IFERROR(InvoiceDetails713[[#This Row],[Unit Finish Price]]*InvoiceDetails713[[#This Row],[Qty]],0)))
B13: 7 | C13: =INDEX(Table17[Total],MATCH(InvoiceDetails713[[#This Row],[Line Number]],Table17[Line Number],0)) | D13: =INDEX(Table17[Door Name],MATCH(InvoiceDetails713[[#This Row],[Line Number]],Table17[Line Number],0)) | E13: =INDEX(Table17[Door Price],MATCH(InvoiceDetails713[[#This Row],[Line Number]],Table17[Line Number],0)) -> 0 | G13: =INDEX(Table17[Finish Price],MATCH(InvoiceDetails713[[#This Row],[Line Number]],Table17[Line Number],0)) -> 0 | H13: =IF(InvoiceDetails713[[#This Row],[Description]]="","",(IFERROR(InvoiceDetails713[[#This Row],[Unit Price]]*InvoiceDetails713[[#This Row],[Qty]]+InvoiceDetails713[[#This Row],[Set Up]],"")+IFERROR(InvoiceDetails713[[#This Row],[Unit Finish Price]]*InvoiceDetails713[[#This Row],[Qty]],0)))
B14: 8 | C14: =INDEX(Table17[Total],MATCH(InvoiceDetails713[[#This Row],[Line Number]],Table17[Line Number],0)) | D14: =INDEX(Table17[Door Name],MATCH(InvoiceDetails713[[#This Row],[Line Number]],Table17[Line Number],0)) | E14: =INDEX(Table17[Door Price],MATCH(InvoiceDetails713[[#This Row],[Line Number]],Table17[Line Number],0)) -> 0 | G14: =INDEX(Table17[Finish Price],MATCH(InvoiceDetails713[[#This Row],[Line Number]],Table17[Line Number],0)) -> 0 | H14: =IF(InvoiceDetails713[[#This Row],[Description]]="","",(IFERROR(InvoiceDetails713[[#This Row],[Unit Price]]*InvoiceDetails713[[#This Row],[Qty]]+InvoiceDetails713[[#This Row],[Set Up]],"")+IFERROR(InvoiceDetails713[[#This Row],[Unit Finish Price]]*InvoiceDetails713[[#This Row],[Qty]],0)))
B15: 9 | C15: =INDEX(Table17[Total],MATCH(InvoiceDetails713[[#This Row],[Line Number]],Table17[Line Number],0)) | D15: =INDEX(Table17[Door Name],MATCH(InvoiceDetails713[[#This Row],[Line Number]],Table17[Line Number],0)) | E15: =INDEX(Table17[Door Price],MATCH(InvoiceDetails713[[#This Row],[Line Number]],Table17[Line Number],0)) -> 0 | G15: =INDEX(Table17[Finish Price],MATCH(InvoiceDetails713[[#This Row],[Line Number]],Table17[Line Number],0)) -> 0 | H15: =IF(InvoiceDetails713[[#This Row],[Description]]="","",(IFERROR(InvoiceDetails713[[#This Row],[Unit Price]]*InvoiceDetails713[[#This Row],[Qty]]+InvoiceDetails713[[#This Row],[Set Up]],"")+IFERROR(InvoiceDetails713[[#This Row],[Unit Finish Price]]*InvoiceDetails713[[#This Row],[Qty]],0)))
B16: 10 | C16: =INDEX(Table17[Total],MATCH(InvoiceDetails713[[#This Row],[Line Number]],Table17[Line Number],0)) | D16: =INDEX(Table17[Door Name],MATCH(InvoiceDetails713[[#This Row],[Line Number]],Table17[Line Number],0)) | E16: =INDEX(Table17[Door Price],MATCH(InvoiceDetails713[[#This Row],[Line Number]],Table17[Line Number],0)) -> 0 | G16: =INDEX(Table17[Finish Price],MATCH(InvoiceDetails713[[#This Row],[Line Number]],Table17[Line Number],0)) -> 0 | H16: =IF(InvoiceDetails713[[#This Row],[Description]]="","",(IFERROR(InvoiceDetails713[[#This Row],[Unit Price]]*InvoiceDetails713[[#This Row],[Qty]]+InvoiceDetails713[[#This Row],[Set Up]],"")+IFERROR(InvoiceDetails713[[#This Row],[Unit Finish Price]]*InvoiceDetails713[[#This Row],[Qty]],0)))
B17: 11 | C17: =INDEX(Table17[Total],MATCH(InvoiceDetails713[[#This Row],[Line Number]],Table17[Line Number],0)) | D17: =INDEX(Table17[Door Name],MATCH(InvoiceDetails713[[#This Row],[Line Number]],Table17[Line Number],0)) | E17: =INDEX(Table17[Door Price],MATCH(InvoiceDetails713[[#This Row],[Line Number]],Table17[Line Number],0)) -> 0 | G17: =INDEX(Table17[Finish Price],MATCH(InvoiceDetails713[[#This Row],[Line Number]],Table17[Line Number],0)) -> 0 | H17: =IF(InvoiceDetails713[[#This Row],[Description]]="","",(IFERROR(InvoiceDetails713[[#This Row],[Unit Price]]*InvoiceDetails713[[#This Row],[Qty]]+InvoiceDetails713[[#This Row],[Set Up]],"")+IFERROR(InvoiceDetails713[[#This Row],[Unit Finish Price]]*InvoiceDetails713[[#This Row],[Qty]],0)))
B18: 12 | C18: =INDEX(Table17[Total],MATCH(InvoiceDetails713[[#This Row],[Line Number]],Table17[Line Number],0)) | D18: =INDEX(Table17[Door Name],MATCH(InvoiceDetails713[[#This Row],[Line Number]],Table17[Line Number],0)) | E18: =INDEX(Table17[Door Price],MATCH(InvoiceDetails713[[#This Row],[Line Number]],Table17[Line Number],0)) -> 0 | G18: =INDEX(Table17[Finish Price],MATCH(InvoiceDetails713[[#This Row],[Line Number]],Table17[Line Number],0)) -> 0 | H18: =IF(InvoiceDetails713[[#This Row],[Description]]="","",(IFERROR(InvoiceDetails713[[#This Row],[Unit Price]]*InvoiceDetails713[[#This Row],[Qty]]+InvoiceDetails713[[#This Row],[Set Up]],"")+IFERROR(InvoiceDetails713[[#This Row],[Unit Finish Price]]*InvoiceDetails713[[#This Row],[Qty]],0)))
... B31: 25 | C31: =INDEX(Table17[Total],MATCH(InvoiceDetails713[[#This Row],[Line Number]],Table17[Line Number],0)) | D31: =INDEX(Table17[Door Name],MATCH(InvoiceDetails713[[#This Row],[Line Number]],Table17[Line Number],0)) | E31: =INDEX(Table17[Door Price],MATCH(InvoiceDetails713[[#This Row],[Line Number]],Table17[Line Number],0)) -> 0 | G31: =INDEX(Table17[Finish Price],MATCH(InvoiceDetails713[[#This Row],[Line Number]],Table17[Line Number],0)) -> 0 | H31: =IF(InvoiceDetails713[[#This Row],[Description]]="","",(IFERROR(InvoiceDetails713[[#This Row],[Unit Price]]*InvoiceDetails713[[#This Row],[Qty]]+InvoiceDetails713[[#This Row],[Set Up]],"")+IFERROR(InvoiceDetails713[[#This Row],[Unit Finish Price]]*InvoiceDetails713[[#This Row],[Qty]],0)))
G32: =IF('Trim Take Off'!C20="poplar","Primed",IF('Trim Take Off'!C20="","",'Trim Take Off'!C20)) -> Primed | H32: =IF(G32="","",SUMIFS(InvoiceDetails713[Line Total],InvoiceDetails713[Description],"*"&G32&"*")) -> 0 | K32: **Double check unit price, if we don't have pricing data in the price data table it will not be correct**
G33: =IF('Trim Take Off'!C21="poplar","Primed",IF('Trim Take Off'!C21="","",'Trim Take Off'!C21)) | H33: =IF(G33="","",SUMIFS(InvoiceDetails713[Line Total],InvoiceDetails713[Description],"*"&G33&"*"))
G34: =IF('Trim Take Off'!C22="poplar","Primed",IF('Trim Take Off'!C22="","",'Trim Take Off'!C22)) | H34: =IF(G34="","",SUMIFS(InvoiceDetails713[Line Total],InvoiceDetails713[Description],"*"&G34&"*"))
G35: Total | H35: =H34+H32 -> #VALUE!

Sheet Trim Estimate
C2: Logo placeholder is in this cell. | E2: Estimate
G3: Date: | H3: =TODAY() -> 45827
G4: Job: | H4: ='Trim Take Off'!$C$2 -> GREENE | J4: Sales Tax
G5: Customer: | H5: ='Trim Take Off'!$C$3 -> BAR 17 | J5: 0.06 | K5: **Sales Tax is included in the totals at the bottom and can be adjusted here**
B6: Line Number | C6: Qty LF | D6: Description | E6: LF Price | F6: Set Up | G6: Finish LF Price | H6: Line Total | K6: **Filter Description Column to remove blanks, or leave them when printing estimate it doesn't really matter**
B7: 1 | C7: =IFERROR(INDEX(TRIM[Lin.Ft.],MATCH(InvoiceDetails7[[#This Row],[Description]],TRIM[Description],0)),"") -> 350 | D7: =IFERROR(INDEX(TRIM[Description],MATCH(InvoiceDetails7[[#This Row],[Line Number]],TRIM[line number],0)),"") -> Poplar PRIMED BASE 5.25 x 0.5 | E7: =IFERROR(INDEX(TRIM[Sell/LF Margin],MATCH(InvoiceDetails7[[#This Row],[Description]],TRIM[Description],0)),"") -> 3.2480525 | F7: =IFERROR(INDEX(TRIM[Set Up Total],MATCH(InvoiceDetails7[[#This Row],[Description]],TRIM[Description],0)),"") -> 725 | G7: =IFERROR(INDEX(TRIM[LF Finish Add],MATCH(InvoiceDetails7[[#This Row],[Description]],TRIM[Description],0)),"") -> 1 | H7: =IF(InvoiceDetails7[[#This Row],[Description]]="","",(IFERROR(InvoiceDetails7[[#This Row],[LF Price]]*InvoiceDetails7[[#This Row],[Qty LF]]+InvoiceDetails7[[#This Row],[Set Up]],"")+IFERROR(InvoiceDetails7[[#This Row],[Finish LF Price]]*InvoiceDetails7[[#This Row],[Qty LF]],0))) -> 2211.8184 | K7: **Any cell can be replaced with a hard keyed value, but changes made to the rest of the sheet will not be reflected in those cells**
B8: 2 | C8: =IFERROR(INDEX(TRIM[Lin.Ft.],MATCH(InvoiceDetails7[[#This Row],[Description]],TRIM[Description],0)),"") -> 714 | D8: =IFERROR(INDEX(TRIM[Description],MATCH(InvoiceDetails7[[#This Row],[Line Number]],TRIM[line number],0)),"") -> Poplar PRIMED CASE 3.25 x 0.625 | E8: =IFERROR(INDEX(TRIM[Sell/LF Margin],MATCH(InvoiceDetails7[[#This Row],[Description]],TRIM[Description],0)),"") -> 2.5170406 | F8: =IFERROR(INDEX(TRIM[Set Up Total],MATCH(InvoiceDetails7[[#This Row],[Description]],TRIM[Description],0)),"") -> 525 | G8: =IFERROR(INDEX(TRIM[LF Finish Add],MATCH(InvoiceDetails7[[#This Row],[Description]],TRIM[Description],0)),"") -> 1 | H8: =IF(InvoiceDetails7[[#This Row],[Description]]="","",(IFERROR(InvoiceDetails7[[#This Row],[LF Price]]*InvoiceDetails7[[#This Row],[Qty LF]]+InvoiceDetails7[[#This Row],[Set Up]],"")+IFERROR(InvoiceDetails7[[#This Row],[Finish LF Price]]*InvoiceDetails7[[#This Row],[Qty LF]],0))) -> 3036.167 | K8: **These numbers are used as an estimate only**
B9: 3 | C9: =IFERROR(INDEX(TRIM[Lin.Ft.],MATCH(InvoiceDetails7[[#This Row],[Description]],TRIM[Description],0)),"") -> 139.5 | D9: =IFERROR(INDEX(TRIM[Description],MATCH(InvoiceDetails7[[#This Row],[Line Number]],TRIM[line number],0)),"") -> Poplar PRIMED HEADER 5.25 x 0.875 | E9: =IFERROR(INDEX(TRIM[Sell/LF Margin],MATCH(InvoiceDetails7[[#This Row],[Description]],TRIM[Description],0)),"") -> 3.2480525 | F9: =IFERROR(INDEX(TRIM[Set Up Total],MATCH(InvoiceDetails7[[#This Row],[Description]],TRIM[Description],0)),"") -> 725 | G9: =IFERROR(INDEX(TRIM[LF Finish Add],MATCH(InvoiceDetails7[[#This Row],[Description]],TRIM[Description],0)),"") -> 1 | H9: =IF(InvoiceDetails7[[#This Row],[Description]]="","",(IFERROR(InvoiceDetails7[[#This Row],[LF Price]]*InvoiceDetails7[[#This Row],[Qty LF]]+InvoiceDetails7[[#This Row],[Set Up]],"")+IFERROR(InvoiceDetails7[[#This Row],[Finish LF Price]]*InvoiceDetails7[[#This Row],[Qty LF]],0))) -> 1317.6033 | K9: **Before an order is placed the builder will need to place an order requesting a specific number of sticks in specific lengths**
B10: 4 | C10: =IFERROR(INDEX(TRIM[Lin.Ft.],MATCH(InvoiceDetails7[[#This Row],[Description]],TRIM[Description],0)),"") -> 21 | D10: =IFERROR(INDEX(TRIM[Description],MATCH(InvoiceDetails7[[#This Row],[Line Number]],TRIM[line number],0)),"") -> Poplar PRIMED INT JAMB 4.75 x 0.75 | E10: =IFERROR(INDEX(TRIM[Sell/LF Margin],MATCH(InvoiceDetails7[[#This Row],[Description]],TRIM[Description],0)),"") -> 3.0116556 | F10: =IFERROR(INDEX(TRIM[Set Up Total],MATCH(InvoiceDetails7[[#This Row],[Description]],TRIM[Description],0)),"") -> 675 | G10: =IFERROR(INDEX(TRIM[LF Finish Add],MATCH(InvoiceDetails7[[#This Row],[Description]],TRIM[Description],0)),"") -> 1 | H10: =IF(InvoiceDetails7[[#This Row],[Description]]="","",(IFERROR(InvoiceDetails7[[#This Row],[LF Price]]*InvoiceDetails7[[#This Row],[Qty LF]]+InvoiceDetails7[[#This Row],[Set Up]],"")+IFERROR(InvoiceDetails7[[#This Row],[Finish LF Price]]*InvoiceDetails7[[#This Row],[Qty LF]],0))) -> 759.24477 | K10: **Unit price and finish price are LF numbers**
B11: 5 | C11: =IFERROR(INDEX(TRIM[Lin.Ft.],MATCH(InvoiceDetails7[[#This Row],[Description]],TRIM[Description],0)),"") -> 273 | D11: =IFERROR(INDEX(TRIM[Description],MATCH(InvoiceDetails7[[#This Row],[Line Number]],TRIM[line number],0)),"") -> Poplar PRIMED WINDOW JAMB 6 x 0.75 | E11: =IFERROR(INDEX(TRIM[Sell/LF Margin],MATCH(InvoiceDetails7[[#This Row],[Description]],TRIM[Description],0)),"") -> 3.4808125 | F11: =IFERROR(INDEX(TRIM[Set Up Total],MATCH(InvoiceDetails7[[#This Row],[Description]],TRIM[Description],0)),"") -> 800 | G11: =IFERROR(INDEX(TRIM[LF Finish Add],MATCH(InvoiceDetails7[[#This Row],[Description]],TRIM[Description],0)),"") -> 1.15 | H11: =IF(InvoiceDetails7[[#This Row],[Description]]="","",(IFERROR(InvoiceDetails7[[#This Row],[LF Price]]*InvoiceDetails7[[#This Row],[Qty LF]]+InvoiceDetails7[[#This Row],[Set Up]],"")+IFERROR(InvoiceDetails7[[#This Row],[Finish LF Price]]*InvoiceDetails7[[#This Row],[Qty LF]],0))) -> 2064.2118 | K11: **Finish price is driven by size of trim, and primed vs stained,FINAL PRICING PENDING ACTUAL DATA**
B12: 6 | C12: =IFERROR(INDEX(TRIM[Lin.Ft.],MATCH(InvoiceDetails7[[#This Row],[Description]],TRIM[Description],0)),"") -> 139.5 | D12: =IFERROR(INDEX(TRIM[Description],MATCH(InvoiceDetails7[[#This Row],[Line Number]],TRIM[line number],0)),"") -> Poplar PRIMED SILL 7.25 x 0.75 | E12: =IFERROR(INDEX(TRIM[Sell/LF Margin],MATCH(InvoiceDetails7[[#This Row],[Description]],TRIM[Description],0)),"") -> 3.8772319 | F12: =IFERROR(INDEX(TRIM[Set Up Total],MATCH(InvoiceDetails7[[#This Row],[Description]],TRIM[Description],0)),"") -> 925 | G12: =IFERROR(INDEX(TRIM[LF Finish Add],MATCH(InvoiceDetails7[[#This Row],[Description]],TRIM[Description],0)),"") -> 1.15 | H12: =IF(InvoiceDetails7[[#This Row],[Description]]="","",(IFERROR(InvoiceDetails7[[#This Row],[LF Price]]*InvoiceDetails7[[#This Row],[Qty LF]]+InvoiceDetails7[[#This Row],[Set Up]],"")+IFERROR(InvoiceDetails7[[#This Row],[Finish LF Price]]*InvoiceDetails7[[#This Row],[Qty LF]],0))) -> 1626.2988 | K12: **The final order will use the LF pricing on the quantity requested from the builder**
B13: 7 | C13: =IFERROR(INDEX(TRIM[Lin.Ft.],MATCH(InvoiceDetails7[[#This Row],[Description]],TRIM[Description],0)),"") -> 139.5 | D13: =IFERROR(INDEX(TRIM[Description],MATCH(InvoiceDetails7[[#This Row],[Line Number]],TRIM[line number],0)),"") -> Poplar PRIMED APRON 5.25 x 0.5 | E13: =IFERROR(INDEX(TRIM[Sell/LF Margin],MATCH(InvoiceDetails7[[#This Row],[Description]],TRIM[Description],0)),"") -> 3.2480525 | F13: =IFERROR(INDEX(TRIM[Set Up Total],MATCH(InvoiceDetails7[[#This Row],[Description]],TRIM[Description],0)),"") -> 725 | G13: =IFERROR(INDEX(TRIM[LF Finish Add],MATCH(InvoiceDetails7[[#This Row],[Description]],TRIM[Description],0)),"") -> 1 | H13: =IF(InvoiceDetails7[[#This Row],[Description]]="","",(IFERROR(InvoiceDetails7[[#This Row],[LF Price]]*InvoiceDetails7[[#This Row],[Qty LF]]+InvoiceDetails7[[#This Row],[Set Up]],"")+IFERROR(InvoiceDetails7[[#This Row],[Finish LF Price]]*InvoiceDetails7[[#This Row],[Qty LF]],0))) -> 1317.6033 | K13: **Set up fee is separate and based on knife and profile complexity**
B14: 8 | C14: =IFERROR(INDEX(TRIM[Lin.Ft.],MATCH(InvoiceDetails7[[#This Row],[Description]],TRIM[Description],0)),"") | D14: =IFERROR(INDEX(TRIM[Description],MATCH(InvoiceDetails7[[#This Row],[Line Number]],TRIM[line number],0)),"") | E14: =IFERROR(INDEX(TRIM[Sell/LF Margin],MATCH(InvoiceDetails7[[#This Row],[Description]],TRIM[Description],0)),"") | F14: =IFERROR(INDEX(TRIM[Set Up Total],MATCH(InvoiceDetails7[[#This Row],[Description]],TRIM[Description],0)),"") | G14: =IFERROR(INDEX(TRIM[LF Finish Add],MATCH(InvoiceDetails7[[#This Row],[Description]],TRIM[Description],0)),"") | H14: =IF(InvoiceDetails7[[#This Row],[Description]]="","",(IFERROR(InvoiceDetails7[[#This Row],[LF Price]]*InvoiceDetails7[[#This Row],[Qty LF]]+InvoiceDetails7[[#This Row],[Set Up]],"")+IFERROR(InvoiceDetails7[[#This Row],[Finish LF Price]]*InvoiceDetails7[[#This Row],[Qty LF]],0)))
B15: 9 | C15: =IFERROR(INDEX(TRIM[Lin.Ft.],MATCH(InvoiceDetails7[[#This Row],[Description]],TRIM[Description],0)),"") | D15: =IFERROR(INDEX(TRIM[Description],MATCH(InvoiceDetails7[[#This Row],[Line Number]],TRIM[line number],0)),"") | E15: =IFERROR(INDEX(TRIM[Sell/LF Margin],MATCH(InvoiceDetails7[[#This Row],[Description]],TRIM[Description],0)),"") | F15: =IFERROR(INDEX(TRIM[Set Up Total],MATCH(InvoiceDetails7[[#This Row],[Description]],TRIM[Description],0)),"") | G15: =IFERROR(INDEX(TRIM[LF Finish Add],MATCH(InvoiceDetails7[[#This Row],[Description]],TRIM[Description],0)),"") | H15: =IF(InvoiceDetails7[[#This Row],[Description]]="","",(IFERROR(InvoiceDetails7[[#This Row],[LF Price]]*InvoiceDetails7[[#This Row],[Qty LF]]+InvoiceDetails7[[#This Row],[Set Up]],"")+IFERROR(InvoiceDetails7[[#This Row],[Finish LF Price]]*InvoiceDetails7[[#This Row],[Qty LF]],0)))
B16: 10 | C16: =IFERROR(INDEX(TRIM[Lin.Ft.],MATCH(InvoiceDetails7[[#This Row],[Description]],TRIM[Description],0)),"") | D16: =IFERROR(INDEX(TRIM[Description],MATCH(InvoiceDetails7[[#This Row],[Line Number]],TRIM[line number],0)),"") | E16: =IFERROR(INDEX(TRIM[Sell/LF Margin],MATCH(InvoiceDetails7[[#This Row],[Description]],TRIM[Description],0)),"") | F16: =IFERROR(INDEX(TRIM[Set Up Total],MATCH(InvoiceDetails7[[#This Row],[Description]],TRIM[Description],0)),"") | G16: =IFERROR(INDEX(TRIM[LF Finish Add],MATCH(InvoiceDetails7[[#This Row],[Description]],TRIM[Description],0)),"") | H16: =IF(InvoiceDetails7[[#This Row],[Description]]="","",(IFERROR(InvoiceDetails7[[#This Row],[LF Price]]*InvoiceDetails7[[#This Row],[Qty LF]]+InvoiceDetails7[[#This Row],[Set Up]],"")+IFERROR(InvoiceDetails7[[#This Row],[Finish LF Price]]*InvoiceDetails7[[#This Row],[Qty LF]],0)))
B17: 11 | C17: =IFERROR(INDEX(TRIM[Lin.Ft.],MATCH(InvoiceDetails7[[#This Row],[Description]],TRIM[Description],0)),"") | D17: =IFERROR(INDEX(TRIM[Description],MATCH(InvoiceDetails7[[#This Row],[Line Number]],TRIM[line number],0)),"") | E17: =IFERROR(INDEX(TRIM[Sell/LF Margin],MATCH(InvoiceDetails7[[#This Row],[Description]],TRIM[Description],0)),"") | F17: =IFERROR(INDEX(TRIM[Set Up Total],MATCH(InvoiceDetails7[[#This Row],[Description]],TRIM[Description],0)),"") | G17: =IFERROR(INDEX(TRIM[LF Finish Add],MATCH(InvoiceDetails7[[#This Row],[Description]],TRIM[Description],0)),"") | H17: =IF(InvoiceDetails7[[#This Row],[Description]]="","",(IFERROR(InvoiceDetails7[[#This Row],[LF Price]]*InvoiceDetails7[[#This Row],[Qty LF]]+InvoiceDetails7[[#This Row],[Set Up]],"")+IFERROR(InvoiceDetails7[[#This Row],[Finish LF Price]]*InvoiceDetails7[[#This Row],[Qty LF]],0)))
B18: 12 | C18: =IFERROR(INDEX(TRIM[Lin.Ft.],MATCH(InvoiceDetails7[[#This Row],[Description]],TRIM[Description],0)),"") | D18: =IFERROR(INDEX(TRIM[Description],MATCH(InvoiceDetails7[[#This Row],[Line Number]],TRIM[line number],0)),"") | E18: =IFERROR(INDEX(TRIM[Sell/LF Margin],MATCH(InvoiceDetails7[[#This Row],[Description]],TRIM[Description],0)),"") | F18: =IFERROR(INDEX(TRIM[Set Up Total],MATCH(InvoiceDetails7[[#This Row],[Description]],TRIM[Description],0)),"") | G18: =IFERROR(INDEX(TRIM[LF Finish Add],MATCH(InvoiceDetails7[[#This Row],[Description]],TRIM[Description],0)),"") | H18: =IF(InvoiceDetails7[[#This Row],[Description]]="","",(IFERROR(InvoiceDetails7[[#This Row],[LF Price]]*InvoiceDetails7[[#This Row],[Qty LF]]+InvoiceDetails7[[#This Row],[Set Up]],"")+IFERROR(InvoiceDetails7[[#This Row],[Finish LF Price]]*InvoiceDetails7[[#This Row],[Qty LF]],0)))
B19: 13 | C19: =IFERROR(INDEX(TRIM[Lin.Ft.],MATCH(InvoiceDetails7[[#This Row],[Description]],TRIM[Description],0)),"") | D19: =IFERROR(INDEX(TRIM[Description],MATCH(InvoiceDetails7[[#This Row],[Line Number]],TRIM[line number],0)),"") | E19: =IFERROR(INDEX(TRIM[Sell/LF Margin],MATCH(InvoiceDetails7[[#This Row],[Description]],TRIM[Description],0)),"") | F19: =IFERROR(INDEX(TRIM[Set Up Total],MATCH(InvoiceDetails7[[#This Row],[Description]],TRIM[Description],0)),"") | G19: =IFERROR(INDEX(TRIM[LF Finish Add],MATCH(InvoiceDetails7[[#This Row],[Description]],TRIM[Description],0)),"") | H19: =IF(InvoiceDetails7[[#This Row],[Description]]="","",(IFERROR(InvoiceDetails7[[#This Row],[LF Price]]*InvoiceDetails7[[#This Row],[Qty LF]]+InvoiceDetails7[[#This Row],[Set Up]],"")+IFERROR(InvoiceDetails7[[#This Row],[Finish LF Price]]*InvoiceDetails7[[#This Row],[Qty LF]],0)))
B20: 14 | C20: =IFERROR(INDEX(TRIM[Lin.Ft.],MATCH(InvoiceDetails7[[#This Row],[Description]],TRIM[Description],0)),"") | D20: =IFERROR(INDEX(TRIM[Description],MATCH(InvoiceDetails7[[#This Row],[Line Number]],TRIM[line number],0)),"") | E20: =IFERROR(INDEX(TRIM[Sell/LF Margin],MATCH(InvoiceDetails7[[#This Row],[Description]],TRIM[Description],0)),"") | F20: =IFERROR(INDEX(TRIM[Set Up Total],MATCH(InvoiceDetails7[[#This Row],[Description]],TRIM[Description],0)),"") | G20: =IFERROR(INDEX(TRIM[LF Finish Add],MATCH(InvoiceDetails7[[#This Row],[Description]],TRIM[Description],0)),"") | H20: =IF(InvoiceDetails7[[#This Row],[Description]]="","",(IFERROR(InvoiceDetails7[[#This Row],[LF Price]]*InvoiceDetails7[[#This Row],[Qty LF]]+InvoiceDetails7[[#This Row],[Set Up]],"")+IFERROR(InvoiceDetails7[[#This Row],[Finish LF Price]]*InvoiceDetails7[[#This Row],[Qty LF]],0)))
B21: 15 | C21: =IFERROR(INDEX(TRIM[Lin.Ft.],MATCH(InvoiceDetails7[[#This Row],[Description]],TRIM[Description],0)),"") | D21: =IFERROR(INDEX(TRIM[Description],MATCH(InvoiceDetails7[[#This Row],[Line Number]],TRIM[line number],0)),"") | E21: =IFERROR(INDEX(TRIM[Sell/LF Margin],MATCH(InvoiceDetails7[[#This Row],[Description]],TRIM[Description],0)),"") | F21: =IFERROR(INDEX(TRIM[Set Up Total],MATCH(InvoiceDetails7[[#This Row],[Description]],TRIM[Description],0)),"") | G21: =IFERROR(INDEX(TRIM[LF Finish Add],MATCH(InvoiceDetails7[[#This Row],[Description]],TRIM[Description],0)),"") | H21: =IF(InvoiceDetails7[[#This Row],[Description]]="","",(IFERROR(InvoiceDetails7[[#This Row],[LF Price]]*InvoiceDetails7[[#This Row],[Qty LF]]+InvoiceDetails7[[#This Row],[Set Up]],"")+IFERROR(InvoiceDetails7[[#This Row],[Finish LF Price]]*InvoiceDetails7[[#This Row],[Qty LF]],0)))
B22: 16 | C22: =IFERROR(INDEX(TRIM[Lin.Ft.],MATCH(InvoiceDetails7[[#This Row],[Description]],TRIM[Description],0)),"") | D22: =IFERROR(INDEX(TRIM[Description],MATCH(InvoiceDetails7[[#This Row],[Line Number]],TRIM[line number],0)),"") | E22: =IFERROR(INDEX(TRIM[Sell/LF Margin],MATCH(InvoiceDetails7[[#This Row],[Description]],TRIM[Description],0)),"") | F22: =IFERROR(INDEX(TRIM[Set Up Total],MATCH(InvoiceDetails7[[#This Row],[Description]],TRIM[Description],0)),"") | G22: =IFERROR(INDEX(TRIM[LF Finish Add],MATCH(InvoiceDetails7[[#This Row],[Description]],TRIM[Description],0)),"") | H22: =IF(InvoiceDetails7[[#This Row],[Description]]="","",(IFERROR(InvoiceDetails7[[#This Row],[LF Price]]*InvoiceDetails7[[#This Row],[Qty LF]]+InvoiceDetails7[[#This Row],[Set Up]],"")+IFERROR(InvoiceDetails7[[#This Row],[Finish LF Price]]*InvoiceDetails7[[#This Row],[Qty LF]],0)))
B23: 17 | C23: =IFERROR(INDEX(TRIM[Lin.Ft.],MATCH(InvoiceDetails7[[#This Row],[Description]],TRIM[Description],0)),"") | D23: =IFERROR(INDEX(TRIM[Description],MATCH(InvoiceDetails7[[#This Row],[Line Number]],TRIM[line number],0)),"") | E23: =IFERROR(INDEX(TRIM[Sell/LF Margin],MATCH(InvoiceDetails7[[#This Row],[Description]],TRIM[Description],0)),"") | F23: =IFERROR(INDEX(TRIM[Set Up Total],MATCH(InvoiceDetails7[[#This Row],[Description]],TRIM[Description],0)),"") | G23: =IFERROR(INDEX(TRIM[LF Finish Add],MATCH(InvoiceDetails7[[#This Row],[Description]],TRIM[Description],0)),"") | H23: =IF(InvoiceDetails7[[#This Row],[Description]]="","",(IFERROR(InvoiceDetails7[[#This Row],[LF Price]]*InvoiceDetails7[[#This Row],[Qty LF]]+InvoiceDetails7[[#This Row],[Set Up]],"")+IFERROR(InvoiceDetails7[[#This Row],[Finish LF Price]]*InvoiceDetails7[[#This Row],[Qty LF]],0)))
B24: 18 | C24: =IFERROR(INDEX(TRIM[Lin.Ft.],MATCH(InvoiceDetails7[[#This Row],[Description]],TRIM[Description],0)),"") | D24: =IFERROR(INDEX(TRIM[Description],MATCH(InvoiceDetails7[[#This Row],[Line Number]],TRIM[line number],0)),"") | E24: =IFERROR(INDEX(TRIM[Sell/LF Margin],MATCH(InvoiceDetails7[[#This Row],[Description]],TRIM[Description],0)),"") | F24: =IFERROR(INDEX(TRIM[Set Up Total],MATCH(InvoiceDetails7[[#This Row],[Description]],TRIM[Description],0)),"") | G24: =IFERROR(INDEX(TRIM[LF Finish Add],MATCH(InvoiceDetails7[[#This Row],[Description]],TRIM[Description],0)),"") | H24: =IF(InvoiceDetails7[[#This Row],[Description]]="","",(IFERROR(InvoiceDetails7[[#This Row],[LF Price]]*InvoiceDetails7[[#This Row],[Qty LF]]+InvoiceDetails7[[#This Row],[Set Up]],"")+IFERROR(InvoiceDetails7[[#This Row],[Finish LF Price]]*InvoiceDetails7[[#This Row],[Qty LF]],0)))
B25: 19 | C25: =IFERROR(INDEX(TRIM[Lin.Ft.],MATCH(InvoiceDetails7[[#This Row],[Description]],TRIM[Description],0)),"") | D25: =IFERROR(INDEX(TRIM[Description],MATCH(InvoiceDetails7[[#This Row],[Line Number]],TRIM[line number],0)),"") | E25: =IFERROR(INDEX(TRIM[Sell/LF Margin],MATCH(InvoiceDetails7[[#This Row],[Description]],TRIM[Description],0)),"") | F25: =IFERROR(INDEX(TRIM[Set Up Total],MATCH(InvoiceDetails7[[#This Row],[Description]],TRIM[Description],0)),"") | G25: =IFERROR(INDEX(TRIM[LF Finish Add],MATCH(InvoiceDetails7[[#This Row],[Description]],TRIM[Description],0)),"") | H25: =IF(InvoiceDetails7[[#This Row],[Description]]="","",(IFERROR(InvoiceDetails7[[#This Row],[LF Price]]*InvoiceDetails7[[#This Row],[Qty LF]]+InvoiceDetails7[[#This Row],[Set Up]],"")+IFERROR(InvoiceDetails7[[#This Row],[Finish LF Price]]*InvoiceDetails7[[#This Row],[Qty LF]],0)))
... B31: 25 | C31: =IFERROR(INDEX(TRIM[Lin.Ft.],MATCH(InvoiceDetails7[[#This Row],[Description]],TRIM[Description],0)),"") | D31: =IFERROR(INDEX(TRIM[Description],MATCH(InvoiceDetails7[[#This Row],[Line Number]],TRIM[line number],0)),"") | E31: =IFERROR(INDEX(TRIM[Sell/LF Margin],MATCH(InvoiceDetails7[[#This Row],[Description]],TRIM[Description],0)),"") | F31: =IFERROR(INDEX(TRIM[Set Up Total],MATCH(InvoiceDetails7[[#This Row],[Description]],TRIM[Description],0)),"") | G31: =IFERROR(INDEX(TRIM[LF Finish Add],MATCH(InvoiceDetails7[[#This Row],[Description]],TRIM[Description],0)),"") | H31: =IF(InvoiceDetails7[[#This Row],[Description]]="","",(IFERROR(InvoiceDetails7[[#This Row],[LF Price]]*InvoiceDetails7[[#This Row],[Qty LF]]+InvoiceDetails7[[#This Row],[Set Up]],"")+IFERROR(InvoiceDetails7[[#This Row],[Finish LF Price]]*InvoiceDetails7[[#This Row],[Qty LF]],0)))
G32: =IF('Trim Take Off'!C20="","",'Trim Take Off'!C20) -> Poplar | H32: =IF(G32="","",SUMIFS(InvoiceDetails7[Line Total],InvoiceDetails7[Description],"*"&G32&"*")) -> 12332.947 | K32: **Double check unit price, if we don't have pricing data in the price data table it will not be correct**
G33: =IF('Trim Take Off'!C21="","",'Trim Take Off'!C21) | H33: =IF(G33="","",SUMIFS(InvoiceDetails7[Line Total],InvoiceDetails7[Description],"*"&G33&"*"))
G34: =IF('Trim Take Off'!C22="","",'Trim Take Off'!C22) | H34: =IF(G34="","",SUMIFS(InvoiceDetails7[Line Total],InvoiceDetails7[Description],"*"&G34&"*"))
G35: Total | H35: =H34+H32 -> #VALUE!

Sheet Hardwood Price Data
L1: **10' UON** | O1: BASE | P1: CASE | Q1: HEADER | R1: INT JAMB | S1: WINDOW JAMB | T1: SILL | U1: APRON | V1: DENTIL
C2: Species | D2: 1 | E2: 1.25 | F2: 1.5 | G2: 2 | H2: 1 sorted | I2: 1.25 sorted | J2: 1.5 sorted | K2: 2 sorted | N2: STANDARD WIDTH | O2: 5.25 | P2: 3.25 | Q2: 5.25 | R2: 4.75 | S2: 6 | T2: 7.25 | U2: =O2 -> 5.25 | V2: 1.5
C3: Knotty Alder | D3: 1.25 | H3: 2.15 | N3: STANDARD THICKNESS | O3: 0.5 | P3: 0.625 | Q3: 0.875 | R3: 0.75 | S3: 0.75 | T3: 0.75 | U3: =O3 -> 0.5 | V3: 0.5
C4: Superior Alder | D4: 4.25 | H4: 5 | N4: ECONOMY WIDTH | O4: 2.25 | P4: 3.25 | Q4: 4.25 | R4: 4.75 | S4: 6 | T4: 7.25 | U4: =O4 -> 2.25
C5: Poplar | D5: 2.3 | H5: 2.3 | N5: ECONOMY THICKNESS | O5: 0.5 | P5: 0.625 | Q5: 0.75 | R5: 0.75 | S5: 0.75 | T5: 0.75 | U5: =O5 -> 0.5
C6: Rift White Oak | D6: 11 | E6: 12.2 | F6: 12.2 | H6: 11 | N6: UPGRADE WIDTH | O6: 7 | P6: 4.25 | Q6: 7 | R6: 4.75 | S6: 6 | T6: 7.25 | U6: =O6 -> 7 | V6: 2
C7: PS White Oak | D7: 6.8 | E7: 7.6 | F7: 8 | H7: 6.8 | N7: UPGRADED THICKNESS | O7: 0.75 | P7: 1 | Q7: 1.125 | R7: 0.75 | S7: 0.75 | T7: 0.75 | U7: =O7 -> 0.75 | V7: 0.75
C8: Rift Red Oak
C9: PS Red Oak
C10: Walnut
C11: Maple
C12: Cherry
C13: Hickory
A14: VG Fir
A15: Sapele Mahog.
A16: 1/4 White Oak
A17: Knotty Pine
A18: Clear Pine
A19: Hemlock
A20: Birch / Natural
A21: Birch / White
A22: Ash
A23: Wormy maple
A24: K Fir mixed tight
A25: Beech
C26: MDF

Sheet LookUps
E2: 0
E3: 4/4 | F3: 5/4 | G3: 6/4 | H3: 8/4 | AA3: DOOR HEIGHT | AB3: YN | AC3: FINISH LEVEL | AD3: STYLE | AE3: PROFILE
D4: RIP SIZE | E4: 4/4 | F4: 5/4 | G4: 6/4 | H4: 8/4 | R4: Finish | S4: Rough | U4: Finish | V4: Rate | W4: Help | Y4: Type | AA4: 80 | AB4: YES | AC4: STANDARD | AD4: CRAFTSMAN | AE4: E2E
D5: 0.75 | E5: =K5*(1+$E$2) -> 0.111 | F5: =L5*(1+$E$2) -> 0.138 | G5: =M5*(1+$E$2) -> 0.166 | H5: =N5*(1+$E$2) -> 0.222 | K5: 0.111 | L5: 0.138 | M5: 0.166 | N5: 0.222 | R5: 0 | S5: 1 | U5: Primed Small | V5: 0.85 | W5: Primed | Y5: Base | AA5: 84 | AB5: NO | AC5: ECONOMY | AD5: CRAFTSMAN PLUS | AE5: CUSTOM
D6: 1 | E6: =K6*(1+$E$2) -> 0.148 | F6: =L6*(1+$E$2) -> 0.185 | G6: =M6*(1+$E$2) -> 0.222 | H6: =N6*(1+$E$2) -> 0.295 | K6: 0.148 | L6: 0.185 | M6: 0.222 | N6: 0.295 | R6: 1 | S6: 1.25 | U6: Primed Avg | V6: 1 | W6: Primed | Y6: Case | AA6: 96 | AC6: UPGRADED | AD6: MITERED | AE6: BOOK
D7: 1.125 | E7: =K7*(1+$E$2) -> 0.12551985 | F7: =L7*(1+$E$2) -> 0.208 | G7: =M7*(1+$E$2) -> 0.249 | H7: =N7*(1+$E$2) -> 0.332 | K7: 0.12551985 | L7: 0.208 | M7: 0.249 | N7: 0.332 | R7: 1.25 | S7: 1.5 | U7: Primed Large | V7: 1.15 | W7: Primed | Y7: Header | AC7: CUSTOM
D8: 1.25 | E8: =K8*(1+$E$2) -> 0.185 | F8: =L8*(1+$E$2) -> 0.231 | G8: =M8*(1+$E$2) -> 0.277 | H8: =N8*(1+$E$2) -> 0.369 | K8: 0.185 | L8: 0.231 | M8: 0.277 | N8: 0.369 | R8: 1.5 | S8: 2 | U8: Stained Small | V8: 2 | W8: Stained | Y8: Int Jamb
D9: 1.375 | E9: =K9*(1+$E$2) -> 0.203 | F9: =L9*(1+$E$2) -> 0.254 | G9: =M9*(1+$E$2) -> 0.305 | H9: =N9*(1+$E$2) -> 0.406 | K9: 0.203 | L9: 0.254 | M9: 0.305 | N9: 0.406 | R9: 2 | S9: CHECK | U9: Stained Avg | V9: 2.25 | W9: Stained | Y9: Ext Jamb
D10: 1.5 | E10: =K10*(1+$E$2) -> 0.222 | F10: =L10*(1+$E$2) -> 0.277 | G10: =M10*(1+$E$2) -> 0.332 | H10: =N10*(1+$E$2) -> 0.443 | K10: 0.222 | L10: 0.277 | M10: 0.332 | N10: 0.443 | U10: Stained Large | V10: 2.5 | W10: Stained | Y10: Sill
D11: 1.625 | E11: =K11*(1+$E$2) -> 0.24 | F11: =L11*(1+$E$2) -> 0.3 | G11: =M11*(1+$E$2) -> 0.36 | H11: =N11*(1+$E$2) -> 0.48 | K11: 0.24 | L11: 0.3 | M11: 0.36 | N11: 0.48 | V11: 0 | Y11: Apron
D12: 1.75 | E12: =K12*(1+$E$2) -> 0.258 | F12: =L12*(1+$E$2) -> 0.323 | G12: =M12*(1+$E$2) -> 0.388 | H12: =N12*(1+$E$2) -> 0.517 | K12: 0.258 | L12: 0.323 | M12: 0.388 | N12: 0.517 | Y12: DENTIL
D13: 1.875 | E13: =K13*(1+$E$2) -> 0.277 | F13: =L13*(1+$E$2) -> 0.346 | G13: =M13*(1+$E$2) -> 0.415 | H13: =N13*(1+$E$2) -> 0.554 | K13: 0.277 | L13: 0.346 | M13: 0.415 | N13: 0.554
D14: 2 | E14: =K14*(1+$E$2) -> 0.28 | F14: =L14*(1+$E$2) -> 0.351 | G14: =M14*(1+$E$2) -> 0.421 | H14: =N14*(1+$E$2) -> 0.561 | K14: 0.28 | L14: 0.351 | M14: 0.421 | N14: 0.561
D15: 2.125 | E15: =K15*(1+$E$2) -> 0.285 | F15: =L15*(1+$E$2) -> 0.356 | G15: =M15*(1+$E$2) -> 0.427 | H15: =N15*(1+$E$2) -> 0.569 | K15: 0.285 | L15: 0.356 | M15: 0.427 | N15: 0.569
D16: 2.25 | E16: =K16*(1+$E$2) -> 0.301 | F16: =L16*(1+$E$2) -> 0.377 | G16: =M16*(1+$E$2) -> 0.452 | H16: =N16*(1+$E$2) -> 0.603 | K16: 0.301 | L16: 0.377 | M16: 0.452 | N16: 0.603
D17: 2.375 | E17: =K17*(1+$E$2) -> 0.318 | F17: =L17*(1+$E$2) -> 0.397 | G17: =M17*(1+$E$2) -> 0.477 | H17: =N17*(1+$E$2) -> 0.636 | K17: 0.318 | L17: 0.397 | M17: 0.477 | N17: 0.636
D18: 2.5 | E18: =K18*(1+$E$2) -> 0.335 | F18: =L18*(1+$E$2) -> 0.418 | G18: =M18*(1+$E$2) -> 0.502 | H18: =N18*(1+$E$2) -> 0.669 | K18: 0.335 | L18: 0.418 | M18: 0.502 | N18: 0.669 | T18: primed small | U18: =INDEX(finish[Help],MATCH(T18,finish[Finish],0)) -> Primed
D19: 2.625 | E19: =K19*(1+$E$2) -> 0.351 | F19: =L19*(1+$E$2) -> 0.439 | G19: =M19*(1+$E$2) -> 0.527 | H19: =N19*(1+$E$2) -> 0.703 | K19: 0.351 | L19: 0.439 | M19: 0.527 | N19: 0.703
D20: 2.75 | E20: =K20*(1+$E$2) -> 0.368 | F20: =L20*(1+$E$2) -> 0.46 | G20: =M20*(1+$E$2) -> 0.552 | H20: =N20*(1+$E$2) -> 0.736 | K20: 0.368 | L20: 0.46 | M20: 0.552 | N20: 0.736
D21: 2.875 | E21: =K21*(1+$E$2) -> 0.385 | F21: =L21*(1+$E$2) -> 0.481 | G21: =M21*(1+$E$2) -> 0.577 | H21: =N21*(1+$E$2) -> 0.77 | K21: 0.385 | L21: 0.481 | M21: 0.577 | N21: 0.77
D22: 3 | E22: =K22*(1+$E$2) -> 0.402 | F22: =L22*(1+$E$2) -> 0.502 | G22: =M22*(1+$E$2) -> 0.603 | H22: =N22*(1+$E$2) -> 0.803 | K22: 0.402 | L22: 0.502 | M22: 0.603 | N22: 0.803
D23: 3.125 | E23: =K23*(1+$E$2) -> 0.418 | F23: =L23*(1+$E$2) -> 0.523 | G23: =M23*(1+$E$2) -> 0.628 | H23: =N23*(1+$E$2) -> 0.837 | K23: 0.418 | L23: 0.523 | M23: 0.628 | N23: 0.837
D24: 3.25 | E24: =K24*(1+$E$2) -> 0.435 | F24: =L24*(1+$E$2) -> 0.544 | G24: =M24*(1+$E$2) -> 0.653 | H24: =N24*(1+$E$2) -> 0.87 | K24: 0.435 | L24: 0.544 | M24: 0.653 | N24: 0.87
D25: 3.375 | E25: =K25*(1+$E$2) -> 0.452 | F25: =L25*(1+$E$2) -> 0.565 | G25: =M25*(1+$E$2) -> 0.678 | H25: =N25*(1+$E$2) -> 0.904 | K25: 0.452 | L25: 0.565 | M25: 0.678 | N25: 0.904
D26: 3.5 | E26: =K26*(1+$E$2) -> 0.469 | F26: =L26*(1+$E$2) -> 0.586 | G26: =M26*(1+$E$2) -> 0.703 | H26: =N26*(1+$E$2) -> 0.937 | K26: 0.469 | L26: 0.586 | M26: 0.703 | N26: 0.937
D27: 3.625 | E27: =K27*(1+$E$2) -> 0.485 | F27: =L27*(1+$E$2) -> 0.607 | G27: =M27*(1+$E$2) -> 0.728 | H27: =N27*(1+$E$2) -> 0.971 | K27: 0.485 | L27: 0.607 | M27: 0.728 | N27: 0.971
D28: 3.75 | E28: =K28*(1+$E$2) -> 0.502 | F28: =L28*(1+$E$2) -> 0.628 | G28: =M28*(1+$E$2) -> 0.753 | H28: =N28*(1+$E$2) -> 1.004 | K28: 0.502 | L28: 0.628 | M28: 0.753 | N28: 1.004
D29: 3.875 | E29: =K29*(1+$E$2) -> 0.519 | F29: =L29*(1+$E$2) -> 0.649 | G29: =M29*(1+$E$2) -> 0.778 | H29: =N29*(1+$E$2) -> 1.038 | K29: 0.519 | L29: 0.649 | M29: 0.778 | N29: 1.038
D30: 4 | E30: =K30*(1+$E$2) -> 0.529 | F30: =L30*(1+$E$2) -> 0.661 | G30: =M30*(1+$E$2) -> 0.793 | H30: =N30*(1+$E$2) -> 1.058 | K30: 0.529 | L30: 0.661 | M30: 0.793 | N30: 1.058
... D42: 7 | E42: =K42*(1+$E$2) -> 0.787 | F42: =L42*(1+$E$2) -> 0.984 | G42: =M42*(1+$E$2) -> 1.181 | H42: =N42*(1+$E$2) -> 1.574 | K42: 0.787 | L42: 0.984 | M42: 1.181 | N42: 1.574
D43: 7.25 | E43: =K43*(1+$E$2) -> 0.809 | F43: =L43*(1+$E$2) -> 1.011 | G43: =M43*(1+$E$2) -> 1.213 | H43: =N43*(1+$E$2) -> 1.617 | K43: 0.809 | L43: 1.011 | M43: 1.213 | N43: 1.617 | Q43: `
D44: 7.5 | E44: =K44*(1+$E$2) -> 0.829 | F44: =L44*(1+$E$2) -> 1.036 | G44: =M44*(1+$E$2) -> 1.243 | H44: =N44*(1+$E$2) -> 1.657 | K44: 0.829 | L44: 1.036 | M44: 1.243 | N44: 1.657
D45: 7.75 | E45: =K45*(1+$E$2) -> 0.851 | F45: =L45*(1+$E$2) -> 1.063 | G45: =M45*(1+$E$2) -> 1.276 | H45: =N45*(1+$E$2) -> 1.701 | K45: 0.851 | L45: 1.063 | M45: 1.276 | N45: 1.701
D46: 8 | E46: =K46*(1+$E$2) -> 0.872 | F46: =L46*(1+$E$2) -> 1.09 | G46: =M46*(1+$E$2) -> 1.309 | H46: =N46*(1+$E$2) -> 1.745 | K46: 0.872 | L46: 1.09 | M46: 1.309 | N46: 1.745
D47: 8.25 | E47: =K47*(1+$E$2) -> 0.888 | F47: =L47*(1+$E$2) -> 1.11 | G47: =M47*(1+$E$2) -> 1.332 | H47: =N47*(1+$E$2) -> 1.776 | K47: 0.888 | L47: 1.11 | M47: 1.332 | N47: 1.776
D48: 8.5 | E48: =K48*(1+$E$2) -> 0.915 | F48: =L48*(1+$E$2) -> 1.144 | G48: =M48*(1+$E$2) -> 1.372 | H48: =N48*(1+$E$2) -> 1.83 | K48: 0.915 | L48: 1.144 | M48: 1.372 | N48: 1.83
D49: 8.75 | E49: =K49*(1+$E$2) -> 0.936 | F49: =L49*(1+$E$2) -> 1.17 | G49: =M49*(1+$E$2) -> 1.404 | H49: =N49*(1+$E$2) -> 1.872 | K49: 0.936 | L49: 1.17 | M49: 1.404 | N49: 1.872
D50: 9 | E50: =K50*(1+$E$2) -> 0.963 | F50: =L50*(1+$E$2) -> 1.203 | G50: =M50*(1+$E$2) -> 1.444 | H50: =N50*(1+$E$2) -> 1.925 | K50: 0.963 | L50: 1.203 | M50: 1.444 | N50: 1.925
